Workbook

Sheet COA
A1: Kode Akun | B1: Nama Akun | D1: Kode Akun | E1: Nama Akun
A2: Aset Lancar
A3: Kas & Bank | D3: Aset Lancar
A4: 1101 | B4: Kas | D4: 1101 | E4: Kas Kecil
A5: 1102 | B5: BRI 562 | D5: 1102 | E5: BRI 562
A6: 1103 | B6: BRI 568 | D6: 1103 | E6: BRI 568 | F6: Giro
A7: 1104 | B7: BRI 309 (Giro) | D7: 1104 | E7: Rekening Owner
A8: 1105 | B8: BTN 041 (Giro) | D8: 1105 | E8: Rekening Bapak Owner
A9: 1106 | B9: BNI 084 (Giro) | D9: 1103 | E9: Deposito Jangka Pendek
A10: 1107 | B10: Mandiri 669 (Giro) | D10: 1104 | E10: Piutang Usaha
A11: 1108 | B11: Rekening Owner | D11: 1105 | E11: Piutang Afiliasi
A12: 1109 | B12: BRI 560 | D12: 1105 | E12: Piutang Afiliasi
A13: Piutang | D13: 1106 | E13: Piutang Lain-lain
A14: 1201 | B14: Deposito Jangka Pendek | D14: 1107 | E14: Uang Muka Pembelian Tanah
A15: 1202 | B15: Piutang Usaha | D15: 1108 | E15: Persediaan Tanah dalam Pengembangan
A16: 1203 | B16: Piutang Afiliasi | D16: 1109 | E16: Persediaan Bangunan dalam Proses
A17: 1204 | B17: Piutang Lain-lain | D17: 1110 | E17: Persediaan Properti Siap Jual
A18: 1205 | B18: Uang Muka Pembelian Tanah | D18: 1111 | E18: Pajak Dibayar di Muka
A19: 1206 | B19: Uang Muka Pembelian Konveksi | D19: 1112 | E19: Biaya Dibayar di Muka
A20: 1207 | B20: Pajak Dibayar di Muka | D20: Jumlah Aset Lancar
A21: 1208 | B21: Biaya Dibayar di Muka | D21: Aset Tidak Lancar
A22: Persediaan | D22: 1201 | E22: Tanah dan Bangunan Investasi
A23: 1301 | B23: Persediaan Tanah dalam Pengembangan | D23: 1202 | E23: Gedung Kantor
A24: 1302 | B24: Persediaan Bangunan dalam Proses | D24: 1203 | E24: Akumulasi Penyusutan Gedung
A25: 1303 | B25: Persediaan Properti Siap Jual | D25: 1204 | E25: Peralatan dan Mesin | F25: inv kantor
A26: 1304 | B26: Persediaan Bahan Baku | D26: 1205 | E26: Akumulasi Penyusutan Peralatan
A27: 1305 | B27: Persediaan Barang dalam Proses | D27: 1206 | E27: Kendaraan Operasional
A28: 1306 | B28: Persediaan Barang Jadi | D28: 1207 | E28: Akumulasi Penyusutan Kendaraan
A29: Aset Tidak Lancar | D29: 1208 | E29: Aset Dalam Penyelesaian
A30: 1401 | B30: Tanah dan Bangunan Investasi | D30: 1209 | E30: Investasi Jangka Panjang
A31: 1402 | B31: Gedung Kantor | D31: 1210 | E31: Aset Tak Berwujud
A32: 1403 | B32: Akumulasi Penyusutan Gedung | D32: Jumlah Aset Tidak Lancar
A33: 1404 | B33: Peralatan dan Mesin | D33: Kewajiban Lancar
A34: 1405 | B34: Akumulasi Penyusutan Peralatan | D34: 2101 | E34: Hutang Usaha
A35: 1406 | B35: Kendaraan Operasional | D35: 2102 | E35: Hutang Pajak
A36: 1407 | B36: Akumulasi Penyusutan Kendaraan | D36: 2103 | E36: Hutang Subkon
A37: 1408 | B37: Inventaris Kantor | D37: 2103 | E37: Hutang Gaji
A38: 1409 | B38: Akumulasi Penyusutan Inventaris Kantor | D38: 2104 | E38: Hutang Bunga
A39: 1410 | B39: Aset Dalam Penyelesaian | D39: 2105 | E39: Uang Muka Penjualan Properti | F39: Afiliasi
A40: 1411 | B40: Investasi Jangka Panjang | D40: 2106 | E40: Biaya yang Masih Harus Dibayar
A41: 1412 | B41: Aset Tak Berwujud | D41: 2107 | E41: Hutang Jangka Pendek ke Bank
A42: Kewajiban Lancar | D42: Jumlah Kewajiban Lancar
A43: 2101 | B43: Hutang Usaha | D43: Kewajiban Jangka Panjang
A44: 2102 | B44: Hutang Pajak | D44: 2201 | E44: Hutang Bank Jangka Panjang
A45: 2103 | B45: Hutang Subkon | D45: 2202 | E45: Hutang Obligasi
A46: 2104 | B46: Hutang Bunga | D46: 2203 | E46: Hutang Pembiayaan Leasing
A47: 2105 | B47: Uang Muka Penjualan Properti | D47: 2204 | E47: Liabilitas Imbalan Kerja
A48: 2106 | B48: Uang Muka Penjualan Konveksi | D48: Jumlah Kewajiban Jangka Panjang
A49: 2107 | B49: Biaya yang Masih Harus Dibayar | D49: Ekuitas
A50: 2108 | B50: Hutang Jangka Pendek ke Bank | D50: 3101 | E50: Modal Disetor
A51: Kewajiban Jangka Panjang | D51: 3102 | E51: Tambahan Modal Disetor
A52: 2201 | B52: Hutang Bank Jangka Panjang | D52: 3103 | E52: Laba Ditahan
A53: 2202 | B53: Hutang Obligasi | D53: 3104 | E53: Laba Tahun Berjalan
A54: 2203 | B54: Hutang Pembiayaan Leasing | D54: 3105 | E54: Dividen
A55: 2204 | B55: Hutang Afiliasi | D55: Jumlah Ekuitas
A56: 2205 | B56: Liabilitas Imbalan Kerja | D56: Pendapatan
A57: Ekuitas | D57: 4101 | E57: Pendapatan Penjualan Tanah
A58: 3101 | B58: Modal Disetor | D58: 4102 | E58: Pendapatan Penjualan Rumah
A59: 3102 | B59: Tambahan Modal Disetor | D59: 4103 | E59: Pendapatan Penjualan Ruko/Apartemen
A60: 3103 | B60: Laba Ditahan | D60: 4104 | E60: Pendapatan Jasa Konstruksi
A61: 3104 | B61: Laba Tahun Berjalan | D61: 4105 | E61: Pendapatan Sewa Properti
A62: 3105 | B62: Dividen | D62: 4106 | E62: Pendapatan Penjualan Baju | F62: Percetakan | G62: Baju Brand
A63: Pendapatan | D63: 4107 | E63: Pendapatan Penjualan atas Pemesanan Custom
A64: 4101 | B64: Pendapatan Penjualan Tanah | D64: Jumlah Pendapatan
A65: 4102 | B65: Pendapatan Penjualan Rumah | D65: Pendapatan Lain-Lain
A66: 4103 | B66: Pendapatan Penjualan Ruko/Apartemen | D66: 4201 | E66: Pendapatan Administrasi
A67: 4104 | B67: Pendapatan Jasa Konstruksi | D67: 4202 | E67: Pendapatan Bunga
A68: 4105 | B68: Pendapatan Sewa Properti | D68: 4203 | E68: Keuntungan Penjualan Aset
A69: 4106 | B69: Pendapatan Penjualan Baju Konveksi | D69: 4204 | E69: Pendapatan Lainnya
A70: 4107 | B70: Pendapatan Penjualan atas Pemesanan Custom | D70: 4205 | E70: Pendapatan Investasi
A71: 4108 | B71: Pendapatan Jasa Percetakan | D71: 4206 | E71: Pendapatan Non-Operasional
A72: 4109 | B72: Pendapatan Jasa Konveksi | D72: Jumlah Pendapatan Lain-Lain
A73: 4110 | B73: Pendapatan Penjualan Baju Brand | D73: Harga Pokok Penjualan
A74: Pendapatan Lain-Lain | D74: 5101 | E74: Biaya Perolehan Tanah
A75: 4201 | B75: Pendapatan Administrasi | D75: 5102 | E75: Biaya Material Langsung | F75: Material Alam | G75: Material Pabrikasi
A76: 4202 | B76: Pendapatan Bunga | D76: 5103 | E76: Biaya Tenaga Kerja Langsung
A77: 4203 | B77: Keuntungan Penjualan Aset | D77: 5104 | E77: Biaya Tenaga Kerja Tidak Langsung
A78: 4204 | B78: Pendapatan Lainnya | D78: 5105 | E78: Biaya Overhead Lainnya | F78: Biaya Subkon Tukang | H78: Sekala & Senada
A79: 4205 | B79: Pendapatan Investasi | D79: 5106 | E79: Biaya Infrastruktur & Fasilitas Umum | F79: Subkon Listrik | H79: Biaya Kain | I79: Pasang Kancing | J79: Label
A80: 4206 | B80: Pendapatan Non-Operasional | D80: 5107 | E80: Biaya Perizinan dan Notaris | F80: Subkon Kusen | H80: Benang | I80: Bordir | J80: DTF
A81: Harga Pokok Penjualan | D81: 5108 | E81: Biaya Promosi Penjualan (yang dikapitalisasi) | H81: Ongkos Jahit | I81: Ongkos Potong | J81: Print
A82: 5101 | B82: Biaya Perolehan Tanah | D82: 5109 | E82: Biaya Langsung Proyek Lainnya
A83: 5102 | B83: Biaya Material Langsung (Material Alam) | D83: Jumlah Harga Pokok Penjualan
A84: 5103 | B84: Biaya Material Langsung (Material Pabrikasi) | D84: Beban Umum & Administrasi
A85: 5104 | B85: Biaya Tenaga Kerja Langsung | D85: 6101 | E85: Gaji & Tunjangan
A86: 5105 | B86: Biaya Tenaga Kerja Tidak Langsung | D86: 6102 | E86: Biaya Listrik, Air, & Utilitas | F86: Listrik
A87: 5106 | B87: Biaya Overhead Lainnya | D87: 6103 | E87: Biaya Sewa Kantor | F87: Air
A88: 5107 | B88: Biaya Infrastruktur & Fasilitas Umum | D88: 6104 | E88: Biaya ATK
A89: 5108 | B89: Biaya Perizinan dan Notaris | D89: 6105 | E89: Biaya Internet Kantor | F89: Lain-Lain
A90: 5109 | B90: Biaya Promosi Penjualan (yang dikapitalisasi) | D90: 6106 | E90: Biaya Penyusutan Aset Tetap
A91: 5110 | B91: Biaya Langsung Proyek Lainnya | D91: 6107 | E91: Biaya Pemeliharaan Gedung Kantor
A92: 5111 | B92: Biaya Material Langsung Sekala | D92: 6107 | E92: Biaya Pemeliharaan Gedung Kantor
A93: Beban Umum & Administrasi | D93: 6108 | E93: Biaya Transportasi & Kendaraan
A94: 6101 | B94: Gaji & Tunjangan | D94: 6109 | E94: Biaya Asuransi
A95: 6102 | B95: Biaya Listrik | D95: 6110 | E95: Biaya Pihak Afiliasi
A96: 6103 | B96: Biaya Air | D96: Jumlah Beban Umum & Administrasi
A97: 6104 | B97: Biaya Sewa Kantor | D97: Beban Pemasaran
A98: 6105 | B98: Biaya ATK | D98: 6201 | E98: Biaya Iklan & Promosi
A99: 6106 | B99: Biaya Internet Kantor | D99: 6202 | E99: Komisi Penjualan
A100: 6107 | B100: Biaya Penyusutan Aset Tetap | D100: 6203 | E100: Biaya Event & Pameran Properti
...

Sheet WS
B1: =C61/12 -> 1893000 | O1: 46161 | R1: 800000000
B2: Balance Sheet | C2: =IF(C52-C78<1,C78,"check again") -> 5.4541781e+09 | F2: =IF(F52-F78<>0,"check again",F78) -> 5.9156766e+09 | I2: =IF(I52-I78<>0,"check again",I78) -> 7.4776924e+09 | L2: =IF(L52-L78<>0,"check again",L78) -> 1.0256229e+10 | O2: =IF(O52-O78<>0,"check again",O78) -> 1.0762977e+10 | R2: =IF(R52-R78<>0,"check again",R78) -> check again | U2: =IF(U52-U78<>0,"check again",U78) -> check again | X2: =IF(X52-X78<>0,"check again",X78) -> check again | AA2: =IF(AA52-AA78<>0,"check again",AA78) -> check again | AD2: =IF(AD52-AD78<>0,"check again",AD78) -> check again | AG2: =IF(AG52-AG78<>0,"check again",AG78) -> check again | AJ2: =IF(AJ52-AJ78<>0,"check again",AJ78) -> check again | AM2: =IF(AM52-AM78<>0,"check again",AM78) -> check again
B3: Profit/Loss | C3: =C100-C150 -> 0 | F3: =F100-F150 -> -58760634 | I3: =I100-I150 -> -16202453 | L3: =L100-L150 -> 117664143 | O3: =O100-O150 -> 1194932519 | R3: =R100-R150 -> 1901304172 | U3: =U100-U150 -> 0 | X3: =X100-X150 -> 0 | AA3: =AA100-AA150 -> 0 | AD3: =AD100-AD150 -> 0 | AG3: =AG100-AG150 -> 0 | AJ3: =AJ100-AJ150 -> 0 | AM3: =AM100-AM150 -> 0 | AN3: =SUM(D3:AG3) -> 3138937747
A5: Kode Akun | B5: Nama Akun | C5: 2025 | D5: Mutasi | F5: 46023 | G5: Mutasi | I5: 46054 | J5: Mutasi | L5: 46082 | M5: Mutasi | O5: 46113 | P5: Mutasi | R5: 46143 | S5: Mutasi | U5: 46174 | V5: Mutasi | X5: 46204 | Y5: Mutasi | AA5: 46235 | AB5: Mutasi | AD5: 46266 | AE5: Mutasi | AG5: 46296 | AH5: Mutasi | AJ5: 46327 | AK5: Mutasi | AM5: 46357
D6: Debet | E6: Kredit | G6: Debet | H6: Kredit | J6: Debet | K6: Kredit | M6: Debet | N6: Kredit | P6: Debet | Q6: Kredit | S6: Debet | T6: Kredit | V6: Debet | W6: Kredit | Y6: Debet | Z6: Kredit | AB6: Debet | AC6: Kredit | AE6: Debet | AF6: Kredit | AH6: Debet | AI6: Kredit | AK6: Debet | AL6: Kredit
A7: Aset Lancar
A8: Kas & Bank
A9: 1101 | B9: Kas | C9: 0 | D9: =SUMIFS(JU!$H$5:$H$178,JU!$F$5:$F$178,WS!$A9) -> 0 | E9: =SUMIFS(JU!$K$5:$K$178,JU!$I$5:$I$178,WS!$A9) -> 0 | F9: =C9+D9-E9 -> 0 | G9: =SUMIFS(JU!$H$180:$H$440,JU!$F$180:$F$440,WS!$A9) -> 0 | H9: =SUMIFS(JU!$K$180:$K$440,JU!$I$180:$I$440,WS!$A9) -> 0 | I9: =F9+G9-H9 -> 0 | J9: =SUMIFS(JU!$H$441:$H$695,JU!$F$441:$F$695,WS!$A9) -> 0 | K9: =SUMIFS(JU!$K$441:$K$695,JU!$I$441:$I$695,WS!$A9) -> 0 | L9: =I9+J9-K9 -> 0 | M9: =SUMIFS(JU!$H$696:$H$1062,JU!$F$696:$F$1062,$A9) -> 0 | N9: =SUMIFS(JU!$K$696:$K$1062,JU!$I$696:$I$1062,WS!$A9) -> 0 | O9: =L9+M9-N9 -> 0 | P9: =SUMIFS(JU!$H$1063:$H$5007,JU!$F$1063:$F$5007,WS!$A9) -> 0 | Q9: =SUMIFS(JU!$K$1063:$K$5007,JU!$I$1063:$I$5007,WS!$A9) -> 0 | R9: =O9+P9-Q9 -> 0 | S9: =SUMIFS(JU!$H$5107:$H$5107,JU!$F$5107:$F$5107,WS!$A9) -> 0 | T9: =SUMIFS(JU!$K$5107:$K$5107,JU!$I$5107:$I$5107,WS!$A9) -> 0 | U9: =R9+S9-T9 -> 0 | V9: =SUMIFS(JU!$H$5107:$H$5107,JU!$F$5107:$F$5107,WS!$A9) -> 0 | W9: =SUMIFS(JU!$K$5107:$K$5107,JU!$I$5107:$I$5107,WS!$A9) -> 0 | X9: =U9+V9-W9 -> 0 | Y9: =SUMIFS(JU!$H$5107:$H$5107,JU!$F$5107:$F$5107,WS!$A9) -> 0 | Z9: =SUMIFS(JU!$K$5107:$K$5107,JU!$I$5107:$I$5107,WS!$A9) -> 0 | AA9: =X9+Y9-Z9 -> 0 | AB9: =SUMIFS(JU!$H$5107:$H$5107,JU!$F$5107:$F$5107,WS!$A9) -> 0 | AC9: =SUMIFS(JU!$K$5107:$K$5107,JU!$I$5107:$I$5107,WS!$A9) -> 0 | AD9: =AA9+AB9-AC9 -> 0 | AE9: =SUMIFS(JU!$H$5107:$H$5107,JU!$F$5107:$F$5107,WS!$A9) -> 0 | AF9: =SUMIFS(JU!$K$5107:$K$5107,JU!$I$5107:$I$5107,WS!$A9) -> 0 | AG9: =AD9+AE9-AF9 -> 0 | AH9: =SUMIFS(JU!$H$5107:$H$5107,JU!$F$5107:$F$5107,WS!$A9) -> 0 | AI9: =SUMIFS(JU!$K$5107:$K$5107,JU!$I$5107:$I$5107,WS!$A9) -> 0 | AJ9: =AG9+AH9-AI9 -> 0 | AK9: =SUMIFS(JU!$H$5107:$H$5107,JU!$F$5107:$F$5107,WS!$A9) -> 0 | AL9: =SUMIFS(JU!$K$5107:$K$5107,JU!$I$5107:$I$5107,WS!$A9) -> 0 | AM9: =AJ9+AK9-AL9 -> 0 | AN9: 446751 | AO9: =AG9-AN9 -> -446751
A10: 1102 | B10: BRI 562 | C10: 0 | D10: =SUMIFS(JU!$H$5:$H$178,JU!$F$5:$F$178,WS!$A10) -> 0 | E10: =SUMIFS(JU!$K$5:$K$178,JU!$I$5:$I$178,WS!$A10) -> 0 | F10: =C10+D10-E10 -> 0 | G10: =SUMIFS(JU!$H$180:$H$440,JU!$F$180:$F$440,WS!$A10) -> 0 | H10: =SUMIFS(JU!$K$180:$K$440,JU!$I$180:$I$440,WS!$A10) -> 0 | I10: =F10+G10-H10 -> 0 | J10: =SUMIFS(JU!$H$441:$H$695,JU!$F$441:$F$695,WS!$A10) -> 0 | K10: =SUMIFS(JU!$K$441:$K$695,JU!$I$441:$I$695,WS!$A10) -> 0 | L10: =I10+J10-K10 -> 0 | M10: =SUMIFS(JU!$H$696:$H$1062,JU!$F$696:$F$1062,$A10) -> 0 | N10: =SUMIFS(JU!$K$696:$K$1062,JU!$I$696:$I$1062,WS!$A10) -> 0 | O10: =L10+M10-N10 -> 0 | P10: =SUMIFS(JU!$H$1063:$H$5007,JU!$F$1063:$F$5007,WS!$A10) -> 0 | Q10: =SUMIFS(JU!$K$1063:$K$5007,JU!$I$1063:$I$5007,WS!$A10) -> 0 | R10: =O10+P10-Q10 -> 0 | S10: =SUMIFS(JU!$H$5107:$H$5107,JU!$F$5107:$F$5107,WS!$A10) -> 0 | T10: =SUMIFS(JU!$K$5107:$K$5107,JU!$I$5107:$I$5107,WS!$A10) -> 0 | U10: =R10+S10-T10 -> 0 | V10: =SUMIFS(JU!$H$5107:$H$5107,JU!$F$5107:$F$5107,WS!$A10) -> 0 | W10: =SUMIFS(JU!$K$5107:$K$5107,JU!$I$5107:$I$5107,WS!$A10) -> 0 | X10: =U10+V10-W10 -> 0 | Y10: =SUMIFS(JU!$H$5107:$H$5107,JU!$F$5107:$F$5107,WS!$A10) -> 0 | Z10: =SUMIFS(JU!$K$5107:$K$5107,JU!$I$5107:$I$5107,WS!$A10) -> 0 | AA10: =X10+Y10-Z10 -> 0 | AB10: =SUMIFS(JU!$H$5107:$H$5107,JU!$F$5107:$F$5107,WS!$A10) -> 0 | AC10: =SUMIFS(JU!$K$5107:$K$5107,JU!$I$5107:$I$5107,WS!$A10) -> 0 | AD10: =AA10+AB10-AC10 -> 0 | AE10: =SUMIFS(JU!$H$5107:$H$5107,JU!$F$5107:$F$5107,WS!$A10) -> 0 | AF10: =SUMIFS(JU!$K$5107:$K$5107,JU!$I$5107:$I$5107,WS!$A10) -> 0 | AG10: =AD10+AE10-AF10 -> 0 | AH10: =SUMIFS(JU!$H$5107:$H$5107,JU!$F$5107:$F$5107,WS!$A10) -> 0 | AI10: =SUMIFS(JU!$K$5107:$K$5107,JU!$I$5107:$I$5107,WS!$A10) -> 0 | AJ10: =AG10+AH10-AI10 -> 0 | AK10: =SUMIFS(JU!$H$5107:$H$5107,JU!$F$5107:$F$5107,WS!$A10) -> 0 | AL10: =SUMIFS(JU!$K$5107:$K$5107,JU!$I$5107:$I$5107,WS!$A10) -> 0 | AM10: =AJ10+AK10-AL10 -> 0 | AN10: Saldo Real RK | AO10: Selisih
A11: 1103 | B11: BRI 568 | C11: 14931577 | D11: =SUMIFS(JU!$H$5:$H$178,JU!$F$5:$F$178,WS!$A11) -> 1897877594 | E11: =SUMIFS(JU!$K$5:$K$178,JU!$I$5:$I$178,WS!$A11) -> 1909356910 | F11: =C11+D11-E11 -> 3452261.2 | G11: =SUMIFS(JU!$H$180:$H$440,JU!$F$180:$F$440,WS!$A11) -> 5508497990 | H11: =SUMIFS(JU!$K$180:$K$440,JU!$I$180:$I$440,WS!$A11) -> 5467947247 | I11: =F11+G11-H11 -> 44003004 | J11: =SUMIFS(JU!$H$441:$H$695,JU!$F$441:$F$695,WS!$A11) -> 3718534853 | K11: =SUMIFS(JU!$K$441:$K$695,JU!$I$441:$I$695,WS!$A11) -> 3745432928 | L11: =I11+J11-K11 -> 17104929 | M11: =SUMIFS(JU!$H$696:$H$1062,JU!$F$696:$F$1062,$A11) -> 5526256754 | N11: =SUMIFS(JU!$K$696:$K$1062,JU!$I$696:$I$1062,WS!$A11) -> 5539476187 | O11: =L11+M11-N11 -> 3885496.2 | P11: =SUMIFS(JU!$H$1063:$H$5007,JU!$F$1063:$F$5007,WS!$A11) -> 4770567500 | Q11: =SUMIFS(JU!$K$1063:$K$5007,JU!$I$1063:$I$5007,WS!$A11) -> 4717910456 | R11: =O11+P11-Q11 -> 56542540 | S11: =SUMIFS(JU!$H$5107:$H$5107,JU!$F$5107:$F$5107,WS!$A11) -> 0 | T11: =SUMIFS(JU!$K$5107:$K$5107,JU!$I$5107:$I$5107,WS!$A11) -> 0 | U11: =R11+S11-T11 -> 56542540 | V11: =SUMIFS(JU!$H$5107:$H$5107,JU!$F$5107:$F$5107,WS!$A11) -> 0 | W11: =SUMIFS(JU!$K$5107:$K$5107,JU!$I$5107:$I$5107,WS!$A11) -> 0 | X11: =U11+V11-W11 -> 56542540 | Y11: =SUMIFS(JU!$H$5107:$H$5107,JU!$F$5107:$F$5107,WS!$A11) -> 0 | Z11: =SUMIFS(JU!$K$5107:$K$5107,JU!$I$5107:$I$5107,WS!$A11) -> 0 | AA11: =X11+Y11-Z11 -> 56542540 | AB11: =SUMIFS(JU!$H$5107:$H$5107,JU!$F$5107:$F$5107,WS!$A11) -> 0 | AC11: =SUMIFS(JU!$K$5107:$K$5107,JU!$I$5107:$I$5107,WS!$A11) -> 0 | AD11: =AA11+AB11-AC11 -> 56542540 | AE11: =SUMIFS(JU!$H$5107:$H$5107,JU!$F$5107:$F$5107,WS!$A11) -> 0 | AF11: =SUMIFS(JU!$K$5107:$K$5107,JU!$I$5107:$I$5107,WS!$A11) -> 0 | AG11: =AD11+AE11-AF11 -> 56542540 | AH11: =SUMIFS(JU!$H$5107:$H$5107,JU!$F$5107:$F$5107,WS!$A11) -> 0 | AI11: =SUMIFS(JU!$K$5107:$K$5107,JU!$I$5107:$I$5107,WS!$A11) -> 0 | AJ11: =AG11+AH11-AI11 -> 56542540 | AK11: =SUMIFS(JU!$H$5107:$H$5107,JU!$F$5107:$F$5107,WS!$A11) -> 0 | AL11: =SUMIFS(JU!$K$5107:$K$5107,JU!$I$5107:$I$5107,WS!$A11) -> 0 | AM11: =AJ11+AK11-AL11 -> 56542540 | AN11: 311777388 | AO11: =AG11-AN11 -> -2.5523485e+08
A12: 1104 | B12: BRI 309 (Giro) | C12: 26000000 | D12: =SUMIFS(JU!$H$5:$H$178,JU!$F$5:$F$178,WS!$A12) -> 0 | E12: =SUMIFS(JU!$K$5:$K$178,JU!$I$5:$I$178,WS!$A12) -> 0 | F12: =C12+D12-E12 -> 26000000 | G12: =SUMIFS(JU!$H$180:$H$440,JU!$F$180:$F$440,WS!$A12) -> 0 | H12: =SUMIFS(JU!$K$180:$K$440,JU!$I$180:$I$440,WS!$A12) -> 0 | I12: =F12+G12-H12 -> 26000000 | J12: =SUMIFS(JU!$H$441:$H$695,JU!$F$441:$F$695,WS!$A12) -> 0 | K12: =SUMIFS(JU!$K$441:$K$695,JU!$I$441:$I$695,WS!$A12) -> 0 | L12: =I12+J12-K12 -> 26000000 | M12: =SUMIFS(JU!$H$696:$H$1062,JU!$F$696:$F$1062,$A12) -> 0 | N12: =SUMIFS(JU!$K$696:$K$1062,JU!$I$696:$I$1062,WS!$A12) -> 0 | O12: =L12+M12-N12 -> 26000000 | P12: =SUMIFS(JU!$H$1063:$H$5007,JU!$F$1063:$F$5007,WS!$A12) -> 0 | Q12: =SUMIFS(JU!$K$1063:$K$5007,JU!$I$1063:$I$5007,WS!$A12) -> 0 | R12: =O12+P12-Q12 -> 26000000 | S12: =SUMIFS(JU!$H$5107:$H$5107,JU!$F$5107:$F$5107,WS!$A12) -> 0 | T12: =SUMIFS(JU!$K$5107:$K$5107,JU!$I$5107:$I$5107,WS!$A12) -> 0 | U12: =R12+S12-T12 -> 26000000 | V12: =SUMIFS(JU!$H$5107:$H$5107,JU!$F$5107:$F$5107,WS!$A12) -> 0 | W12: =SUMIFS(JU!$K$5107:$K$5107,JU!$I$5107:$I$5107,WS!$A12) -> 0 | X12: =U12+V12-W12 -> 26000000 | Y12: =SUMIFS(JU!$H$5107:$H$5107,JU!$F$5107:$F$5107,WS!$A12) -> 0 | Z12: =SUMIFS(JU!$K$5107:$K$5107,JU!$I$5107:$I$5107,WS!$A12) -> 0 | AA12: =X12+Y12-Z12 -> 26000000 | AB12: =SUMIFS(JU!$H$5107:$H$5107,JU!$F$5107:$F$5107,WS!$A12) -> 0 | AC12: =SUMIFS(JU!$K$5107:$K$5107,JU!$I$5107:$I$5107,WS!$A12) -> 0 | AD12: =AA12+AB12-AC12 -> 26000000 | AE12: =SUMIFS(JU!$H$5107:$H$5107,JU!$F$5107:$F$5107,WS!$A12) -> 0 | AF12: =SUMIFS(JU!$K$5107:$K$5107,JU!$I$5107:$I$5107,WS!$A12) -> 0 | AG12: =AD12+AE12-AF12 -> 26000000 | AH12: =SUMIFS(JU!$H$5107:$H$5107,JU!$F$5107:$F$5107,WS!$A12) -> 0 | AI12: =SUMIFS(JU!$K$5107:$K$5107,JU!$I$5107:$I$5107,WS!$A12) -> 0 | AJ12: =AG12+AH12-AI12 -> 26000000 | AK12: =SUMIFS(JU!$H$5107:$H$5107,JU!$F$5107:$F$5107,WS!$A12) -> 0 | AL12: =SUMIFS(JU!$K$5107:$K$5107,JU!$I$5107:$I$5107,WS!$A12) -> 0 | AM12: =AJ12+AK12-AL12 -> 26000000
A13: 1105 | B13: BTN 041 (Giro) | C13: 0 | D13: =SUMIFS(JU!$H$5:$H$178,JU!$F$5:$F$178,WS!$A13) -> 0 | E13: =SUMIFS(JU!$K$5:$K$178,JU!$I$5:$I$178,WS!$A13) -> 0 | F13: =C13+D13-E13 -> 0 | G13: =SUMIFS(JU!$H$180:$H$440,JU!$F$180:$F$440,WS!$A13) -> 0 | H13: =SUMIFS(JU!$K$180:$K$440,JU!$I$180:$I$440,WS!$A13) -> 0 | I13: =F13+G13-H13 -> 0 | J13: =SUMIFS(JU!$H$441:$H$695,JU!$F$441:$F$695,WS!$A13) -> 0 | K13: =SUMIFS(JU!$K$441:$K$695,JU!$I$441:$I$695,WS!$A13) -> 0 | L13: =I13+J13-K13 -> 0 | M13: =SUMIFS(JU!$H$696:$H$1062,JU!$F$696:$F$1062,$A13) -> 0 | N13: =SUMIFS(JU!$K$696:$K$1062,JU!$I$696:$I$1062,WS!$A13) -> 0 | O13: =L13+M13-N13 -> 0 | P13: =SUMIFS(JU!$H$1063:$H$5007,JU!$F$1063:$F$5007,WS!$A13) -> 0 | Q13: =SUMIFS(JU!$K$1063:$K$5007,JU!$I$1063:$I$5007,WS!$A13) -> 0 | R13: =O13+P13-Q13 -> 0 | S13: =SUMIFS(JU!$H$5107:$H$5107,JU!$F$5107:$F$5107,WS!$A13) -> 0 | T13: =SUMIFS(JU!$K$5107:$K$5107,JU!$I$5107:$I$5107,WS!$A13) -> 0 | U13: =R13+S13-T13 -> 0 | V13: =SUMIFS(JU!$H$5107:$H$5107,JU!$F$5107:$F$5107,WS!$A13) -> 0 | W13: =SUMIFS(JU!$K$5107:$K$5107,JU!$I$5107:$I$5107,WS!$A13) -> 0 | X13: =U13+V13-W13 -> 0 | Y13: =SUMIFS(JU!$H$5107:$H$5107,JU!$F$5107:$F$5107,WS!$A13) -> 0 | Z13: =SUMIFS(JU!$K$5107:$K$5107,JU!$I$5107:$I$5107,WS!$A13) -> 0 | AA13: =X13+Y13-Z13 -> 0 | AB13: =SUMIFS(JU!$H$5107:$H$5107,JU!$F$5107:$F$5107,WS!$A13) -> 0 | AC13: =SUMIFS(JU!$K$5107:$K$5107,JU!$I$5107:$I$5107,WS!$A13) -> 0 | AD13: =AA13+AB13-AC13 -> 0 | AE13: =SUMIFS(JU!$H$5107:$H$5107,JU!$F$5107:$F$5107,WS!$A13) -> 0 | AF13: =SUMIFS(JU!$K$5107:$K$5107,JU!$I$5107:$I$5107,WS!$A13) -> 0 | AG13: =AD13+AE13-AF13 -> 0 | AH13: =SUMIFS(JU!$H$5107:$H$5107,JU!$F$5107:$F$5107,WS!$A13) -> 0 | AI13: =SUMIFS(JU!$K$5107:$K$5107,JU!$I$5107:$I$5107,WS!$A13) -> 0 | AJ13: =AG13+AH13-AI13 -> 0 | AK13: =SUMIFS(JU!$H$5107:$H$5107,JU!$F$5107:$F$5107,WS!$A13) -> 0 | AL13: =SUMIFS(JU!$K$5107:$K$5107,JU!$I$5107:$I$5107,WS!$A13) -> 0 | AM13: =AJ13+AK13-AL13 -> 0
A14: 1106 | B14: BNI 084 (Giro) | C14: 0 | D14: =SUMIFS(JU!$H$5:$H$178,JU!$F$5:$F$178,WS!$A14) -> 0 | E14: =SUMIFS(JU!$K$5:$K$178,JU!$I$5:$I$178,WS!$A14) -> 0 | F14: =C14+D14-E14 -> 0 | G14: =SUMIFS(JU!$H$180:$H$440,JU!$F$180:$F$440,WS!$A14) -> 0 | H14: =SUMIFS(JU!$K$180:$K$440,JU!$I$180:$I$440,WS!$A14) -> 0 | I14: =F14+G14-H14 -> 0 | J14: =SUMIFS(JU!$H$441:$H$695,JU!$F$441:$F$695,WS!$A14) -> 0 | K14: =SUMIFS(JU!$K$441:$K$695,JU!$I$441:$I$695,WS!$A14) -> 0 | L14: =I14+J14-K14 -> 0 | M14: =SUMIFS(JU!$H$696:$H$1062,JU!$F$696:$F$1062,$A14) -> 0 | N14: =SUMIFS(JU!$K$696:$K$1062,JU!$I$696:$I$1062,WS!$A14) -> 0 | O14: =L14+M14-N14 -> 0 | P14: =SUMIFS(JU!$H$1063:$H$5007,JU!$F$1063:$F$5007,WS!$A14) -> 0 | Q14: =SUMIFS(JU!$K$1063:$K$5007,JU!$I$1063:$I$5007,WS!$A14) -> 0 | R14: =O14+P14-Q14 -> 0 | S14: =SUMIFS(JU!$H$5107:$H$5107,JU!$F$5107:$F$5107,WS!$A14) -> 0 | T14: =SUMIFS(JU!$K$5107:$K$5107,JU!$I$5107:$I$5107,WS!$A14) -> 0 | U14: =R14+S14-T14 -> 0 | V14: =SUMIFS(JU!$H$5107:$H$5107,JU!$F$5107:$F$5107,WS!$A14) -> 0 | W14: =SUMIFS(JU!$K$5107:$K$5107,JU!$I$5107:$I$5107,WS!$A14) -> 0 | X14: =U14+V14-W14 -> 0 | Y14: =SUMIFS(JU!$H$5107:$H$5107,JU!$F$5107:$F$5107,WS!$A14) -> 0 | Z14: =SUMIFS(JU!$K$5107:$K$5107,JU!$I$5107:$I$5107,WS!$A14) -> 0 | AA14: =X14+Y14-Z14 -> 0 | AB14: =SUMIFS(JU!$H$5107:$H$5107,JU!$F$5107:$F$5107,WS!$A14) -> 0 | AC14: =SUMIFS(JU!$K$5107:$K$5107,JU!$I$5107:$I$5107,WS!$A14) -> 0 | AD14: =AA14+AB14-AC14 -> 0 | AE14: =SUMIFS(JU!$H$5107:$H$5107,JU!$F$5107:$F$5107,WS!$A14) -> 0 | AF14: =SUMIFS(JU!$K$5107:$K$5107,JU!$I$5107:$I$5107,WS!$A14) -> 0 | AG14: =AD14+AE14-AF14 -> 0 | AH14: =SUMIFS(JU!$H$5107:$H$5107,JU!$F$5107:$F$5107,WS!$A14) -> 0 | AI14: =SUMIFS(JU!$K$5107:$K$5107,JU!$I$5107:$I$5107,WS!$A14) -> 0 | AJ14: =AG14+AH14-AI14 -> 0 | AK14: =SUMIFS(JU!$H$5107:$H$5107,JU!$F$5107:$F$5107,WS!$A14) -> 0 | AL14: =SUMIFS(JU!$K$5107:$K$5107,JU!$I$5107:$I$5107,WS!$A14) -> 0 | AM14: =AJ14+AK14-AL14 -> 0
A15: 1107 | B15: Mandiri 669 (Giro) | C15: 0 | D15: =SUMIFS(JU!$H$5:$H$178,JU!$F$5:$F$178,WS!$A15) -> 0 | E15: =SUMIFS(JU!$K$5:$K$178,JU!$I$5:$I$178,WS!$A15) -> 0 | F15: =C15+D15-E15 -> 0 | G15: =SUMIFS(JU!$H$180:$H$440,JU!$F$180:$F$440,WS!$A15) -> 0 | H15: =SUMIFS(JU!$K$180:$K$440,JU!$I$180:$I$440,WS!$A15) -> 0 | I15: =F15+G15-H15 -> 0 | J15: =SUMIFS(JU!$H$441:$H$695,JU!$F$441:$F$695,WS!$A15) -> 0 | K15: =SUMIFS(JU!$K$441:$K$695,JU!$I$441:$I$695,WS!$A15) -> 0 | L15: =I15+J15-K15 -> 0 | M15: =SUMIFS(JU!$H$696:$H$1062,JU!$F$696:$F$1062,$A15) -> 0 | N15: =SUMIFS(JU!$K$696:$K$1062,JU!$I$696:$I$1062,WS!$A15) -> 0 | O15: =L15+M15-N15 -> 0 | P15: =SUMIFS(JU!$H$1063:$H$5007,JU!$F$1063:$F$5007,WS!$A15) -> 0 | Q15: =SUMIFS(JU!$K$1063:$K$5007,JU!$I$1063:$I$5007,WS!$A15) -> 0 | R15: =O15+P15-Q15 -> 0 | S15: =SUMIFS(JU!$H$5107:$H$5107,JU!$F$5107:$F$5107,WS!$A15) -> 0 | T15: =SUMIFS(JU!$K$5107:$K$5107,JU!$I$5107:$I$5107,WS!$A15) -> 0 | U15: =R15+S15-T15 -> 0 | V15: =SUMIFS(JU!$H$5107:$H$5107,JU!$F$5107:$F$5107,WS!$A15) -> 0 | W15: =SUMIFS(JU!$K$5107:$K$5107,JU!$I$5107:$I$5107,WS!$A15) -> 0 | X15: =U15+V15-W15 -> 0 | Y15: =SUMIFS(JU!$H$5107:$H$5107,JU!$F$5107:$F$5107,WS!$A15) -> 0 | Z15: =SUMIFS(JU!$K$5107:$K$5107,JU!$I$5107:$I$5107,WS!$A15) -> 0 | AA15: =X15+Y15-Z15 -> 0 | AB15: =SUMIFS(JU!$H$5107:$H$5107,JU!$F$5107:$F$5107,WS!$A15) -> 0 | AC15: =SUMIFS(JU!$K$5107:$K$5107,JU!$I$5107:$I$5107,WS!$A15) -> 0 | AD15: =AA15+AB15-AC15 -> 0 | AE15: =SUMIFS(JU!$H$5107:$H$5107,JU!$F$5107:$F$5107,WS!$A15) -> 0 | AF15: =SUMIFS(JU!$K$5107:$K$5107,JU!$I$5107:$I$5107,WS!$A15) -> 0 | AG15: =AD15+AE15-AF15 -> 0 | AH15: =SUMIFS(JU!$H$5107:$H$5107,JU!$F$5107:$F$5107,WS!$A15) -> 0 | AI15: =SUMIFS(JU!$K$5107:$K$5107,JU!$I$5107:$I$5107,WS!$A15) -> 0 | AJ15: =AG15+AH15-AI15 -> 0 | AK15: =SUMIFS(JU!$H$5107:$H$5107,JU!$F$5107:$F$5107,WS!$A15) -> 0 | AL15: =SUMIFS(JU!$K$5107:$K$5107,JU!$I$5107:$I$5107,WS!$A15) -> 0 | AM15: =AJ15+AK15-AL15 -> 0
A16: 1108 | B16: Rekening Owner | C16: 144518 | D16: =SUMIFS(JU!$H$5:$H$178,JU!$F$5:$F$178,WS!$A16) -> 0 | E16: =SUMIFS(JU!$K$5:$K$178,JU!$I$5:$I$178,WS!$A16) -> 0 | F16: =C16+D16-E16 -> 144518 | G16: =SUMIFS(JU!$H$180:$H$440,JU!$F$180:$F$440,WS!$A16) -> 200000000 | H16: =SUMIFS(JU!$K$180:$K$440,JU!$I$180:$I$440,WS!$A16) -> 0 | I16: =F16+G16-H16 -> 200144518 | J16: =SUMIFS(JU!$H$441:$H$695,JU!$F$441:$F$695,WS!$A16) -> 1200000000 | K16: =SUMIFS(JU!$K$441:$K$695,JU!$I$441:$I$695,WS!$A16) -> 200000000 | L16: =I16+J16-K16 -> 1200144518 | M16: =SUMIFS(JU!$H$696:$H$1062,JU!$F$696:$F$1062,$A16) -> 420000000 | N16: =SUMIFS(JU!$K$696:$K$1062,JU!$I$696:$I$1062,WS!$A16) -> 1184000000 | O16: =L16+M16-N16 -> 436144518 | P16: =SUMIFS(JU!$H$1063:$H$5007,JU!$F$1063:$F$5007,WS!$A16) -> 1190000000 | Q16: =SUMIFS(JU!$K$1063:$K$5007,JU!$I$1063:$I$5007,WS!$A16) -> 835000000 | R16: =O16+P16-Q16 -> 791144518 | S16: =SUMIFS(JU!$H$5107:$H$5107,JU!$F$5107:$F$5107,WS!$A16) -> 0 | T16: =SUMIFS(JU!$K$5107:$K$5107,JU!$I$5107:$I$5107,WS!$A16) -> 0 | U16: =R16+S16-T16 -> 791144518 | V16: =SUMIFS(JU!$H$5107:$H$5107,JU!$F$5107:$F$5107,WS!$A16) -> 0 | W16: =SUMIFS(JU!$K$5107:$K$5107,JU!$I$5107:$I$5107,WS!$A16) -> 0 | X16: =U16+V16-W16 -> 791144518 | Y16: =SUMIFS(JU!$H$5107:$H$5107,JU!$F$5107:$F$5107,WS!$A16) -> 0 | Z16: =SUMIFS(JU!$K$5107:$K$5107,JU!$I$5107:$I$5107,WS!$A16) -> 0 | AA16: =X16+Y16-Z16 -> 791144518 | AB16: =SUMIFS(JU!$H$5107:$H$5107,JU!$F$5107:$F$5107,WS!$A16) -> 0 | AC16: =SUMIFS(JU!$K$5107:$K$5107,JU!$I$5107:$I$5107,WS!$A16) -> 0 | AD16: =AA16+AB16-AC16 -> 791144518 | AE16: =SUMIFS(JU!$H$5107:$H$5107,JU!$F$5107:$F$5107,WS!$A16) -> 0 | AF16: =SUMIFS(JU!$K$5107:$K$5107,JU!$I$5107:$I$5107,WS!$A16) -> 0 | AG16: =AD16+AE16-AF16 -> 791144518 | AH16: =SUMIFS(JU!$H$5107:$H$5107,JU!$F$5107:$F$5107,WS!$A16) -> 0 | AI16: =SUMIFS(JU!$K$5107:$K$5107,JU!$I$5107:$I$5107,WS!$A16) -> 0 | AJ16: =AG16+AH16-AI16 -> 791144518 | AK16: =SUMIFS(JU!$H$5107:$H$5107,JU!$F$5107:$F$5107,WS!$A16) -> 0 | AL16: =SUMIFS(JU!$K$5107:$K$5107,JU!$I$5107:$I$5107,WS!$A16) -> 0 | AM16: =AJ16+AK16-AL16 -> 791144518
A17: 1109 | B17: BRI 560 | C17: 0 | D17: =SUMIFS(JU!$H$5:$H$178,JU!$F$5:$F$178,WS!$A17) -> 0 | E17: =SUMIFS(JU!$K$5:$K$178,JU!$I$5:$I$178,WS!$A17) -> 0 | F17: =C17+D17-E17 -> 0 | G17: =SUMIFS(JU!$H$180:$H$440,JU!$F$180:$F$440,WS!$A17) -> 0 | H17: =SUMIFS(JU!$K$180:$K$440,JU!$I$180:$I$440,WS!$A17) -> 0 | I17: =F17+G17-H17 -> 0 | J17: =SUMIFS(JU!$H$441:$H$695,JU!$F$441:$F$695,WS!$A17) -> 0 | K17: =SUMIFS(JU!$K$441:$K$695,JU!$I$441:$I$695,WS!$A17) -> 0 | L17: =I17+J17-K17 -> 0 | M17: =SUMIFS(JU!$H$696:$H$1062,JU!$F$696:$F$1062,$A17) -> 0 | N17: =SUMIFS(JU!$K$696:$K$1062,JU!$I$696:$I$1062,WS!$A17) -> 0 | O17: =L17+M17-N17 -> 0 | P17: =SUMIFS(JU!$H$1063:$H$5007,JU!$F$1063:$F$5007,WS!$A17) -> 0 | Q17: =SUMIFS(JU!$K$1063:$K$5007,JU!$I$1063:$I$5007,WS!$A17) -> 0 | R17: =O17+P17-Q17 -> 0 | S17: =SUMIFS(JU!$H$5107:$H$5107,JU!$F$5107:$F$5107,WS!$A17) -> 0 | T17: =SUMIFS(JU!$K$5107:$K$5107,JU!$I$5107:$I$5107,WS!$A17) -> 0 | U17: =R17+S17-T17 -> 0 | V17: =SUMIFS(JU!$H$5107:$H$5107,JU!$F$5107:$F$5107,WS!$A17) -> 0 | W17: =SUMIFS(JU!$K$5107:$K$5107,JU!$I$5107:$I$5107,WS!$A17) -> 0 | X17: =U17+V17-W17 -> 0 | Y17: =SUMIFS(JU!$H$5107:$H$5107,JU!$F$5107:$F$5107,WS!$A17) -> 0 | Z17: =SUMIFS(JU!$K$5107:$K$5107,JU!$I$5107:$I$5107,WS!$A17) -> 0 | AA17: =X17+Y17-Z17 -> 0 | AB17: =SUMIFS(JU!$H$5107:$H$5107,JU!$F$5107:$F$5107,WS!$A17) -> 0 | AC17: =SUMIFS(JU!$K$5107:$K$5107,JU!$I$5107:$I$5107,WS!$A17) -> 0 | AD17: =AA17+AB17-AC17 -> 0 | AE17: =SUMIFS(JU!$H$5107:$H$5107,JU!$F$5107:$F$5107,WS!$A17) -> 0 | AF17: =SUMIFS(JU!$K$5107:$K$5107,JU!$I$5107:$I$5107,WS!$A17) -> 0 | AG17: =AD17+AE17-AF17 -> 0 | AH17: =SUMIFS(JU!$H$5107:$H$5107,JU!$F$5107:$F$5107,WS!$A17) -> 0 | AI17: =SUMIFS(JU!$K$5107:$K$5107,JU!$I$5107:$I$5107,WS!$A17) -> 0 | AJ17: =AG17+AH17-AI17 -> 0 | AK17: =SUMIFS(JU!$H$5107:$H$5107,JU!$F$5107:$F$5107,WS!$A17) -> 0 | AL17: =SUMIFS(JU!$K$5107:$K$5107,JU!$I$5107:$I$5107,WS!$A17) -> 0 | AM17: =AJ17+AK17-AL17 -> 0 | AN17: 58428285 | AO17: =AG17-AN17 -> -58428285
A18: Total Kas & Bank | C18: =SUM(C9:C17) -> 41076095 | D18: =SUMIFS(JU!$H$5:$H$178,JU!$F$5:$F$178,WS!$A18) -> 0 | E18: =SUMIFS(JU!$K$5:$K$178,JU!$I$5:$I$178,WS!$A18) -> 0 | F18: =SUM(F9:F17) -> 29596779 | G18: =SUMIFS(JU!$H$180:$H$440,JU!$F$180:$F$440,WS!$A18) -> 0 | H18: =SUMIFS(JU!$K$180:$K$440,JU!$I$180:$I$440,WS!$A18) -> 0 | I18: =SUM(I9:I17) -> 2.7014752e+08 | J18: =SUMIFS(JU!$H$441:$H$695,JU!$F$441:$F$695,WS!$A18) -> 0 | K18: =SUMIFS(JU!$K$441:$K$695,JU!$I$441:$I$695,WS!$A18) -> 0 | L18: =SUM(L9:L17) -> 1.2432494e+09 | M18: =SUMIFS(JU!$H$696:$H$1062,JU!$F$696:$F$1062,$A18) -> 0 | N18: =SUMIFS(JU!$K$696:$K$1062,JU!$I$696:$I$1062,WS!$A18) -> 0 | O18: =SUM(O9:O17) -> 4.6603001e+08 | P18: =SUMIFS(JU!$H$1063:$H$5007,JU!$F$1063:$F$5007,WS!$A18) -> 0 | Q18: =SUMIFS(JU!$K$1063:$K$5007,JU!$I$1063:$I$5007,WS!$A18) -> 0 | R18: =SUM(R9:R17) -> 8.7368706e+08 | S18: =SUMIFS(JU!$H$5107:$H$5107,JU!$F$5107:$F$5107,WS!$A18) -> 0 | T18: =SUMIFS(JU!$K$5107:$K$5107,JU!$I$5107:$I$5107,WS!$A18) -> 0 | U18: =SUM(U9:U17) -> 8.7368706e+08 | V18: =SUMIFS(JU!$H$5107:$H$5107,JU!$F$5107:$F$5107,WS!$A18) -> 0 | W18: =SUMIFS(JU!$K$5107:$K$5107,JU!$I$5107:$I$5107,WS!$A18) -> 0 | X18: =SUM(X9:X17) -> 8.7368706e+08 | Y18: =SUMIFS(JU!$H$5107:$H$5107,JU!$F$5107:$F$5107,WS!$A18) -> 0 | Z18: =SUMIFS(JU!$K$5107:$K$5107,JU!$I$5107:$I$5107,WS!$A18) -> 0 | AA18: =SUM(AA9:AA17) -> 8.7368706e+08 | AB18: =SUMIFS(JU!$H$5107:$H$5107,JU!$F$5107:$F$5107,WS!$A18) -> 0 | AC18: =SUMIFS(JU!$K$5107:$K$5107,JU!$I$5107:$I$5107,WS!$A18) -> 0 | AD18: =SUM(AD9:AD17) -> 8.7368706e+08 | AE18: =SUMIFS(JU!$H$5107:$H$5107,JU!$F$5107:$F$5107,WS!$A18) -> 0 | AF18: =SUMIFS(JU!$K$5107:$K$5107,JU!$I$5107:$I$5107,WS!$A18) -> 0 | AG18: =SUM(AG9:AG17) -> 8.7368706e+08 | AH18: =SUMIFS(JU!$H$5107:$H$5107,JU!$F$5107:$F$5107,WS!$A18) -> 0 | AI18: =SUMIFS(JU!$K$5107:$K$5107,JU!$I$5107:$I$5107,WS!$A18) -> 0 | AJ18: =SUM(AJ9:AJ17) -> 8.7368706e+08 | AK18: =SUMIFS(JU!$H$5107:$H$5107,JU!$F$5107:$F$5107,WS!$A18) -> 0 | AL18: =SUMIFS(JU!$K$5107:$K$5107,JU!$I$5107:$I$5107,WS!$A18) -> 0 | AM18: =SUM(AM9:AM17) -> 8.7368706e+08
A19: Piutang | D19: =SUMIFS(JU!$H$5:$H$178,JU!$F$5:$F$178,WS!$A19) -> 0 | E19: =SUMIFS(JU!$K$5:$K$178,JU!$I$5:$I$178,WS!$A19) -> 0 | G19: =SUMIFS(JU!$H$180:$H$440,JU!$F$180:$F$440,WS!$A19) -> 0 | H19: =SUMIFS(JU!$K$180:$K$440,JU!$I$180:$I$440,WS!$A19) -> 0 | J19: =SUMIFS(JU!$H$441:$H$695,JU!$F$441:$F$695,WS!$A19) -> 0 | K19: =SUMIFS(JU!$K$441:$K$695,JU!$I$441:$I$695,WS!$A19) -> 0 | M19: =SUMIFS(JU!$H$696:$H$1062,JU!$F$696:$F$1062,$A19) -> 0 | N19: =SUMIFS(JU!$K$696:$K$1062,JU!$I$696:$I$1062,WS!$A19) -> 0 | P19: =SUMIFS(JU!$H$1063:$H$5007,JU!$F$1063:$F$5007,WS!$A19) -> 0 | Q19: =SUMIFS(JU!$K$1063:$K$5007,JU!$I$1063:$I$5007,WS!$A19) -> 0 | S19: =SUMIFS(JU!$H$5107:$H$5107,JU!$F$5107:$F$5107,WS!$A19) -> 0 | T19: =SUMIFS(JU!$K$5107:$K$5107,JU!$I$5107:$I$5107,WS!$A19) -> 0 | V19: =SUMIFS(JU!$H$5107:$H$5107,JU!$F$5107:$F$5107,WS!$A19) -> 0 | W19: =SUMIFS(JU!$K$5107:$K$5107,JU!$I$5107:$I$5107,WS!$A19) -> 0 | Y19: =SUMIFS(JU!$H$5107:$H$5107,JU!$F$5107:$F$5107,WS!$A19) -> 0 | Z19: =SUMIFS(JU!$K$5107:$K$5107,JU!$I$5107:$I$5107,WS!$A19) -> 0 | AB19: =SUMIFS(JU!$H$5107:$H$5107,JU!$F$5107:$F$5107,WS!$A19) -> 0 | AC19: =SUMIFS(JU!$K$5107:$K$5107,JU!$I$5107:$I$5107,WS!$A19) -> 0 | AE19: =SUMIFS(JU!$H$5107:$H$5107,JU!$F$5107:$F$5107,WS!$A19) -> 0 | AF19: =SUMIFS(JU!$K$5107:$K$5107,JU!$I$5107:$I$5107,WS!$A19) -> 0 | AH19: =SUMIFS(JU!$H$5107:$H$5107,JU!$F$5107:$F$5107,WS!$A19) -> 0 | AI19: =SUMIFS(JU!$K$5107:$K$5107,JU!$I$5107:$I$5107,WS!$A19) -> 0 | AK19: =SUMIFS(JU!$H$5107:$H$5107,JU!$F$5107:$F$5107,WS!$A19) -> 0 | AL19: =SUMIFS(JU!$K$5107:$K$5107,JU!$I$5107:$I$5107,WS!$A19) -> 0
A20: 1201 | B20: Deposito Jangka Pendek | C20: 0 | D20: =SUMIFS(JU!$H$5:$H$178,JU!$F$5:$F$178,WS!$A20) -> 0 | E20: =SUMIFS(JU!$K$5:$K$178,JU!$I$5:$I$178,WS!$A20) -> 0 | F20: =C20+D20-E20 -> 0 | G20: =SUMIFS(JU!$H$180:$H$440,JU!$F$180:$F$440,WS!$A20) -> 0 | H20: =SUMIFS(JU!$K$180:$K$440,JU!$I$180:$I$440,WS!$A20) -> 0 | I20: =F20+G20-H20 -> 0 | J20: =SUMIFS(JU!$H$441:$H$695,JU!$F$441:$F$695,WS!$A20) -> 0 | K20: =SUMIFS(JU!$K$441:$K$695,JU!$I$441:$I$695,WS!$A20) -> 0 | L20: =I20+J20-K20 -> 0 | M20: =SUMIFS(JU!$H$696:$H$1062,JU!$F$696:$F$1062,$A20) -> 0 | N20: =SUMIFS(JU!$K$696:$K$1062,JU!$I$696:$I$1062,WS!$A20) -> 0 | O20: =L20+M20-N20 -> 0 | P20: =SUMIFS(JU!$H$1063:$H$5007,JU!$F$1063:$F$5007,WS!$A20) -> 0 | Q20: =SUMIFS(JU!$K$1063:$K$5007,JU!$I$1063:$I$5007,WS!$A20) -> 0 | R20: =O20+P20-Q20 -> 0 | S20: =SUMIFS(JU!$H$5107:$H$5107,JU!$F$5107:$F$5107,WS!$A20) -> 0 | T20: =SUMIFS(JU!$K$5107:$K$5107,JU!$I$5107:$I$5107,WS!$A20) -> 0 | U20: =R20+S20-T20 -> 0 | V20: =SUMIFS(JU!$H$5107:$H$5107,JU!$F$5107:$F$5107,WS!$A20) -> 0 | W20: =SUMIFS(JU!$K$5107:$K$5107,JU!$I$5107:$I$5107,WS!$A20) -> 0 | X20: =U20+V20-W20 -> 0 | Y20: =SUMIFS(JU!$H$5107:$H$5107,JU!$F$5107:$F$5107,WS!$A20) -> 0 | Z20: =SUMIFS(JU!$K$5107:$K$5107,JU!$I$5107:$I$5107,WS!$A20) -> 0 | AA20: =X20+Y20-Z20 -> 0 | AB20: =SUMIFS(JU!$H$5107:$H$5107,JU!$F$5107:$F$5107,WS!$A20) -> 0 | AC20: =SUMIFS(JU!$K$5107:$K$5107,JU!$I$5107:$I$5107,WS!$A20) -> 0 | AD20: =AA20+AB20-AC20 -> 0 | AE20: =SUMIFS(JU!$H$5107:$H$5107,JU!$F$5107:$F$5107,WS!$A20) -> 0 | AF20: =SUMIFS(JU!$K$5107:$K$5107,JU!$I$5107:$I$5107,WS!$A20) -> 0 | AG20: =AD20+AE20-AF20 -> 0 | AH20: =SUMIFS(JU!$H$5107:$H$5107,JU!$F$5107:$F$5107,WS!$A20) -> 0 | AI20: =SUMIFS(JU!$K$5107:$K$5107,JU!$I$5107:$I$5107,WS!$A20) -> 0 | AJ20: =AG20+AH20-AI20 -> 0 | AK20: =SUMIFS(JU!$H$5107:$H$5107,JU!$F$5107:$F$5107,WS!$A20) -> 0 | AL20: =SUMIFS(JU!$K$5107:$K$5107,JU!$I$5107:$I$5107,WS!$A20) -> 0 | AM20: =AJ20+AK20-AL20 -> 0
A21: 1202 | B21: Piutang Usaha | C21: 1410490000 | D21: =SUMIFS(JU!$H$5:$H$178,JU!$F$5:$F$178,WS!$A21) -> 138000000 | E21: =SUMIFS(JU!$K$5:$K$178,JU!$I$5:$I$178,WS!$A21) -> 507350000 | F21: =C21+D21-E21 -> 1041140000 | G21: =SUMIFS(JU!$H$180:$H$440,JU!$F$180:$F$440,WS!$A21) -> 507000000 | H21: =SUMIFS(JU!$K$180:$K$440,JU!$I$180:$I$440,WS!$A21) -> 734679346 | I21: =F21+G21-H21 -> 813460654 | J21: =SUMIFS(JU!$H$441:$H$695,JU!$F$441:$F$695,WS!$A21) -> 522000000 | K21: =SUMIFS(JU!$K$441:$K$695,JU!$I$441:$I$695,WS!$A21) -> 624000000 | L21: =I21+J21-K21 -> 711460654 | M21: =SUMIFS(JU!$H$696:$H$1062,JU!$F$696:$F$1062,$A21) -> 2030610000 | N21: =SUMIFS(JU!$K$696:$K$1062,JU!$I$696:$I$1062,WS!$A21) -> 1359500000 | O21: =L21+M21-N21 -> 1382570654 | P21: =SUMIFS(JU!$H$1063:$H$5007,JU!$F$1063:$F$5007,WS!$A21) -> 2102744000 | Q21: =SUMIFS(JU!$K$1063:$K$5007,JU!$I$1063:$I$5007,WS!$A21) -> 1180990000 | R21: =O21+P21-Q21 -> 2304324654 | S21: =SUMIFS(JU!$H$5107:$H$5107,JU!$F$5107:$F$5107,WS!$A21) -> 0 | T21: =SUMIFS(JU!$K$5107:$K$5107,JU!$I$5107:$I$5107,WS!$A21) -> 0 | U21: =R21+S21-T21 -> 2304324654 | V21: =SUMIFS(JU!$H$5107:$H$5107,JU!$F$5107:$F$5107,WS!$A21) -> 0 | W21: =SUMIFS(JU!$K$5107:$K$5107,JU!$I$5107:$I$5107,WS!$A21) -> 0 | X21: =U21+V21-W21 -> 2304324654 | Y21: =SUMIFS(JU!$H$5107:$H$5107,JU!$F$5107:$F$5107,WS!$A21) -> 0 | Z21: =SUMIFS(JU!$K$5107:$K$5107,JU!$I$5107:$I$5107,WS!$A21) -> 0 | AA21: =X21+Y21-Z21 -> 2304324654 | AB21: =SUMIFS(JU!$H$5107:$H$5107,JU!$F$5107:$F$5107,WS!$A21) -> 0 | AC21: =SUMIFS(JU!$K$5107:$K$5107,JU!$I$5107:$I$5107,WS!$A21) -> 0 | AD21: =AA21+AB21-AC21 -> 2304324654 | AE21: =SUMIFS(JU!$H$5107:$H$5107,JU!$F$5107:$F$5107,WS!$A21) -> 0 | AF21: =SUMIFS(JU!$K$5107:$K$5107,JU!$I$5107:$I$5107,WS!$A21) -> 0 | AG21: =AD21+AE21-AF21 -> 2304324654 | AH21: =SUMIFS(JU!$H$5107:$H$5107,JU!$F$5107:$F$5107,WS!$A21) -> 0 | AI21: =SUMIFS(JU!$K$5107:$K$5107,JU!$I$5107:$I$5107,WS!$A21) -> 0 | AJ21: =AG21+AH21-AI21 -> 2304324654 | AK21: =SUMIFS(JU!$H$5107:$H$5107,JU!$F$5107:$F$5107,WS!$A21) -> 0 | AL21: =SUMIFS(JU!$K$5107:$K$5107,JU!$I$5107:$I$5107,WS!$A21) -> 0 | AM21: =AJ21+AK21-AL21 -> 2304324654
A22: 1203 | B22: Piutang Afiliasi | C22: 352700000 | D22: =SUMIFS(JU!$H$5:$H$178,JU!$F$5:$F$178,WS!$A22) -> 159987500 | E22: =SUMIFS(JU!$K$5:$K$178,JU!$I$5:$I$178,WS!$A22) -> 177487500 | F22: =C22+D22-E22 -> 335200000 | G22: =SUMIFS(JU!$H$180:$H$440,JU!$F$180:$F$440,WS!$A22) -> 201800000 | H22: =SUMIFS(JU!$K$180:$K$440,JU!$I$180:$I$440,WS!$A22) -> 26800000 | I22: =F22+G22-H22 -> 510200000 | J22: =SUMIFS(JU!$H$441:$H$695,JU!$F$441:$F$695,WS!$A22) -> 170250000 | K22: =SUMIFS(JU!$K$441:$K$695,JU!$I$441:$I$695,WS!$A22) -> 77000000 | L22: =I22+J22-K22 -> 603450000 | M22: =SUMIFS(JU!$H$696:$H$1062,JU!$F$696:$F$1062,$A22) -> 405865000 | N22: =SUMIFS(JU!$K$696:$K$1062,JU!$I$696:$I$1062,WS!$A22) -> 299500000 | O22: =L22+M22-N22 -> 709815000 | P22: =SUMIFS(JU!$H$1063:$H$5007,JU!$F$1063:$F$5007,WS!$A22) -> 810942000 | Q22: =SUMIFS(JU!$K$1063:$K$5007,JU!$I$1063:$I$5007,WS!$A22) -> 66000000 | R22: =O22+P22-Q22 -> 1454757000 | S22: =SUMIFS(JU!$H$5107:$H$5107,JU!$F$5107:$F$5107,WS!$A22) -> 0 | T22: =SUMIFS(JU!$K$5107:$K$5107,JU!$I$5107:$I$5107,WS!$A22) -> 0 | U22: =R22+S22-T22 -> 1454757000 | V22: =SUMIFS(JU!$H$5107:$H$5107,JU!$F$5107:$F$5107,WS!$A22) -> 0 | W22: =SUMIFS(JU!$K$5107:$K$5107,JU!$I$5107:$I$5107,WS!$A22) -> 0 | X22: =U22+V22-W22 -> 1454757000 | Y22: =SUMIFS(JU!$H$5107:$H$5107,JU!$F$5107:$F$5107,WS!$A22) -> 0 | Z22: =SUMIFS(JU!$K$5107:$K$5107,JU!$I$5107:$I$5107,WS!$A22) -> 0 | AA22: =X22+Y22-Z22 -> 1454757000 | AB22: =SUMIFS(JU!$H$5107:$H$5107,JU!$F$5107:$F$5107,WS!$A22) -> 0 | AC22: =SUMIFS(JU!$K$5107:$K$5107,JU!$I$5107:$I$5107,WS!$A22) -> 0 | AD22: =AA22+AB22-AC22 -> 1454757000 | AE22: =SUMIFS(JU!$H$5107:$H$5107,JU!$F$5107:$F$5107,WS!$A22) -> 0 | AF22: =SUMIFS(JU!$K$5107:$K$5107,JU!$I$5107:$I$5107,WS!$A22) -> 0 | AG22: =AD22+AE22-AF22 -> 1454757000 | AH22: =SUMIFS(JU!$H$5107:$H$5107,JU!$F$5107:$F$5107,WS!$A22) -> 0 | AI22: =SUMIFS(JU!$K$5107:$K$5107,JU!$I$5107:$I$5107,WS!$A22) -> 0 | AJ22: =AG22+AH22-AI22 -> 1454757000 | AK22: =SUMIFS(JU!$H$5107:$H$5107,JU!$F$5107:$F$5107,WS!$A22) -> 0 | AL22: =SUMIFS(JU!$K$5107:$K$5107,JU!$I$5107:$I$5107,WS!$A22) -> 0 | AM22: =AJ22+AK22-AL22 -> 1454757000
A23: 1204 | B23: Piutang Lain-lain | C23: 99500000 | D23: =SUMIFS(JU!$H$5:$H$178,JU!$F$5:$F$178,WS!$A23) -> 25000000 | E23: =SUMIFS(JU!$K$5:$K$178,JU!$I$5:$I$178,WS!$A23) -> 52500000 | F23: =C23+D23-E23 -> 72000000 | G23: =SUMIFS(JU!$H$180:$H$440,JU!$F$180:$F$440,WS!$A23) -> 10000000 | H23: =SUMIFS(JU!$K$180:$K$440,JU!$I$180:$I$440,WS!$A23) -> 0 | I23: =F23+G23-H23 -> 82000000 | J23: =SUMIFS(JU!$H$441:$H$695,JU!$F$441:$F$695,WS!$A23) -> 15000000 | K23: =SUMIFS(JU!$K$441:$K$695,JU!$I$441:$I$695,WS!$A23) -> 15000000 | L23: =I23+J23-K23 -> 82000000 | M23: =SUMIFS(JU!$H$696:$H$1062,JU!$F$696:$F$1062,$A23) -> 3040000 | N23: =SUMIFS(JU!$K$696:$K$1062,JU!$I$696:$I$1062,WS!$A23) -> 10000000 | O23: =L23+M23-N23 -> 75040000 | P23: =SUMIFS(JU!$H$1063:$H$5007,JU!$F$1063:$F$5007,WS!$A23) -> 0 | Q23: =SUMIFS(JU!$K$1063:$K$5007,JU!$I$1063:$I$5007,WS!$A23) -> 0 | R23: =O23+P23-Q23 -> 75040000 | S23: =SUMIFS(JU!$H$5107:$H$5107,JU!$F$5107:$F$5107,WS!$A23) -> 0 | T23: =SUMIFS(JU!$K$5107:$K$5107,JU!$I$5107:$I$5107,WS!$A23) -> 0 | U23: =R23+S23-T23 -> 75040000 | V23: =SUMIFS(JU!$H$5107:$H$5107,JU!$F$5107:$F$5107,WS!$A23) -> 0 | W23: =SUMIFS(JU!$K$5107:$K$5107,JU!$I$5107:$I$5107,WS!$A23) -> 0 | X23: =U23+V23-W23 -> 75040000 | Y23: =SUMIFS(JU!$H$5107:$H$5107,JU!$F$5107:$F$5107,WS!$A23) -> 0 | Z23: =SUMIFS(JU!$K$5107:$K$5107,JU!$I$5107:$I$5107,WS!$A23) -> 0 | AA23: =X23+Y23-Z23 -> 75040000 | AB23: =SUMIFS(JU!$H$5107:$H$5107,JU!$F$5107:$F$5107,WS!$A23) -> 0 | AC23: =SUMIFS(JU!$K$5107:$K$5107,JU!$I$5107:$I$5107,WS!$A23) -> 0 | AD23: =AA23+AB23-AC23 -> 75040000 | AE23: =SUMIFS(JU!$H$5107:$H$5107,JU!$F$5107:$F$5107,WS!$A23) -> 0 | AF23: =SUMIFS(JU!$K$5107:$K$5107,JU!$I$5107:$I$5107,WS!$A23) -> 0 | AG23: =AD23+AE23-AF23 -> 75040000 | AH23: =SUMIFS(JU!$H$5107:$H$5107,JU!$F$5107:$F$5107,WS!$A23) -> 0 | AI23: =SUMIFS(JU!$K$5107:$K$5107,JU!$I$5107:$I$5107,WS!$A23) -> 0 | AJ23: =AG23+AH23-AI23 -> 75040000 | AK23: =SUMIFS(JU!$H$5107:$H$5107,JU!$F$5107:$F$5107,WS!$A23) -> 0 | AL23: =SUMIFS(JU!$K$5107:$K$5107,JU!$I$5107:$I$5107,WS!$A23) -> 0 | AM23: =AJ23+AK23-AL23 -> 75040000
A24: 1205 | B24: Uang Muka Pembelian Tanah | C24: 0 | D24: =SUMIFS(JU!$H$5:$H$178,JU!$F$5:$F$178,WS!$A24) -> 0 | E24: =SUMIFS(JU!$K$5:$K$178,JU!$I$5:$I$178,WS!$A24) -> 0 | F24: =C24+D24-E24 -> 0 | G24: =SUMIFS(JU!$H$180:$H$440,JU!$F$180:$F$440,WS!$A24) -> 0 | H24: =SUMIFS(JU!$K$180:$K$440,JU!$I$180:$I$440,WS!$A24) -> 0 | I24: =F24+G24-H24 -> 0 | J24: =SUMIFS(JU!$H$441:$H$695,JU!$F$441:$F$695,WS!$A24) -> 0 | K24: =SUMIFS(JU!$K$441:$K$695,JU!$I$441:$I$695,WS!$A24) -> 0 | L24: =I24+J24-K24 -> 0 | M24: =SUMIFS(JU!$H$696:$H$1062,JU!$F$696:$F$1062,$A24) -> 0 | N24: =SUMIFS(JU!$K$696:$K$1062,JU!$I$696:$I$1062,WS!$A24) -> 0 | O24: =L24+M24-N24 -> 0 | P24: =SUMIFS(JU!$H$1063:$H$5007,JU!$F$1063:$F$5007,WS!$A24) -> 0 | Q24: =SUMIFS(JU!$K$1063:$K$5007,JU!$I$1063:$I$5007,WS!$A24) -> 0 | R24: =O24+P24-Q24 -> 0 | S24: =SUMIFS(JU!$H$5107:$H$5107,JU!$F$5107:$F$5107,WS!$A24) -> 0 | T24: =SUMIFS(JU!$K$5107:$K$5107,JU!$I$5107:$I$5107,WS!$A24) -> 0 | U24: =R24+S24-T24 -> 0 | V24: =SUMIFS(JU!$H$5107:$H$5107,JU!$F$5107:$F$5107,WS!$A24) -> 0 | W24: =SUMIFS(JU!$K$5107:$K$5107,JU!$I$5107:$I$5107,WS!$A24) -> 0 | X24: =U24+V24-W24 -> 0 | Y24: =SUMIFS(JU!$H$5107:$H$5107,JU!$F$5107:$F$5107,WS!$A24) -> 0 | Z24: =SUMIFS(JU!$K$5107:$K$5107,JU!$I$5107:$I$5107,WS!$A24) -> 0 | AA24: =X24+Y24-Z24 -> 0 | AB24: =SUMIFS(JU!$H$5107:$H$5107,JU!$F$5107:$F$5107,WS!$A24) -> 0 | AC24: =SUMIFS(JU!$K$5107:$K$5107,JU!$I$5107:$I$5107,WS!$A24) -> 0 | AD24: =AA24+AB24-AC24 -> 0 | AE24: =SUMIFS(JU!$H$5107:$H$5107,JU!$F$5107:$F$5107,WS!$A24) -> 0 | AF24: =SUMIFS(JU!$K$5107:$K$5107,JU!$I$5107:$I$5107,WS!$A24) -> 0 | AG24: =AD24+AE24-AF24 -> 0 | AH24: =SUMIFS(JU!$H$5107:$H$5107,JU!$F$5107:$F$5107,WS!$A24) -> 0 | AI24: =SUMIFS(JU!$K$5107:$K$5107,JU!$I$5107:$I$5107,WS!$A24) -> 0 | AJ24: =AG24+AH24-AI24 -> 0 | AK24: =SUMIFS(JU!$H$5107:$H$5107,JU!$F$5107:$F$5107,WS!$A24) -> 0 | AL24: =SUMIFS(JU!$K$5107:$K$5107,JU!$I$5107:$I$5107,WS!$A24) -> 0 | AM24: =AJ24+AK24-AL24 -> 0
A25: 1206 | B25: Uang Muka Pembelian Konveksi | C25: 0 | D25: =SUMIFS(JU!$H$5:$H$178,JU!$F$5:$F$178,WS!$A25) -> 0 | E25: =SUMIFS(JU!$K$5:$K$178,JU!$I$5:$I$178,WS!$A25) -> 0 | F25: =C25+D25-E25 -> 0 | G25: =SUMIFS(JU!$H$180:$H$440,JU!$F$180:$F$440,WS!$A25) -> 0 | H25: =SUMIFS(JU!$K$180:$K$440,JU!$I$180:$I$440,WS!$A25) -> 0 | I25: =F25+G25-H25 -> 0 | J25: =SUMIFS(JU!$H$441:$H$695,JU!$F$441:$F$695,WS!$A25) -> 0 | K25: =SUMIFS(JU!$K$441:$K$695,JU!$I$441:$I$695,WS!$A25) -> 0 | L25: =I25+J25-K25 -> 0 | M25: =SUMIFS(JU!$H$696:$H$1062,JU!$F$696:$F$1062,$A25) -> 0 | N25: =SUMIFS(JU!$K$696:$K$1062,JU!$I$696:$I$1062,WS!$A25) -> 0 | O25: =L25+M25-N25 -> 0 | P25: =SUMIFS(JU!$H$1063:$H$5007,JU!$F$1063:$F$5007,WS!$A25) -> 0 | Q25: =SUMIFS(JU!$K$1063:$K$5007,JU!$I$1063:$I$5007,WS!$A25) -> 0 | R25: =O25+P25-Q25 -> 0 | S25: =SUMIFS(JU!$H$5107:$H$5107,JU!$F$5107:$F$5107,WS!$A25) -> 0 | T25: =SUMIFS(JU!$K$5107:$K$5107,JU!$I$5107:$I$5107,WS!$A25) -> 0 | U25: =R25+S25-T25 -> 0 | V25: =SUMIFS(JU!$H$5107:$H$5107,JU!$F$5107:$F$5107,WS!$A25) -> 0 | W25: =SUMIFS(JU!$K$5107:$K$5107,JU!$I$5107:$I$5107,WS!$A25) -> 0 | X25: =U25+V25-W25 -> 0 | Y25: =SUMIFS(JU!$H$5107:$H$5107,JU!$F$5107:$F$5107,WS!$A25) -> 0 | Z25: =SUMIFS(JU!$K$5107:$K$5107,JU!$I$5107:$I$5107,WS!$A25) -> 0 | AA25: =X25+Y25-Z25 -> 0 | AB25: =SUMIFS(JU!$H$5107:$H$5107,JU!$F$5107:$F$5107,WS!$A25) -> 0 | AC25: =SUMIFS(JU!$K$5107:$K$5107,JU!$I$5107:$I$5107,WS!$A25) -> 0 | AD25: =AA25+AB25-AC25 -> 0 | AE25: =SUMIFS(JU!$H$5107:$H$5107,JU!$F$5107:$F$5107,WS!$A25) -> 0 | AF25: =SUMIFS(JU!$K$5107:$K$5107,JU!$I$5107:$I$5107,WS!$A25) -> 0 | AG25: =AD25+AE25-AF25 -> 0 | AH25: =SUMIFS(JU!$H$5107:$H$5107,JU!$F$5107:$F$5107,WS!$A25) -> 0 | AI25: =SUMIFS(JU!$K$5107:$K$5107,JU!$I$5107:$I$5107,WS!$A25) -> 0 | AJ25: =AG25+AH25-AI25 -> 0 | AK25: =SUMIFS(JU!$H$5107:$H$5107,JU!$F$5107:$F$5107,WS!$A25) -> 0 | AL25: =SUMIFS(JU!$K$5107:$K$5107,JU!$I$5107:$I$5107,WS!$A25) -> 0 | AM25: =AJ25+AK25-AL25 -> 0
A26: 1207 | B26: Pajak Dibayar di Muka | C26: 0 | D26: =SUMIFS(JU!$H$5:$H$178,JU!$F$5:$F$178,WS!$A26) -> 0 | E26: =SUMIFS(JU!$K$5:$K$178,JU!$I$5:$I$178,WS!$A26) -> 0 | F26: =C26+D26-E26 -> 0 | G26: =SUMIFS(JU!$H$180:$H$440,JU!$F$180:$F$440,WS!$A26) -> 0 | H26: =SUMIFS(JU!$K$180:$K$440,JU!$I$180:$I$440,WS!$A26) -> 0 | I26: =F26+G26-H26 -> 0 | J26: =SUMIFS(JU!$H$441:$H$695,JU!$F$441:$F$695,WS!$A26) -> 0 | K26: =SUMIFS(JU!$K$441:$K$695,JU!$I$441:$I$695,WS!$A26) -> 0 | L26: =I26+J26-K26 -> 0 | M26: =SUMIFS(JU!$H$696:$H$1062,JU!$F$696:$F$1062,$A26) -> 0 | N26: =SUMIFS(JU!$K$696:$K$1062,JU!$I$696:$I$1062,WS!$A26) -> 0 | O26: =L26+M26-N26 -> 0 | P26: =SUMIFS(JU!$H$1063:$H$5007,JU!$F$1063:$F$5007,WS!$A26) -> 0 | Q26: =SUMIFS(JU!$K$1063:$K$5007,JU!$I$1063:$I$5007,WS!$A26) -> 0 | R26: =O26+P26-Q26 -> 0 | S26: =SUMIFS(JU!$H$5107:$H$5107,JU!$F$5107:$F$5107,WS!$A26) -> 0 | T26: =SUMIFS(JU!$K$5107:$K$5107,JU!$I$5107:$I$5107,WS!$A26) -> 0 | U26: =R26+S26-T26 -> 0 | V26: =SUMIFS(JU!$H$5107:$H$5107,JU!$F$5107:$F$5107,WS!$A26) -> 0 | W26: =SUMIFS(JU!$K$5107:$K$5107,JU!$I$5107:$I$5107,WS!$A26) -> 0 | X26: =U26+V26-W26 -> 0 | Y26: =SUMIFS(JU!$H$5107:$H$5107,JU!$F$5107:$F$5107,WS!$A26) -> 0 | Z26: =SUMIFS(JU!$K$5107:$K$5107,JU!$I$5107:$I$5107,WS!$A26) -> 0 | AA26: =X26+Y26-Z26 -> 0 | AB26: =SUMIFS(JU!$H$5107:$H$5107,JU!$F$5107:$F$5107,WS!$A26) -> 0 | AC26: =SUMIFS(JU!$K$5107:$K$5107,JU!$I$5107:$I$5107,WS!$A26) -> 0 | AD26: =AA26+AB26-AC26 -> 0 | AE26: =SUMIFS(JU!$H$5107:$H$5107,JU!$F$5107:$F$5107,WS!$A26) -> 0 | AF26: =SUMIFS(JU!$K$5107:$K$5107,JU!$I$5107:$I$5107,WS!$A26) -> 0 | AG26: =AD26+AE26-AF26 -> 0 | AH26: =SUMIFS(JU!$H$5107:$H$5107,JU!$F$5107:$F$5107,WS!$A26) -> 0 | AI26: =SUMIFS(JU!$K$5107:$K$5107,JU!$I$5107:$I$5107,WS!$A26) -> 0 | AJ26: =AG26+AH26-AI26 -> 0 | AK26: =SUMIFS(JU!$H$5107:$H$5107,JU!$F$5107:$F$5107,WS!$A26) -> 0 | AL26: =SUMIFS(JU!$K$5107:$K$5107,JU!$I$5107:$I$5107,WS!$A26) -> 0 | AM26: =AJ26+AK26-AL26 -> 0
A27: 1208 | B27: Biaya Dibayar di Muka | C27: 0 | D27: =SUMIFS(JU!$H$5:$H$178,JU!$F$5:$F$178,WS!$A27) -> 0 | E27: =SUMIFS(JU!$K$5:$K$178,JU!$I$5:$I$178,WS!$A27) -> 0 | F27: =C27+D27-E27 -> 0 | G27: =SUMIFS(JU!$H$180:$H$440,JU!$F$180:$F$440,WS!$A27) -> 0 | H27: =SUMIFS(JU!$K$180:$K$440,JU!$I$180:$I$440,WS!$A27) -> 0 | I27: =F27+G27-H27 -> 0 | J27: =SUMIFS(JU!$H$441:$H$695,JU!$F$441:$F$695,WS!$A27) -> 0 | K27: =SUMIFS(JU!$K$441:$K$695,JU!$I$441:$I$695,WS!$A27) -> 0 | L27: =I27+J27-K27 -> 0 | M27: =SUMIFS(JU!$H$696:$H$1062,JU!$F$696:$F$1062,$A27) -> 62500000 | N27: =SUMIFS(JU!$K$696:$K$1062,JU!$I$696:$I$1062,WS!$A27) -> 0 | O27: =L27+M27-N27 -> 62500000 | P27: =SUMIFS(JU!$H$1063:$H$5007,JU!$F$1063:$F$5007,WS!$A27) -> 0 | Q27: =SUMIFS(JU!$K$1063:$K$5007,JU!$I$1063:$I$5007,WS!$A27) -> 0 | R27: =O27+P27-Q27 -> 62500000 | S27: =SUMIFS(JU!$H$5107:$H$5107,JU!$F$5107:$F$5107,WS!$A27) -> 0 | T27: =SUMIFS(JU!$K$5107:$K$5107,JU!$I$5107:$I$5107,WS!$A27) -> 0 | U27: =R27+S27-T27 -> 62500000 | V27: =SUMIFS(JU!$H$5107:$H$5107,JU!$F$5107:$F$5107,WS!$A27) -> 0 | W27: =SUMIFS(JU!$K$5107:$K$5107,JU!$I$5107:$I$5107,WS!$A27) -> 0 | X27: =U27+V27-W27 -> 62500000 | Y27: =SUMIFS(JU!$H$5107:$H$5107,JU!$F$5107:$F$5107,WS!$A27) -> 0 | Z27: =SUMIFS(JU!$K$5107:$K$5107,JU!$I$5107:$I$5107,WS!$A27) -> 0 | AA27: =X27+Y27-Z27 -> 62500000 | AB27: =SUMIFS(JU!$H$5107:$H$5107,JU!$F$5107:$F$5107,WS!$A27) -> 0 | AC27: =SUMIFS(JU!$K$5107:$K$5107,JU!$I$5107:$I$5107,WS!$A27) -> 0 | AD27: =AA27+AB27-AC27 -> 62500000 | AE27: =SUMIFS(JU!$H$5107:$H$5107,JU!$F$5107:$F$5107,WS!$A27) -> 0 | AF27: =SUMIFS(JU!$K$5107:$K$5107,JU!$I$5107:$I$5107,WS!$A27) -> 0 | AG27: =AD27+AE27-AF27 -> 62500000 | AH27: =SUMIFS(JU!$H$5107:$H$5107,JU!$F$5107:$F$5107,WS!$A27) -> 0 | AI27: =SUMIFS(JU!$K$5107:$K$5107,JU!$I$5107:$I$5107,WS!$A27) -> 0 | AJ27: =AG27+AH27-AI27 -> 62500000 | AK27: =SUMIFS(JU!$H$5107:$H$5107,JU!$F$5107:$F$5107,WS!$A27) -> 0 | AL27: =SUMIFS(JU!$K$5107:$K$5107,JU!$I$5107:$I$5107,WS!$A27) -> 0 | AM27: =AJ27+AK27-AL27 -> 62500000
A28: Total Piutang | C28: 1862690000 | D28: =SUMIFS(JU!$H$5:$H$178,JU!$F$5:$F$178,WS!$A28) -> 0 | E28: =SUMIFS(JU!$K$5:$K$178,JU!$I$5:$I$178,WS!$A28) -> 0 | F28: =SUM(F20:F27) -> 1448340000 | G28: =SUMIFS(JU!$H$180:$H$440,JU!$F$180:$F$440,WS!$A28) -> 0 | H28: =SUMIFS(JU!$K$180:$K$440,JU!$I$180:$I$440,WS!$A28) -> 0 | I28: =SUM(I20:I27) -> 1405660654 | J28: =SUMIFS(JU!$H$441:$H$695,JU!$F$441:$F$695,WS!$A28) -> 0 | K28: =SUMIFS(JU!$K$441:$K$695,JU!$I$441:$I$695,WS!$A28) -> 0 | L28: =SUM(L20:L27) -> 1396910654 | M28: =SUMIFS(JU!$H$696:$H$1062,JU!$F$696:$F$1062,$A28) -> 0 | N28: =SUMIFS(JU!$K$696:$K$1062,JU!$I$696:$I$1062,WS!$A28) -> 0 | O28: =SUM(O20:O27) -> 2229925654 | P28: =SUMIFS(JU!$H$1063:$H$5007,JU!$F$1063:$F$5007,WS!$A28) -> 0 | Q28: =SUMIFS(JU!$K$1063:$K$5007,JU!$I$1063:$I$5007,WS!$A28) -> 0 | R28: =SUM(R20:R27) -> 3896621654 | S28: =SUMIFS(JU!$H$5107:$H$5107,JU!$F$5107:$F$5107,WS!$A28) -> 0 | T28: =SUMIFS(JU!$K$5107:$K$5107,JU!$I$5107:$I$5107,WS!$A28) -> 0 | U28: =SUM(U20:U27) -> 3896621654 | V28: =SUMIFS(JU!$H$5107:$H$5107,JU!$F$5107:$F$5107,WS!$A28) -> 0 | W28: =SUMIFS(JU!$K$5107:$K$5107,JU!$I$5107:$I$5107,WS!$A28) -> 0 | X28: =SUM(X20:X27) -> 3896621654 | Y28: =SUMIFS(JU!$H$5107:$H$5107,JU!$F$5107:$F$5107,WS!$A28) -> 0 | Z28: =SUMIFS(JU!$K$5107:$K$5107,JU!$I$5107:$I$5107,WS!$A28) -> 0 | AA28: =SUM(AA20:AA27) -> 3896621654 | AB28: =SUMIFS(JU!$H$5107:$H$5107,JU!$F$5107:$F$5107,WS!$A28) -> 0 | AC28: =SUMIFS(JU!$K$5107:$K$5107,JU!$I$5107:$I$5107,WS!$A28) -> 0 | AD28: =SUM(AD20:AD27) -> 3896621654 | AE28: =SUMIFS(JU!$H$5107:$H$5107,JU!$F$5107:$F$5107,WS!$A28) -> 0 | AF28: =SUMIFS(JU!$K$5107:$K$5107,JU!$I$5107:$I$5107,WS!$A28) -> 0 | AG28: =SUM(AG20:AG27) -> 3896621654 | AH28: =SUMIFS(JU!$H$5107:$H$5107,JU!$F$5107:$F$5107,WS!$A28) -> 0 | AI28: =SUMIFS(JU!$K$5107:$K$5107,JU!$I$5107:$I$5107,WS!$A28) -> 0 | AJ28: =SUM(AJ20:AJ27) -> 3896621654 | AK28: =SUMIFS(JU!$H$5107:$H$5107,JU!$F$5107:$F$5107,WS!$A28) -> 0 | AL28: =SUMIFS(JU!$K$5107:$K$5107,JU!$I$5107:$I$5107,WS!$A28) -> 0 | AM28: =SUM(AM20:AM27) -> 3896621654
A29: Persediaan | D29: =SUMIFS(JU!$H$5:$H$178,JU!$F$5:$F$178,WS!$A29) -> 0 | E29: =SUMIFS(JU!$K$5:$K$178,JU!$I$5:$I$178,WS!$A29) -> 0 | G29: =SUMIFS(JU!$H$180:$H$440,JU!$F$180:$F$440,WS!$A29) -> 0 | H29: =SUMIFS(JU!$K$180:$K$440,JU!$I$180:$I$440,WS!$A29) -> 0 | J29: =SUMIFS(JU!$H$441:$H$695,JU!$F$441:$F$695,WS!$A29) -> 0 | K29: =SUMIFS(JU!$K$441:$K$695,JU!$I$441:$I$695,WS!$A29) -> 0 | M29: =SUMIFS(JU!$H$696:$H$1062,JU!$F$696:$F$1062,$A29) -> 0 | N29: =SUMIFS(JU!$K$696:$K$1062,JU!$I$696:$I$1062,WS!$A29) -> 0 | P29: =SUMIFS(JU!$H$1063:$H$5007,JU!$F$1063:$F$5007,WS!$A29) -> 0 | Q29: =SUMIFS(JU!$K$1063:$K$5007,JU!$I$1063:$I$5007,WS!$A29) -> 0 | S29: =SUMIFS(JU!$H$5107:$H$5107,JU!$F$5107:$F$5107,WS!$A29) -> 0 | T29: =SUMIFS(JU!$K$5107:$K$5107,JU!$I$5107:$I$5107,WS!$A29) -> 0 | V29: =SUMIFS(JU!$H$5107:$H$5107,JU!$F$5107:$F$5107,WS!$A29) -> 0 | W29: =SUMIFS(JU!$K$5107:$K$5107,JU!$I$5107:$I$5107,WS!$A29) -> 0 | Y29: =SUMIFS(JU!$H$5107:$H$5107,JU!$F$5107:$F$5107,WS!$A29) -> 0 | Z29: =SUMIFS(JU!$K$5107:$K$5107,JU!$I$5107:$I$5107,WS!$A29) -> 0 | AB29: =SUMIFS(JU!$H$5107:$H$5107,JU!$F$5107:$F$5107,WS!$A29) -> 0 | AC29: =SUMIFS(JU!$K$5107:$K$5107,JU!$I$5107:$I$5107,WS!$A29) -> 0 | AE29: =SUMIFS(JU!$H$5107:$H$5107,JU!$F$5107:$F$5107,WS!$A29) -> 0 | AF29: =SUMIFS(JU!$K$5107:$K$5107,JU!$I$5107:$I$5107,WS!$A29) -> 0 | AH29: =SUMIFS(JU!$H$5107:$H$5107,JU!$F$5107:$F$5107,WS!$A29) -> 0 | AI29: =SUMIFS(JU!$K$5107:$K$5107,JU!$I$5107:$I$5107,WS!$A29) -> 0 | AK29: =SUMIFS(JU!$H$5107:$H$5107,JU!$F$5107:$F$5107,WS!$A29) -> 0 | AL29: =SUMIFS(JU!$K$5107:$K$5107,JU!$I$5107:$I$5107,WS!$A29) -> 0
A30: 1301 | B30: Persediaan Tanah dalam Pengembangan | C30: 1500000000 | D30: =SUMIFS(JU!$H$5:$H$178,JU!$F$5:$F$178,WS!$A30) -> 96523717 | E30: =SUMIFS(JU!$K$5:$K$178,JU!$I$5:$I$178,WS!$A30) -> 0 | F30: =C30+D30-E30 -> 1596523717 | G30: =SUMIFS(JU!$H$180:$H$440,JU!$F$180:$F$440,WS!$A30) -> 1074680000 | H30: =SUMIFS(JU!$K$180:$K$440,JU!$I$180:$I$440,WS!$A30) -> 0 | I30: =F30+G30-H30 -> 2671203717 | J30: =SUMIFS(JU!$H$441:$H$695,JU!$F$441:$F$695,WS!$A30) -> 1260750000 | K30: =SUMIFS(JU!$K$441:$K$695,JU!$I$441:$I$695,WS!$A30) -> 0 | L30: =I30+J30-K30 -> 3931953717 | M30: =SUMIFS(JU!$H$696:$H$1062,JU!$F$696:$F$1062,$A30) -> 75400000 | N30: =SUMIFS(JU!$K$696:$K$1062,JU!$I$696:$I$1062,WS!$A30) -> 0 | O30: =L30+M30-N30 -> 4007353717 | P30: =SUMIFS(JU!$H$1063:$H$5007,JU!$F$1063:$F$5007,WS!$A30) -> 601750000 | Q30: =SUMIFS(JU!$K$1063:$K$5007,JU!$I$1063:$I$5007,WS!$A30) -> 128000000 | R30: =O30+P30-Q30 -> 4481103717 | S30: =SUMIFS(JU!$H$5107:$H$5107,JU!$F$5107:$F$5107,WS!$A30) -> 0 | T30: =SUMIFS(JU!$K$5107:$K$5107,JU!$I$5107:$I$5107,WS!$A30) -> 0 | U30: =R30+S30-T30 -> 4481103717 | V30: =SUMIFS(JU!$H$5107:$H$5107,JU!$F$5107:$F$5107,WS!$A30) -> 0 | W30: =SUMIFS(JU!$K$5107:$K$5107,JU!$I$5107:$I$5107,WS!$A30) -> 0 | X30: =U30+V30-W30 -> 4481103717 | Y30: =SUMIFS(JU!$H$5107:$H$5107,JU!$F$5107:$F$5107,WS!$A30) -> 0 | Z30: =SUMIFS(JU!$K$5107:$K$5107,JU!$I$5107:$I$5107,WS!$A30) -> 0 | AA30: =X30+Y30-Z30 -> 4481103717 | AB30: =SUMIFS(JU!$H$5107:$H$5107,JU!$F$5107:$F$5107,WS!$A30) -> 0 | AC30: =SUMIFS(JU!$K$5107:$K$5107,JU!$I$5107:$I$5107,WS!$A30) -> 0 | AD30: =AA30+AB30-AC30 -> 4481103717 | AE30: =SUMIFS(JU!$H$5107:$H$5107,JU!$F$5107:$F$5107,WS!$A30) -> 0 | AF30: =SUMIFS(JU!$K$5107:$K$5107,JU!$I$5107:$I$5107,WS!$A30) -> 0 | AG30: =AD30+AE30-AF30 -> 4481103717 | AH30: =SUMIFS(JU!$H$5107:$H$5107,JU!$F$5107:$F$5107,WS!$A30) -> 0 | AI30: =SUMIFS(JU!$K$5107:$K$5107,JU!$I$5107:$I$5107,WS!$A30) -> 0 | AJ30: =AG30+AH30-AI30 -> 4481103717 | AK30: =SUMIFS(JU!$H$5107:$H$5107,JU!$F$5107:$F$5107,WS!$A30) -> 0 | AL30: =SUMIFS(JU!$K$5107:$K$5107,JU!$I$5107:$I$5107,WS!$A30) -> 0 | AM30: =AJ30+AK30-AL30 -> 4481103717
A31: 1302 | B31: Persediaan Bangunan dalam Proses | C31: 0 | D31: =SUMIFS(JU!$H$5:$H$178,JU!$F$5:$F$178,WS!$A31) -> 213804059 | E31: =SUMIFS(JU!$K$5:$K$178,JU!$I$5:$I$178,WS!$A31) -> 0 | F31: =C31+D31-E31 -> 213804059 | G31: =SUMIFS(JU!$H$180:$H$440,JU!$F$180:$F$440,WS!$A31) -> 484664450 | H31: =SUMIFS(JU!$K$180:$K$440,JU!$I$180:$I$440,WS!$A31) -> 195200000 | I31: =F31+G31-H31 -> 503268509 | J31: =SUMIFS(JU!$H$441:$H$695,JU!$F$441:$F$695,WS!$A31) -> 731465000 | K31: =SUMIFS(JU!$K$441:$K$695,JU!$I$441:$I$695,WS!$A31) -> 195000000 | L31: =I31+J31-K31 -> 1039733509 | M31: =SUMIFS(JU!$H$696:$H$1062,JU!$F$696:$F$1062,$A31) -> 618415100 | N31: =SUMIFS(JU!$K$696:$K$1062,JU!$I$696:$I$1062,WS!$A31) -> 780000000 | O31: =L31+M31-N31 -> 878148609 | P31: =SUMIFS(JU!$H$1063:$H$5007,JU!$F$1063:$F$5007,WS!$A31) -> 889295500 | Q31: =SUMIFS(JU!$K$1063:$K$5007,JU!$I$1063:$I$5007,WS!$A31) -> 863600000 | R31: =O31+P31-Q31 -> 903844109 | S31: =SUMIFS(JU!$H$5107:$H$5107,JU!$F$5107:$F$5107,WS!$A31) -> 0 | T31: =SUMIFS(JU!$K$5107:$K$5107,JU!$I$5107:$I$5107,WS!$A31) -> 0 | U31: =R31+S31-T31 -> 903844109 | V31: =SUMIFS(JU!$H$5107:$H$5107,JU!$F$5107:$F$5107,WS!$A31) -> 0 | W31: =SUMIFS(JU!$K$5107:$K$5107,JU!$I$5107:$I$5107,WS!$A31) -> 0 | X31: =U31+V31-W31 -> 903844109 | Y31: =SUMIFS(JU!$H$5107:$H$5107,JU!$F$5107:$F$5107,WS!$A31) -> 0 | Z31: =SUMIFS(JU!$K$5107:$K$5107,JU!$I$5107:$I$5107,WS!$A31) -> 0 | AA31: =X31+Y31-Z31 -> 903844109 | AB31: =SUMIFS(JU!$H$5107:$H$5107,JU!$F$5107:$F$5107,WS!$A31) -> 0 | AC31: =SUMIFS(JU!$K$5107:$K$5107,JU!$I$5107:$I$5107,WS!$A31) -> 0 | AD31: =AA31+AB31-AC31 -> 903844109 | AE31: =SUMIFS(JU!$H$5107:$H$5107,JU!$F$5107:$F$5107,WS!$A31) -> 0 | AF31: =SUMIFS(JU!$K$5107:$K$5107,JU!$I$5107:$I$5107,WS!$A31) -> 0 | AG31: =AD31+AE31-AF31 -> 903844109 | AH31: =SUMIFS(JU!$H$5107:$H$5107,JU!$F$5107:$F$5107,WS!$A31) -> 0 | AI31: =SUMIFS(JU!$K$5107:$K$5107,JU!$I$5107:$I$5107,WS!$A31) -> 0 | AJ31: =AG31+AH31-AI31 -> 903844109 | AK31: =SUMIFS(JU!$H$5107:$H$5107,JU!$F$5107:$F$5107,WS!$A31) -> 0 | AL31: =SUMIFS(JU!$K$5107:$K$5107,JU!$I$5107:$I$5107,WS!$A31) -> 0 | AM31: =AJ31+AK31-AL31 -> 903844109
A32: 1303 | B32: Persediaan Properti Siap Jual | C32: 1025000003 | D32: =SUMIFS(JU!$H$5:$H$178,JU!$F$5:$F$178,WS!$A32) -> 0 | E32: =SUMIFS(JU!$K$5:$K$178,JU!$I$5:$I$178,WS!$A32) -> 0 | F32: =C32+D32-E32 -> 1025000003 | G32: =SUMIFS(JU!$H$180:$H$440,JU!$F$180:$F$440,WS!$A32) -> 0 | H32: =SUMIFS(JU!$K$180:$K$440,JU!$I$180:$I$440,WS!$A32) -> 0 | I32: =F32+G32-H32 -> 1025000003 | J32: =SUMIFS(JU!$H$441:$H$695,JU!$F$441:$F$695,WS!$A32) -> 0 | K32: =SUMIFS(JU!$K$441:$K$695,JU!$I$441:$I$695,WS!$A32) -> 0 | L32: =I32+J32-K32 -> 1025000003 | M32: =SUMIFS(JU!$H$696:$H$1062,JU!$F$696:$F$1062,$A32) -> 0 | N32: =SUMIFS(JU!$K$696:$K$1062,JU!$I$696:$I$1062,WS!$A32) -> 0 | O32: =L32+M32-N32 -> 1025000003 | P32: =SUMIFS(JU!$H$1063:$H$5007,JU!$F$1063:$F$5007,WS!$A32) -> 0 | Q32: =SUMIFS(JU!$K$1063:$K$5007,JU!$I$1063:$I$5007,WS!$A32) -> 0 | R32: =O32+P32-Q32 -> 1025000003 | S32: =SUMIFS(JU!$H$5107:$H$5107,JU!$F$5107:$F$5107,WS!$A32) -> 0 | T32: =SUMIFS(JU!$K$5107:$K$5107,JU!$I$5107:$I$5107,WS!$A32) -> 0 | U32: =R32+S32-T32 -> 1025000003 | V32: =SUMIFS(JU!$H$5107:$H$5107,JU!$F$5107:$F$5107,WS!$A32) -> 0 | W32: =SUMIFS(JU!$K$5107:$K$5107,JU!$I$5107:$I$5107,WS!$A32) -> 0 | X32: =U32+V32-W32 -> 1025000003 | Y32: =SUMIFS(JU!$H$5107:$H$5107,JU!$F$5107:$F$5107,WS!$A32) -> 0 | Z32: =SUMIFS(JU!$K$5107:$K$5107,JU!$I$5107:$I$5107,WS!$A32) -> 0 | AA32: =X32+Y32-Z32 -> 1025000003 | AB32: =SUMIFS(JU!$H$5107:$H$5107,JU!$F$5107:$F$5107,WS!$A32) -> 0 | AC32: =SUMIFS(JU!$K$5107:$K$5107,JU!$I$5107:$I$5107,WS!$A32) -> 0 | AD32: =AA32+AB32-AC32 -> 1025000003 | AE32: =SUMIFS(JU!$H$5107:$H$5107,JU!$F$5107:$F$5107,WS!$A32) -> 0 | AF32: =SUMIFS(JU!$K$5107:$K$5107,JU!$I$5107:$I$5107,WS!$A32) -> 0 | AG32: =AD32+AE32-AF32 -> 1025000003 | AH32: =SUMIFS(JU!$H$5107:$H$5107,JU!$F$5107:$F$5107,WS!$A32) -> 0 | AI32: =SUMIFS(JU!$K$5107:$K$5107,JU!$I$5107:$I$5107,WS!$A32) -> 0 | AJ32: =AG32+AH32-AI32 -> 1025000003 | AK32: =SUMIFS(JU!$H$5107:$H$5107,JU!$F$5107:$F$5107,WS!$A32) -> 0 | AL32: =SUMIFS(JU!$K$5107:$K$5107,JU!$I$5107:$I$5107,WS!$A32) -> 0 | AM32: =AJ32+AK32-AL32 -> 1025000003
A33: 1304 | B33: Persediaan Bahan Baku | C33: 0 | D33: =SUMIFS(JU!$H$5:$H$178,JU!$F$5:$F$178,WS!$A33) -> 0 | E33: =SUMIFS(JU!$K$5:$K$178,JU!$I$5:$I$178,WS!$A33) -> 0 | F33: =C33+D33-E33 -> 0 | G33: =SUMIFS(JU!$H$180:$H$440,JU!$F$180:$F$440,WS!$A33) -> 0 | H33: =SUMIFS(JU!$K$180:$K$440,JU!$I$180:$I$440,WS!$A33) -> 0 | I33: =F33+G33-H33 -> 0 | J33: =SUMIFS(JU!$H$441:$H$695,JU!$F$441:$F$695,WS!$A33) -> 0 | K33: =SUMIFS(JU!$K$441:$K$695,JU!$I$441:$I$695,WS!$A33) -> 0 | L33: =I33+J33-K33 -> 0 | M33: =SUMIFS(JU!$H$696:$H$1062,JU!$F$696:$F$1062,$A33) -> 0 | N33: =SUMIFS(JU!$K$696:$K$1062,JU!$I$696:$I$1062,WS!$A33) -> 0 | O33: =L33+M33-N33 -> 0 | P33: =SUMIFS(JU!$H$1063:$H$5007,JU!$F$1063:$F$5007,WS!$A33) -> 0 | Q33: =SUMIFS(JU!$K$1063:$K$5007,JU!$I$1063:$I$5007,WS!$A33) -> 0 | R33: =O33+P33-Q33 -> 0 | S33: =SUMIFS(JU!$H$5107:$H$5107,JU!$F$5107:$F$5107,WS!$A33) -> 0 | T33: =SUMIFS(JU!$K$5107:$K$5107,JU!$I$5107:$I$5107,WS!$A33) -> 0 | U33: =R33+S33-T33 -> 0 | V33: =SUMIFS(JU!$H$5107:$H$5107,JU!$F$5107:$F$5107,WS!$A33) -> 0 | W33: =SUMIFS(JU!$K$5107:$K$5107,JU!$I$5107:$I$5107,WS!$A33) -> 0 | X33: =U33+V33-W33 -> 0 | Y33: =SUMIFS(JU!$H$5107:$H$5107,JU!$F$5107:$F$5107,WS!$A33) -> 0 | Z33: =SUMIFS(JU!$K$5107:$K$5107,JU!$I$5107:$I$5107,WS!$A33) -> 0 | AA33: =X33+Y33-Z33 -> 0 | AB33: =SUMIFS(JU!$H$5107:$H$5107,JU!$F$5107:$F$5107,WS!$A33) -> 0 | AC33: =SUMIFS(JU!$K$5107:$K$5107,JU!$I$5107:$I$5107,WS!$A33) -> 0 | AD33: =AA33+AB33-AC33 -> 0 | AE33: =SUMIFS(JU!$H$5107:$H$5107,JU!$F$5107:$F$5107,WS!$A33) -> 0 | AF33: =SUMIFS(JU!$K$5107:$K$5107,JU!$I$5107:$I$5107,WS!$A33) -> 0 | AG33: =AD33+AE33-AF33 -> 0 | AH33: =SUMIFS(JU!$H$5107:$H$5107,JU!$F$5107:$F$5107,WS!$A33) -> 0 | AI33: =SUMIFS(JU!$K$5107:$K$5107,JU!$I$5107:$I$5107,WS!$A33) -> 0 | AJ33: =AG33+AH33-AI33 -> 0 | AK33: =SUMIFS(JU!$H$5107:$H$5107,JU!$F$5107:$F$5107,WS!$A33) -> 0 | AL33: =SUMIFS(JU!$K$5107:$K$5107,JU!$I$5107:$I$5107,WS!$A33) -> 0 | AM33: =AJ33+AK33-AL33 -> 0
A34: 1305 | B34: Persediaan Barang dalam Proses | C34: 0 | D34: =SUMIFS(JU!$H$5:$H$178,JU!$F$5:$F$178,WS!$A34) -> 0 | E34: =SUMIFS(JU!$K$5:$K$178,JU!$I$5:$I$178,WS!$A34) -> 0 | F34: =C34+D34-E34 -> 0 | G34: =SUMIFS(JU!$H$180:$H$440,JU!$F$180:$F$440,WS!$A34) -> 0 | H34: =SUMIFS(JU!$K$180:$K$440,JU!$I$180:$I$440,WS!$A34) -> 0 | I34: =F34+G34-H34 -> 0 | J34: =SUMIFS(JU!$H$441:$H$695,JU!$F$441:$F$695,WS!$A34) -> 0 | K34: =SUMIFS(JU!$K$441:$K$695,JU!$I$441:$I$695,WS!$A34) -> 0 | L34: =I34+J34-K34 -> 0 | M34: =SUMIFS(JU!$H$696:$H$1062,JU!$F$696:$F$1062,$A34) -> 0 | N34: =SUMIFS(JU!$K$696:$K$1062,JU!$I$696:$I$1062,WS!$A34) -> 0 | O34: =L34+M34-N34 -> 0 | P34: =SUMIFS(JU!$H$1063:$H$5007,JU!$F$1063:$F$5007,WS!$A34) -> 0 | Q34: =SUMIFS(JU!$K$1063:$K$5007,JU!$I$1063:$I$5007,WS!$A34) -> 0 | R34: =O34+P34-Q34 -> 0 | S34: =SUMIFS(JU!$H$5107:$H$5107,JU!$F$5107:$F$5107,WS!$A34) -> 0 | T34: =SUMIFS(JU!$K$5107:$K$5107,JU!$I$5107:$I$5107,WS!$A34) -> 0 | U34: =R34+S34-T34 -> 0 | V34: =SUMIFS(JU!$H$5107:$H$5107,JU!$F$5107:$F$5107,WS!$A34) -> 0 | W34: =SUMIFS(JU!$K$5107:$K$5107,JU!$I$5107:$I$5107,WS!$A34) -> 0 | X34: =U34+V34-W34 -> 0 | Y34: =SUMIFS(JU!$H$5107:$H$5107,JU!$F$5107:$F$5107,WS!$A34) -> 0 | Z34: =SUMIFS(JU!$K$5107:$K$5107,JU!$I$5107:$I$5107,WS!$A34) -> 0 | AA34: =X34+Y34-Z34 -> 0 | AB34: =SUMIFS(JU!$H$5107:$H$5107,JU!$F$5107:$F$5107,WS!$A34) -> 0 | AC34: =SUMIFS(JU!$K$5107:$K$5107,JU!$I$5107:$I$5107,WS!$A34) -> 0 | AD34: =AA34+AB34-AC34 -> 0 | AE34: =SUMIFS(JU!$H$5107:$H$5107,JU!$F$5107:$F$5107,WS!$A34) -> 0 | AF34: =SUMIFS(JU!$K$5107:$K$5107,JU!$I$5107:$I$5107,WS!$A34) -> 0 | AG34: =AD34+AE34-AF34 -> 0 | AH34: =SUMIFS(JU!$H$5107:$H$5107,JU!$F$5107:$F$5107,WS!$A34) -> 0 | AI34: =SUMIFS(JU!$K$5107:$K$5107,JU!$I$5107:$I$5107,WS!$A34) -> 0 | AJ34: =AG34+AH34-AI34 -> 0 | AK34: =SUMIFS(JU!$H$5107:$H$5107,JU!$F$5107:$F$5107,WS!$A34) -> 0 | AL34: =SUMIFS(JU!$K$5107:$K$5107,JU!$I$5107:$I$5107,WS!$A34) -> 0 | AM34: =AJ34+AK34-AL34 -> 0
A35: 1306 | B35: Persediaan Barang Jadi | C35: 0 | D35: =SUMIFS(JU!$H$5:$H$178,JU!$F$5:$F$178,WS!$A35) -> 0 | E35: =SUMIFS(JU!$K$5:$K$178,JU!$I$5:$I$178,WS!$A35) -> 0 | F35: =C35+D35-E35 -> 0 | G35: =SUMIFS(JU!$H$180:$H$440,JU!$F$180:$F$440,WS!$A35) -> 0 | H35: =SUMIFS(JU!$K$180:$K$440,JU!$I$180:$I$440,WS!$A35) -> 0 | I35: =F35+G35-H35 -> 0 | J35: =SUMIFS(JU!$H$441:$H$695,JU!$F$441:$F$695,WS!$A35) -> 0 | K35: =SUMIFS(JU!$K$441:$K$695,JU!$I$441:$I$695,WS!$A35) -> 0 | L35: =I35+J35-K35 -> 0 | M35: =SUMIFS(JU!$H$696:$H$1062,JU!$F$696:$F$1062,$A35) -> 0 | N35: =SUMIFS(JU!$K$696:$K$1062,JU!$I$696:$I$1062,WS!$A35) -> 0 | O35: =L35+M35-N35 -> 0 | P35: =SUMIFS(JU!$H$1063:$H$5007,JU!$F$1063:$F$5007,WS!$A35) -> 0 | Q35: =SUMIFS(JU!$K$1063:$K$5007,JU!$I$1063:$I$5007,WS!$A35) -> 0 | R35: =O35+P35-Q35 -> 0 | S35: =SUMIFS(JU!$H$5107:$H$5107,JU!$F$5107:$F$5107,WS!$A35) -> 0 | T35: =SUMIFS(JU!$K$5107:$K$5107,JU!$I$5107:$I$5107,WS!$A35) -> 0 | U35: =R35+S35-T35 -> 0 | V35: =SUMIFS(JU!$H$5107:$H$5107,JU!$F$5107:$F$5107,WS!$A35) -> 0 | W35: =SUMIFS(JU!$K$5107:$K$5107,JU!$I$5107:$I$5107,WS!$A35) -> 0 | X35: =U35+V35-W35 -> 0 | Y35: =SUMIFS(JU!$H$5107:$H$5107,JU!$F$5107:$F$5107,WS!$A35) -> 0 | Z35: =SUMIFS(JU!$K$5107:$K$5107,JU!$I$5107:$I$5107,WS!$A35) -> 0 | AA35: =X35+Y35-Z35 -> 0 | AB35: =SUMIFS(JU!$H$5107:$H$5107,JU!$F$5107:$F$5107,WS!$A35) -> 0 | AC35: =SUMIFS(JU!$K$5107:$K$5107,JU!$I$5107:$I$5107,WS!$A35) -> 0 | AD35: =AA35+AB35-AC35 -> 0 | AE35: =SUMIFS(JU!$H$5107:$H$5107,JU!$F$5107:$F$5107,WS!$A35) -> 0 | AF35: =SUMIFS(JU!$K$5107:$K$5107,JU!$I$5107:$I$5107,WS!$A35) -> 0 | AG35: =AD35+AE35-AF35 -> 0 | AH35: =SUMIFS(JU!$H$5107:$H$5107,JU!$F$5107:$F$5107,WS!$A35) -> 0 | AI35: =SUMIFS(JU!$K$5107:$K$5107,JU!$I$5107:$I$5107,WS!$A35) -> 0 | AJ35: =AG35+AH35-AI35 -> 0 | AK35: =SUMIFS(JU!$H$5107:$H$5107,JU!$F$5107:$F$5107,WS!$A35) -> 0 | AL35: =SUMIFS(JU!$K$5107:$K$5107,JU!$I$5107:$I$5107,WS!$A35) -> 0 | AM35: =AJ35+AK35-AL35 -> 0
A36: Total Persediaan | C36: 2525000003 | D36: =SUMIFS(JU!$H$5:$H$178,JU!$F$5:$F$178,WS!$A36) -> 0 | E36: =SUMIFS(JU!$K$5:$K$178,JU!$I$5:$I$178,WS!$A36) -> 0 | F36: =SUM(F30:F35) -> 2835327779 | G36: =SUMIFS(JU!$H$180:$H$440,JU!$F$180:$F$440,WS!$A36) -> 0 | H36: =SUMIFS(JU!$K$180:$K$440,JU!$I$180:$I$440,WS!$A36) -> 0 | I36: =SUM(I30:I35) -> 4199472229 | J36: =SUMIFS(JU!$H$441:$H$695,JU!$F$441:$F$695,WS!$A36) -> 0 | K36: =SUMIFS(JU!$K$441:$K$695,JU!$I$441:$I$695,WS!$A36) -> 0 | L36: =SUM(L30:L35) -> 5996687229 | M36: =SUMIFS(JU!$H$696:$H$1062,JU!$F$696:$F$1062,$A36) -> 0 | N36: =SUMIFS(JU!$K$696:$K$1062,JU!$I$696:$I$1062,WS!$A36) -> 0 | O36: =SUM(O30:O35) -> 5910502329 | P36: =SUMIFS(JU!$H$1063:$H$5007,JU!$F$1063:$F$5007,WS!$A36) -> 0 | Q36: =SUMIFS(JU!$K$1063:$K$5007,JU!$I$1063:$I$5007,WS!$A36) -> 0 | R36: =SUM(R30:R35) -> 6409947829 | S36: =SUMIFS(JU!$H$5107:$H$5107,JU!$F$5107:$F$5107,WS!$A36) -> 0 | T36: =SUMIFS(JU!$K$5107:$K$5107,JU!$I$5107:$I$5107,WS!$A36) -> 0 | U36: =SUM(U30:U35) -> 6409947829 | V36: =SUMIFS(JU!$H$5107:$H$5107,JU!$F$5107:$F$5107,WS!$A36) -> 0 | W36: =SUMIFS(JU!$K$5107:$K$5107,JU!$I$5107:$I$5107,WS!$A36) -> 0 | X36: =SUM(X30:X35) -> 6409947829 | Y36: =SUMIFS(JU!$H$5107:$H$5107,JU!$F$5107:$F$5107,WS!$A36) -> 0 | Z36: =SUMIFS(JU!$K$5107:$K$5107,JU!$I$5107:$I$5107,WS!$A36) -> 0 | AA36: =SUM(AA30:AA35) -> 6409947829 | AB36: =SUMIFS(JU!$H$5107:$H$5107,JU!$F$5107:$F$5107,WS!$A36) -> 0 | AC36: =SUMIFS(JU!$K$5107:$K$5107,JU!$I$5107:$I$5107,WS!$A36) -> 0 | AD36: =SUM(AD30:AD35) -> 6409947829 | AE36: =SUMIFS(JU!$H$5107:$H$5107,JU!$F$5107:$F$5107,WS!$A36) -> 0 | AF36: =SUMIFS(JU!$K$5107:$K$5107,JU!$I$5107:$I$5107,WS!$A36) -> 0 | AG36: =SUM(AG30:AG35) -> 6409947829 | AH36: =SUMIFS(JU!$H$5107:$H$5107,JU!$F$5107:$F$5107,WS!$A36) -> 0 | AI36: =SUMIFS(JU!$K$5107:$K$5107,JU!$I$5107:$I$5107,WS!$A36) -> 0 | AJ36: =SUM(AJ30:AJ35) -> 6409947829 | AK36: =SUMIFS(JU!$H$5107:$H$5107,JU!$F$5107:$F$5107,WS!$A36) -> 0 | AL36: =SUMIFS(JU!$K$5107:$K$5107,JU!$I$5107:$I$5107,WS!$A36) -> 0 | AM36: =SUM(AM30:AM35) -> 6409947829
A37: Total Aset Lancar | C37: 4.4287661e+09 | D37: =SUMIFS(JU!$H$5:$H$178,JU!$F$5:$F$178,WS!$A37) -> 0 | E37: =SUMIFS(JU!$K$5:$K$178,JU!$I$5:$I$178,WS!$A37) -> 0 | F37: =F18+F28+F36 -> 4.3132646e+09 | G37: =SUMIFS(JU!$H$180:$H$440,JU!$F$180:$F$440,WS!$A37) -> 0 | H37: =SUMIFS(JU!$K$180:$K$440,JU!$I$180:$I$440,WS!$A37) -> 0 | I37: =I18+I28+I36 -> 5.8752804e+09 | J37: =SUMIFS(JU!$H$441:$H$695,JU!$F$441:$F$695,WS!$A37) -> 0 | K37: =SUMIFS(JU!$K$441:$K$695,JU!$I$441:$I$695,WS!$A37) -> 0 | L37: =L18+L28+L36 -> 8.6368473e+09 | M37: =SUMIFS(JU!$H$696:$H$1062,JU!$F$696:$F$1062,$A37) -> 0 | N37: =SUMIFS(JU!$K$696:$K$1062,JU!$I$696:$I$1062,WS!$A37) -> 0 | O37: =O18+O28+O36 -> 8.606458e+09 | P37: =SUMIFS(JU!$H$1063:$H$5007,JU!$F$1063:$F$5007,WS!$A37) -> 0 | Q37: =SUMIFS(JU!$K$1063:$K$5007,JU!$I$1063:$I$5007,WS!$A37) -> 0 | R37: =R18+R28+R36 -> 1.1180257e+10 | S37: =SUMIFS(JU!$H$5107:$H$5107,JU!$F$5107:$F$5107,WS!$A37) -> 0 | T37: =SUMIFS(JU!$K$5107:$K$5107,JU!$I$5107:$I$5107,WS!$A37) -> 0 | U37: =U18+U28+U36 -> 1.1180257e+10 | V37: =SUMIFS(JU!$H$5107:$H$5107,JU!$F$5107:$F$5107,WS!$A37) -> 0 | W37: =SUMIFS(JU!$K$5107:$K$5107,JU!$I$5107:$I$5107,WS!$A37) -> 0 | X37: =X18+X28+X36 -> 1.1180257e+10 | Y37: =SUMIFS(JU!$H$5107:$H$5107,JU!$F$5107:$F$5107,WS!$A37) -> 0 | Z37: =SUMIFS(JU!$K$5107:$K$5107,JU!$I$5107:$I$5107,WS!$A37) -> 0 | AA37: =AA18+AA28+AA36 -> 1.1180257e+10 | AB37: =SUMIFS(JU!$H$5107:$H$5107,JU!$F$5107:$F$5107,WS!$A37) -> 0 | AC37: =SUMIFS(JU!$K$5107:$K$5107,JU!$I$5107:$I$5107,WS!$A37) -> 0 | AD37: =AD18+AD28+AD36 -> 1.1180257e+10 | AE37: =SUMIFS(JU!$H$5107:$H$5107,JU!$F$5107:$F$5107,WS!$A37) -> 0 | AF37: =SUMIFS(JU!$K$5107:$K$5107,JU!$I$5107:$I$5107,WS!$A37) -> 0 | AG37: =AG18+AG28+AG36 -> 1.1180257e+10 | AH37: =SUMIFS(JU!$H$5107:$H$5107,JU!$F$5107:$F$5107,WS!$A37) -> 0 | AI37: =SUMIFS(JU!$K$5107:$K$5107,JU!$I$5107:$I$5107,WS!$A37) -> 0 | AJ37: =AJ18+AJ28+AJ36 -> 1.1180257e+10 | AK37: =SUMIFS(JU!$H$5107:$H$5107,JU!$F$5107:$F$5107,WS!$A37) -> 0 | AL37: =SUMIFS(JU!$K$5107:$K$5107,JU!$I$5107:$I$5107,WS!$A37) -> 0 | AM37: =AM18+AM28+AM36 -> 1.1180257e+10
A38: Aset Tidak Lancar | D38: =SUMIFS(JU!$H$5:$H$178,JU!$F$5:$F$178,WS!$A38) -> 0 | E38: =SUMIFS(JU!$K$5:$K$178,JU!$I$5:$I$178,WS!$A38) -> 0 | G38: =SUMIFS(JU!$H$180:$H$440,JU!$F$180:$F$440,WS!$A38) -> 0 | H38: =SUMIFS(JU!$K$180:$K$440,JU!$I$180:$I$440,WS!$A38) -> 0 | J38: =SUMIFS(JU!$H$441:$H$695,JU!$F$441:$F$695,WS!$A38) -> 0 | K38: =SUMIFS(JU!$K$441:$K$695,JU!$I$441:$I$695,WS!$A38) -> 0 | M38: =SUMIFS(JU!$H$696:$H$1062,JU!$F$696:$F$1062,$A38) -> 0 | N38: =SUMIFS(JU!$K$696:$K$1062,JU!$I$696:$I$1062,WS!$A38) -> 0 | P38: =SUMIFS(JU!$H$1063:$H$5007,JU!$F$1063:$F$5007,WS!$A38) -> 0 | Q38: =SUMIFS(JU!$K$1063:$K$5007,JU!$I$1063:$I$5007,WS!$A38) -> 0 | S38: =SUMIFS(JU!$H$5107:$H$5107,JU!$F$5107:$F$5107,WS!$A38) -> 0 | T38: =SUMIFS(JU!$K$5107:$K$5107,JU!$I$5107:$I$5107,WS!$A38) -> 0 | V38: =SUMIFS(JU!$H$5107:$H$5107,JU!$F$5107:$F$5107,WS!$A38) -> 0 | W38: =SUMIFS(JU!$K$5107:$K$5107,JU!$I$5107:$I$5107,WS!$A38) -> 0 | Y38: =SUMIFS(JU!$H$5107:$H$5107,JU!$F$5107:$F$5107,WS!$A38) -> 0 | Z38: =SUMIFS(JU!$K$5107:$K$5107,JU!$I$5107:$I$5107,WS!$A38) -> 0 | AB38: =SUMIFS(JU!$H$5107:$H$5107,JU!$F$5107:$F$5107,WS!$A38) -> 0 | AC38: =SUMIFS(JU!$K$5107:$K$5107,JU!$I$5107:$I$5107,WS!$A38) -> 0 | AE38: =SUMIFS(JU!$H$5107:$H$5107,JU!$F$5107:$F$5107,WS!$A38) -> 0 | AF38: =SUMIFS(JU!$K$5107:$K$5107,JU!$I$5107:$I$5107,WS!$A38) -> 0 | AH38: =SUMIFS(JU!$H$5107:$H$5107,JU!$F$5107:$F$5107,WS!$A38) -> 0 | AI38: =SUMIFS(JU!$K$5107:$K$5107,JU!$I$5107:$I$5107,WS!$A38) -> 0 | AK38: =SUMIFS(JU!$H$5107:$H$5107,JU!$F$5107:$F$5107,WS!$A38) -> 0 | AL38: =SUMIFS(JU!$K$5107:$K$5107,JU!$I$5107:$I$5107,WS!$A38) -> 0
A39: 1401 | B39: Tanah dan Bangunan Investasi | C39: 990000000 | D39: =SUMIFS(JU!$H$5:$H$178,JU!$F$5:$F$178,WS!$A39) -> 577000000 | E39: =SUMIFS(JU!$K$5:$K$178,JU!$I$5:$I$178,WS!$A39) -> 0 | F39: =C39+D39-E39 -> 1567000000 | G39: =SUMIFS(JU!$H$180:$H$440,JU!$F$180:$F$440,WS!$A39) -> 0 | H39: =SUMIFS(JU!$K$180:$K$440,JU!$I$180:$I$440,WS!$A39) -> 0 | I39: =F39+G39-H39 -> 1567000000 | J39: =SUMIFS(JU!$H$441:$H$695,JU!$F$441:$F$695,WS!$A39) -> 16969718 | K39: =SUMIFS(JU!$K$441:$K$695,JU!$I$441:$I$695,WS!$A39) -> 0 | L39: =I39+J39-K39 -> 1583969718 | M39: =SUMIFS(JU!$H$696:$H$1062,JU!$F$696:$F$1062,$A39) -> 87217040 | N39: =SUMIFS(JU!$K$696:$K$1062,JU!$I$696:$I$1062,WS!$A39) -> 0 | O39: =L39+M39-N39 -> 1671186758 | P39: =SUMIFS(JU!$H$1063:$H$5007,JU!$F$1063:$F$5007,WS!$A39) -> 0 | Q39: =SUMIFS(JU!$K$1063:$K$5007,JU!$I$1063:$I$5007,WS!$A39) -> 0 | R39: =O39+P39-Q39 -> 1671186758 | S39: =SUMIFS(JU!$H$5107:$H$5107,JU!$F$5107:$F$5107,WS!$A39) -> 0 | T39: =SUMIFS(JU!$K$5107:$K$5107,JU!$I$5107:$I$5107,WS!$A39) -> 0 | U39: =R39+S39-T39 -> 1671186758 | V39: =SUMIFS(JU!$H$5107:$H$5107,JU!$F$5107:$F$5107,WS!$A39) -> 0 | W39: =SUMIFS(JU!$K$5107:$K$5107,JU!$I$5107:$I$5107,WS!$A39) -> 0 | X39: =U39+V39-W39 -> 1671186758 | Y39: =SUMIFS(JU!$H$5107:$H$5107,JU!$F$5107:$F$5107,WS!$A39) -> 0 | Z39: =SUMIFS(JU!$K$5107:$K$5107,JU!$I$5107:$I$5107,WS!$A39) -> 0 | AA39: =X39+Y39-Z39 -> 1671186758 | AB39: =SUMIFS(JU!$H$5107:$H$5107,JU!$F$5107:$F$5107,WS!$A39) -> 0 | AC39: =SUMIFS(JU!$K$5107:$K$5107,JU!$I$5107:$I$5107,WS!$A39) -> 0 | AD39: =AA39+AB39-AC39 -> 1671186758 | AE39: =SUMIFS(JU!$H$5107:$H$5107,JU!$F$5107:$F$5107,WS!$A39) -> 0 | AF39: =SUMIFS(JU!$K$5107:$K$5107,JU!$I$5107:$I$5107,WS!$A39) -> 0 | AG39: =AD39+AE39-AF39 -> 1671186758 | AH39: =SUMIFS(JU!$H$5107:$H$5107,JU!$F$5107:$F$5107,WS!$A39) -> 0 | AI39: =SUMIFS(JU!$K$5107:$K$5107,JU!$I$5107:$I$5107,WS!$A39) -> 0 | AJ39: =AG39+AH39-AI39 -> 1671186758 | AK39: =SUMIFS(JU!$H$5107:$H$5107,JU!$F$5107:$F$5107,WS!$A39) -> 0 | AL39: =SUMIFS(JU!$K$5107:$K$5107,JU!$I$5107:$I$5107,WS!$A39) -> 0 | AM39: =AJ39+AK39-AL39 -> 1671186758
A40: 1402 | B40: Gedung Kantor | C40: 0 | D40: =SUMIFS(JU!$H$5:$H$178,JU!$F$5:$F$178,WS!$A40) -> 0 | E40: =SUMIFS(JU!$K$5:$K$178,JU!$I$5:$I$178,WS!$A40) -> 0 | F40: =C40+D40-E40 -> 0 | G40: =SUMIFS(JU!$H$180:$H$440,JU!$F$180:$F$440,WS!$A40) -> 0 | H40: =SUMIFS(JU!$K$180:$K$440,JU!$I$180:$I$440,WS!$A40) -> 0 | I40: =F40+G40-H40 -> 0 | J40: =SUMIFS(JU!$H$441:$H$695,JU!$F$441:$F$695,WS!$A40) -> 0 | K40: =SUMIFS(JU!$K$441:$K$695,JU!$I$441:$I$695,WS!$A40) -> 0 | L40: =I40+J40-K40 -> 0 | M40: =SUMIFS(JU!$H$696:$H$1062,JU!$F$696:$F$1062,$A40) -> 0 | N40: =SUMIFS(JU!$K$696:$K$1062,JU!$I$696:$I$1062,WS!$A40) -> 0 | O40: =L40+M40-N40 -> 0 | P40: =SUMIFS(JU!$H$1063:$H$5007,JU!$F$1063:$F$5007,WS!$A40) -> 0 | Q40: =SUMIFS(JU!$K$1063:$K$5007,JU!$I$1063:$I$5007,WS!$A40) -> 0 | R40: =O40+P40-Q40 -> 0 | S40: =SUMIFS(JU!$H$5107:$H$5107,JU!$F$5107:$F$5107,WS!$A40) -> 0 | T40: =SUMIFS(JU!$K$5107:$K$5107,JU!$I$5107:$I$5107,WS!$A40) -> 0 | U40: =R40+S40-T40 -> 0 | V40: =SUMIFS(JU!$H$5107:$H$5107,JU!$F$5107:$F$5107,WS!$A40) -> 0 | W40: =SUMIFS(JU!$K$5107:$K$5107,JU!$I$5107:$I$5107,WS!$A40) -> 0 | X40: =U40+V40-W40 -> 0 | Y40: =SUMIFS(JU!$H$5107:$H$5107,JU!$F$5107:$F$5107,WS!$A40) -> 0 | Z40: =SUMIFS(JU!$K$5107:$K$5107,JU!$I$5107:$I$5107,WS!$A40) -> 0 | AA40: =X40+Y40-Z40 -> 0 | AB40: =SUMIFS(JU!$H$5107:$H$5107,JU!$F$5107:$F$5107,WS!$A40) -> 0 | AC40: =SUMIFS(JU!$K$5107:$K$5107,JU!$I$5107:$I$5107,WS!$A40) -> 0 | AD40: =AA40+AB40-AC40 -> 0 | AE40: =SUMIFS(JU!$H$5107:$H$5107,JU!$F$5107:$F$5107,WS!$A40) -> 0 | AF40: =SUMIFS(JU!$K$5107:$K$5107,JU!$I$5107:$I$5107,WS!$A40) -> 0 | AG40: =AD40+AE40-AF40 -> 0 | AH40: =SUMIFS(JU!$H$5107:$H$5107,JU!$F$5107:$F$5107,WS!$A40) -> 0 | AI40: =SUMIFS(JU!$K$5107:$K$5107,JU!$I$5107:$I$5107,WS!$A40) -> 0 | AJ40: =AG40+AH40-AI40 -> 0 | AK40: =SUMIFS(JU!$H$5107:$H$5107,JU!$F$5107:$F$5107,WS!$A40) -> 0 | AL40: =SUMIFS(JU!$K$5107:$K$5107,JU!$I$5107:$I$5107,WS!$A40) -> 0 | AM40: =AJ40+AK40-AL40 -> 0
A41: 1403 | B41: Akumulasi Penyusutan Gedung | C41: 0 | D41: =SUMIFS(JU!$H$5:$H$178,JU!$F$5:$F$178,WS!$A41) -> 0 | E41: =SUMIFS(JU!$K$5:$K$178,JU!$I$5:$I$178,WS!$A41) -> 0 | F41: =C41+D41-E41 -> 0 | G41: =SUMIFS(JU!$H$180:$H$440,JU!$F$180:$F$440,WS!$A41) -> 0 | H41: =SUMIFS(JU!$K$180:$K$440,JU!$I$180:$I$440,WS!$A41) -> 0 | I41: =F41+G41-H41 -> 0 | J41: =SUMIFS(JU!$H$441:$H$695,JU!$F$441:$F$695,WS!$A41) -> 0 | K41: =SUMIFS(JU!$K$441:$K$695,JU!$I$441:$I$695,WS!$A41) -> 0 | L41: =I41+J41-K41 -> 0 | M41: =SUMIFS(JU!$H$696:$H$1062,JU!$F$696:$F$1062,$A41) -> 0 | N41: =SUMIFS(JU!$K$696:$K$1062,JU!$I$696:$I$1062,WS!$A41) -> 0 | O41: =L41+M41-N41 -> 0 | P41: =SUMIFS(JU!$H$1063:$H$5007,JU!$F$1063:$F$5007,WS!$A41) -> 0 | Q41: =SUMIFS(JU!$K$1063:$K$5007,JU!$I$1063:$I$5007,WS!$A41) -> 0 | R41: =O41+P41-Q41 -> 0 | S41: =SUMIFS(JU!$H$5107:$H$5107,JU!$F$5107:$F$5107,WS!$A41) -> 0 | T41: =SUMIFS(JU!$K$5107:$K$5107,JU!$I$5107:$I$5107,WS!$A41) -> 0 | U41: =R41+S41-T41 -> 0 | V41: =SUMIFS(JU!$H$5107:$H$5107,JU!$F$5107:$F$5107,WS!$A41) -> 0 | W41: =SUMIFS(JU!$K$5107:$K$5107,JU!$I$5107:$I$5107,WS!$A41) -> 0 | X41: =U41+V41-W41 -> 0 | Y41: =SUMIFS(JU!$H$5107:$H$5107,JU!$F$5107:$F$5107,WS!$A41) -> 0 | Z41: =SUMIFS(JU!$K$5107:$K$5107,JU!$I$5107:$I$5107,WS!$A41) -> 0 | AA41: =X41+Y41-Z41 -> 0 | AB41: =SUMIFS(JU!$H$5107:$H$5107,JU!$F$5107:$F$5107,WS!$A41) -> 0 | AC41: =SUMIFS(JU!$K$5107:$K$5107,JU!$I$5107:$I$5107,WS!$A41) -> 0 | AD41: =AA41+AB41-AC41 -> 0 | AE41: =SUMIFS(JU!$H$5107:$H$5107,JU!$F$5107:$F$5107,WS!$A41) -> 0 | AF41: =SUMIFS(JU!$K$5107:$K$5107,JU!$I$5107:$I$5107,WS!$A41) -> 0 | AG41: =AD41+AE41-AF41 -> 0 | AH41: =SUMIFS(JU!$H$5107:$H$5107,JU!$F$5107:$F$5107,WS!$A41) -> 0 | AI41: =SUMIFS(JU!$K$5107:$K$5107,JU!$I$5107:$I$5107,WS!$A41) -> 0 | AJ41: =AG41+AH41-AI41 -> 0 | AK41: =SUMIFS(JU!$H$5107:$H$5107,JU!$F$5107:$F$5107,WS!$A41) -> 0 | AL41: =SUMIFS(JU!$K$5107:$K$5107,JU!$I$5107:$I$5107,WS!$A41) -> 0 | AM41: =AJ41+AK41-AL41 -> 0
A42: 1404 | B42: Peralatan dan Mesin | C42: 0 | D42: =SUMIFS(JU!$H$5:$H$178,JU!$F$5:$F$178,WS!$A42) -> 0 | E42: =SUMIFS(JU!$K$5:$K$178,JU!$I$5:$I$178,WS!$A42) -> 0 | F42: =C42+D42-E42 -> 0 | G42: =SUMIFS(JU!$H$180:$H$440,JU!$F$180:$F$440,WS!$A42) -> 0 | H42: =SUMIFS(JU!$K$180:$K$440,JU!$I$180:$I$440,WS!$A42) -> 0 | I42: =F42+G42-H42 -> 0 | J42: =SUMIFS(JU!$H$441:$H$695,JU!$F$441:$F$695,WS!$A42) -> 0 | K42: =SUMIFS(JU!$K$441:$K$695,JU!$I$441:$I$695,WS!$A42) -> 0 | L42: =I42+J42-K42 -> 0 | M42: =SUMIFS(JU!$H$696:$H$1062,JU!$F$696:$F$1062,$A42) -> 0 | N42: =SUMIFS(JU!$K$696:$K$1062,JU!$I$696:$I$1062,WS!$A42) -> 0 | O42: =L42+M42-N42 -> 0 | P42: =SUMIFS(JU!$H$1063:$H$5007,JU!$F$1063:$F$5007,WS!$A42) -> 0 | Q42: =SUMIFS(JU!$K$1063:$K$5007,JU!$I$1063:$I$5007,WS!$A42) -> 0 | R42: =O42+P42-Q42 -> 0 | S42: =SUMIFS(JU!$H$5107:$H$5107,JU!$F$5107:$F$5107,WS!$A42) -> 0 | T42: =SUMIFS(JU!$K$5107:$K$5107,JU!$I$5107:$I$5107,WS!$A42) -> 0 | U42: =R42+S42-T42 -> 0 | V42: =SUMIFS(JU!$H$5107:$H$5107,JU!$F$5107:$F$5107,WS!$A42) -> 0 | W42: =SUMIFS(JU!$K$5107:$K$5107,JU!$I$5107:$I$5107,WS!$A42) -> 0 | X42: =U42+V42-W42 -> 0 | Y42: =SUMIFS(JU!$H$5107:$H$5107,JU!$F$5107:$F$5107,WS!$A42) -> 0 | Z42: =SUMIFS(JU!$K$5107:$K$5107,JU!$I$5107:$I$5107,WS!$A42) -> 0 | AA42: =X42+Y42-Z42 -> 0 | AB42: =SUMIFS(JU!$H$5107:$H$5107,JU!$F$5107:$F$5107,WS!$A42) -> 0 | AC42: =SUMIFS(JU!$K$5107:$K$5107,JU!$I$5107:$I$5107,WS!$A42) -> 0 | AD42: =AA42+AB42-AC42 -> 0 | AE42: =SUMIFS(JU!$H$5107:$H$5107,JU!$F$5107:$F$5107,WS!$A42) -> 0 | AF42: =SUMIFS(JU!$K$5107:$K$5107,JU!$I$5107:$I$5107,WS!$A42) -> 0 | AG42: =AD42+AE42-AF42 -> 0 | AH42: =SUMIFS(JU!$H$5107:$H$5107,JU!$F$5107:$F$5107,WS!$A42) -> 0 | AI42: =SUMIFS(JU!$K$5107:$K$5107,JU!$I$5107:$I$5107,WS!$A42) -> 0 | AJ42: =AG42+AH42-AI42 -> 0 | AK42: =SUMIFS(JU!$H$5107:$H$5107,JU!$F$5107:$F$5107,WS!$A42) -> 0 | AL42: =SUMIFS(JU!$K$5107:$K$5107,JU!$I$5107:$I$5107,WS!$A42) -> 0 | AM42: =AJ42+AK42-AL42 -> 0
A43: 1405 | B43: Akumulasi Penyusutan Peralatan | C43: 0 | D43: =SUMIFS(JU!$H$5:$H$178,JU!$F$5:$F$178,WS!$A43) -> 0 | E43: =SUMIFS(JU!$K$5:$K$178,JU!$I$5:$I$178,WS!$A43) -> 0 | F43: =C43+D43-E43 -> 0 | G43: =SUMIFS(JU!$H$180:$H$440,JU!$F$180:$F$440,WS!$A43) -> 0 | H43: =SUMIFS(JU!$K$180:$K$440,JU!$I$180:$I$440,WS!$A43) -> 0 | I43: =F43+G43-H43 -> 0 | J43: =SUMIFS(JU!$H$441:$H$695,JU!$F$441:$F$695,WS!$A43) -> 0 | K43: =SUMIFS(JU!$K$441:$K$695,JU!$I$441:$I$695,WS!$A43) -> 0 | L43: =I43+J43-K43 -> 0 | M43: =SUMIFS(JU!$H$696:$H$1062,JU!$F$696:$F$1062,$A43) -> 0 | N43: =SUMIFS(JU!$K$696:$K$1062,JU!$I$696:$I$1062,WS!$A43) -> 0 | O43: =L43+M43-N43 -> 0 | P43: =SUMIFS(JU!$H$1063:$H$5007,JU!$F$1063:$F$5007,WS!$A43) -> 0 | Q43: =SUMIFS(JU!$K$1063:$K$5007,JU!$I$1063:$I$5007,WS!$A43) -> 0 | R43: =O43+P43-Q43 -> 0 | S43: =SUMIFS(JU!$H$5107:$H$5107,JU!$F$5107:$F$5107,WS!$A43) -> 0 | T43: =SUMIFS(JU!$K$5107:$K$5107,JU!$I$5107:$I$5107,WS!$A43) -> 0 | U43: =R43+S43-T43 -> 0 | V43: =SUMIFS(JU!$H$5107:$H$5107,JU!$F$5107:$F$5107,WS!$A43) -> 0 | W43: =SUMIFS(JU!$K$5107:$K$5107,JU!$I$5107:$I$5107,WS!$A43) -> 0 | X43: =U43+V43-W43 -> 0 | Y43: =SUMIFS(JU!$H$5107:$H$5107,JU!$F$5107:$F$5107,WS!$A43) -> 0 | Z43: =SUMIFS(JU!$K$5107:$K$5107,JU!$I$5107:$I$5107,WS!$A43) -> 0 | AA43: =X43+Y43-Z43 -> 0 | AB43: =SUMIFS(JU!$H$5107:$H$5107,JU!$F$5107:$F$5107,WS!$A43) -> 0 | AC43: =SUMIFS(JU!$K$5107:$K$5107,JU!$I$5107:$I$5107,WS!$A43) -> 0 | AD43: =AA43+AB43-AC43 -> 0 | AE43: =SUMIFS(JU!$H$5107:$H$5107,JU!$F$5107:$F$5107,WS!$A43) -> 0 | AF43: =SUMIFS(JU!$K$5107:$K$5107,JU!$I$5107:$I$5107,WS!$A43) -> 0 | AG43: =AD43+AE43-AF43 -> 0 | AH43: =SUMIFS(JU!$H$5107:$H$5107,JU!$F$5107:$F$5107,WS!$A43) -> 0 | AI43: =SUMIFS(JU!$K$5107:$K$5107,JU!$I$5107:$I$5107,WS!$A43) -> 0 | AJ43: =AG43+AH43-AI43 -> 0 | AK43: =SUMIFS(JU!$H$5107:$H$5107,JU!$F$5107:$F$5107,WS!$A43) -> 0 | AL43: =SUMIFS(JU!$K$5107:$K$5107,JU!$I$5107:$I$5107,WS!$A43) -> 0 | AM43: =AJ43+AK43-AL43 -> 0
A44: 1406 | B44: Kendaraan Operasional | C44: 0 | D44: =SUMIFS(JU!$H$5:$H$178,JU!$F$5:$F$178,WS!$A44) -> 0 | E44: =SUMIFS(JU!$K$5:$K$178,JU!$I$5:$I$178,WS!$A44) -> 0 | F44: =C44+D44-E44 -> 0 | G44: =SUMIFS(JU!$H$180:$H$440,JU!$F$180:$F$440,WS!$A44) -> 0 | H44: =SUMIFS(JU!$K$180:$K$440,JU!$I$180:$I$440,WS!$A44) -> 0 | I44: =F44+G44-H44 -> 0 | J44: =SUMIFS(JU!$H$441:$H$695,JU!$F$441:$F$695,WS!$A44) -> 0 | K44: =SUMIFS(JU!$K$441:$K$695,JU!$I$441:$I$695,WS!$A44) -> 0 | L44: =I44+J44-K44 -> 0 | M44: =SUMIFS(JU!$H$696:$H$1062,JU!$F$696:$F$1062,$A44) -> 0 | N44: =SUMIFS(JU!$K$696:$K$1062,JU!$I$696:$I$1062,WS!$A44) -> 0 | O44: =L44+M44-N44 -> 0 | P44: =SUMIFS(JU!$H$1063:$H$5007,JU!$F$1063:$F$5007,WS!$A44) -> 36000000 | Q44: =SUMIFS(JU!$K$1063:$K$5007,JU!$I$1063:$I$5007,WS!$A44) -> 0 | R44: =O44+P44-Q44 -> 36000000 | S44: =SUMIFS(JU!$H$5107:$H$5107,JU!$F$5107:$F$5107,WS!$A44) -> 0 | T44: =SUMIFS(JU!$K$5107:$K$5107,JU!$I$5107:$I$5107,WS!$A44) -> 0 | U44: =R44+S44-T44 -> 36000000 | V44: =SUMIFS(JU!$H$5107:$H$5107,JU!$F$5107:$F$5107,WS!$A44) -> 0 | W44: =SUMIFS(JU!$K$5107:$K$5107,JU!$I$5107:$I$5107,WS!$A44) -> 0 | X44: =U44+V44-W44 -> 36000000 | Y44: =SUMIFS(JU!$H$5107:$H$5107,JU!$F$5107:$F$5107,WS!$A44) -> 0 | Z44: =SUMIFS(JU!$K$5107:$K$5107,JU!$I$5107:$I$5107,WS!$A44) -> 0 | AA44: =X44+Y44-Z44 -> 36000000 | AB44: =SUMIFS(JU!$H$5107:$H$5107,JU!$F$5107:$F$5107,WS!$A44) -> 0 | AC44: =SUMIFS(JU!$K$5107:$K$5107,JU!$I$5107:$I$5107,WS!$A44) -> 0 | AD44: =AA44+AB44-AC44 -> 36000000 | AE44: =SUMIFS(JU!$H$5107:$H$5107,JU!$F$5107:$F$5107,WS!$A44) -> 0 | AF44: =SUMIFS(JU!$K$5107:$K$5107,JU!$I$5107:$I$5107,WS!$A44) -> 0 | AG44: =AD44+AE44-AF44 -> 36000000 | AH44: =SUMIFS(JU!$H$5107:$H$5107,JU!$F$5107:$F$5107,WS!$A44) -> 0 | AI44: =SUMIFS(JU!$K$5107:$K$5107,JU!$I$5107:$I$5107,WS!$A44) -> 0 | AJ44: =AG44+AH44-AI44 -> 36000000 | AK44: =SUMIFS(JU!$H$5107:$H$5107,JU!$F$5107:$F$5107,WS!$A44) -> 0 | AL44: =SUMIFS(JU!$K$5107:$K$5107,JU!$I$5107:$I$5107,WS!$A44) -> 0 | AM44: =AJ44+AK44-AL44 -> 36000000
A45: 1407 | B45: Akumulasi Penyusutan Kendaraan | C45: 0 | D45: =SUMIFS(JU!$H$5:$H$178,JU!$F$5:$F$178,WS!$A45) -> 0 | E45: =SUMIFS(JU!$K$5:$K$178,JU!$I$5:$I$178,WS!$A45) -> 0 | F45: =C45+D45-E45 -> 0 | G45: =SUMIFS(JU!$H$180:$H$440,JU!$F$180:$F$440,WS!$A45) -> 0 | H45: =SUMIFS(JU!$K$180:$K$440,JU!$I$180:$I$440,WS!$A45) -> 0 | I45: =F45+G45-H45 -> 0 | J45: =SUMIFS(JU!$H$441:$H$695,JU!$F$441:$F$695,WS!$A45) -> 0 | K45: =SUMIFS(JU!$K$441:$K$695,JU!$I$441:$I$695,WS!$A45) -> 0 | L45: =I45+J45-K45 -> 0 | M45: =SUMIFS(JU!$H$696:$H$1062,JU!$F$696:$F$1062,$A45) -> 0 | N45: =SUMIFS(JU!$K$696:$K$1062,JU!$I$696:$I$1062,WS!$A45) -> 0 | O45: =L45+M45-N45 -> 0 | P45: =SUMIFS(JU!$H$1063:$H$5007,JU!$F$1063:$F$5007,WS!$A45) -> 0 | Q45: =SUMIFS(JU!$K$1063:$K$5007,JU!$I$1063:$I$5007,WS!$A45) -> 0 | R45: =O45+P45-Q45 -> 0 | S45: =SUMIFS(JU!$H$5107:$H$5107,JU!$F$5107:$F$5107,WS!$A45) -> 0 | T45: =SUMIFS(JU!$K$5107:$K$5107,JU!$I$5107:$I$5107,WS!$A45) -> 0 | U45: =R45+S45-T45 -> 0 | V45: =SUMIFS(JU!$H$5107:$H$5107,JU!$F$5107:$F$5107,WS!$A45) -> 0 | W45: =SUMIFS(JU!$K$5107:$K$5107,JU!$I$5107:$I$5107,WS!$A45) -> 0 | X45: =U45+V45-W45 -> 0 | Y45: =SUMIFS(JU!$H$5107:$H$5107,JU!$F$5107:$F$5107,WS!$A45) -> 0 | Z45: =SUMIFS(JU!$K$5107:$K$5107,JU!$I$5107:$I$5107,WS!$A45) -> 0 | AA45: =X45+Y45-Z45 -> 0 | AB45: =SUMIFS(JU!$H$5107:$H$5107,JU!$F$5107:$F$5107,WS!$A45) -> 0 | AC45: =SUMIFS(JU!$K$5107:$K$5107,JU!$I$5107:$I$5107,WS!$A45) -> 0 | AD45: =AA45+AB45-AC45 -> 0 | AE45: =SUMIFS(JU!$H$5107:$H$5107,JU!$F$5107:$F$5107,WS!$A45) -> 0 | AF45: =SUMIFS(JU!$K$5107:$K$5107,JU!$I$5107:$I$5107,WS!$A45) -> 0 | AG45: =AD45+AE45-AF45 -> 0 | AH45: =SUMIFS(JU!$H$5107:$H$5107,JU!$F$5107:$F$5107,WS!$A45) -> 0 | AI45: =SUMIFS(JU!$K$5107:$K$5107,JU!$I$5107:$I$5107,WS!$A45) -> 0 | AJ45: =AG45+AH45-AI45 -> 0 | AK45: =SUMIFS(JU!$H$5107:$H$5107,JU!$F$5107:$F$5107,WS!$A45) -> 0 | AL45: =SUMIFS(JU!$K$5107:$K$5107,JU!$I$5107:$I$5107,WS!$A45) -> 0 | AM45: =AJ45+AK45-AL45 -> 0
A46: 1408 | B46: Inventaris Kantor | C46: 6500000 | D46: =SUMIFS(JU!$H$5:$H$178,JU!$F$5:$F$178,WS!$A46) -> 0 | E46: =SUMIFS(JU!$K$5:$K$178,JU!$I$5:$I$178,WS!$A46) -> 0 | F46: =C46+D46-E46 -> 6500000 | G46: =SUMIFS(JU!$H$180:$H$440,JU!$F$180:$F$440,WS!$A46) -> 0 | H46: =SUMIFS(JU!$K$180:$K$440,JU!$I$180:$I$440,WS!$A46) -> 0 | I46: =F46+G46-H46 -> 6500000 | J46: =SUMIFS(JU!$H$441:$H$695,JU!$F$441:$F$695,WS!$A46) -> 0 | K46: =SUMIFS(JU!$K$441:$K$695,JU!$I$441:$I$695,WS!$A46) -> 0 | L46: =I46+J46-K46 -> 6500000 | M46: =SUMIFS(JU!$H$696:$H$1062,JU!$F$696:$F$1062,$A46) -> 0 | N46: =SUMIFS(JU!$K$696:$K$1062,JU!$I$696:$I$1062,WS!$A46) -> 0 | O46: =L46+M46-N46 -> 6500000 | P46: =SUMIFS(JU!$H$1063:$H$5007,JU!$F$1063:$F$5007,WS!$A46) -> 6700000 | Q46: =SUMIFS(JU!$K$1063:$K$5007,JU!$I$1063:$I$5007,WS!$A46) -> 0 | R46: =O46+P46-Q46 -> 13200000 | S46: =SUMIFS(JU!$H$5107:$H$5107,JU!$F$5107:$F$5107,WS!$A46) -> 0 | T46: =SUMIFS(JU!$K$5107:$K$5107,JU!$I$5107:$I$5107,WS!$A46) -> 0 | U46: =R46+S46-T46 -> 13200000 | V46: =SUMIFS(JU!$H$5107:$H$5107,JU!$F$5107:$F$5107,WS!$A46) -> 0 | W46: =SUMIFS(JU!$K$5107:$K$5107,JU!$I$5107:$I$5107,WS!$A46) -> 0 | X46: =U46+V46-W46 -> 13200000 | Y46: =SUMIFS(JU!$H$5107:$H$5107,JU!$F$5107:$F$5107,WS!$A46) -> 0 | Z46: =SUMIFS(JU!$K$5107:$K$5107,JU!$I$5107:$I$5107,WS!$A46) -> 0 | AA46: =X46+Y46-Z46 -> 13200000 | AB46: =SUMIFS(JU!$H$5107:$H$5107,JU!$F$5107:$F$5107,WS!$A46) -> 0 | AC46: =SUMIFS(JU!$K$5107:$K$5107,JU!$I$5107:$I$5107,WS!$A46) -> 0 | AD46: =AA46+AB46-AC46 -> 13200000 | AE46: =SUMIFS(JU!$H$5107:$H$5107,JU!$F$5107:$F$5107,WS!$A46) -> 0 | AF46: =SUMIFS(JU!$K$5107:$K$5107,JU!$I$5107:$I$5107,WS!$A46) -> 0 | AG46: =AD46+AE46-AF46 -> 13200000 | AH46: =SUMIFS(JU!$H$5107:$H$5107,JU!$F$5107:$F$5107,WS!$A46) -> 0 | AI46: =SUMIFS(JU!$K$5107:$K$5107,JU!$I$5107:$I$5107,WS!$A46) -> 0 | AJ46: =AG46+AH46-AI46 -> 13200000 | AK46: =SUMIFS(JU!$H$5107:$H$5107,JU!$F$5107:$F$5107,WS!$A46) -> 0 | AL46: =SUMIFS(JU!$K$5107:$K$5107,JU!$I$5107:$I$5107,WS!$A46) -> 0 | AM46: =AJ46+AK46-AL46 -> 13200000
A47: 1409 | B47: Akumulasi Penyusutan Inventaris Kantor | C47: 0 | D47: =SUMIFS(JU!$H$5:$H$178,JU!$F$5:$F$178,WS!$A47) -> 0 | E47: =SUMIFS(JU!$K$5:$K$178,JU!$I$5:$I$178,WS!$A47) -> 0 | F47: =C47+D47-E47 -> 0 | G47: =SUMIFS(JU!$H$180:$H$440,JU!$F$180:$F$440,WS!$A47) -> 0 | H47: =SUMIFS(JU!$K$180:$K$440,JU!$I$180:$I$440,WS!$A47) -> 0 | I47: =F47+G47-H47 -> 0 | J47: =SUMIFS(JU!$H$441:$H$695,JU!$F$441:$F$695,WS!$A47) -> 0 | K47: =SUMIFS(JU!$K$441:$K$695,JU!$I$441:$I$695,WS!$A47) -> 0 | L47: =I47+J47-K47 -> 0 | M47: =SUMIFS(JU!$H$696:$H$1062,JU!$F$696:$F$1062,$A47) -> 0 | N47: =SUMIFS(JU!$K$696:$K$1062,JU!$I$696:$I$1062,WS!$A47) -> 0 | O47: =L47+M47-N47 -> 0 | P47: =SUMIFS(JU!$H$1063:$H$5007,JU!$F$1063:$F$5007,WS!$A47) -> 0 | Q47: =SUMIFS(JU!$K$1063:$K$5007,JU!$I$1063:$I$5007,WS!$A47) -> 0 | R47: =O47+P47-Q47 -> 0 | S47: =SUMIFS(JU!$H$5107:$H$5107,JU!$F$5107:$F$5107,WS!$A47) -> 0 | T47: =SUMIFS(JU!$K$5107:$K$5107,JU!$I$5107:$I$5107,WS!$A47) -> 0 | U47: =R47+S47-T47 -> 0 | V47: =SUMIFS(JU!$H$5107:$H$5107,JU!$F$5107:$F$5107,WS!$A47) -> 0 | W47: =SUMIFS(JU!$K$5107:$K$5107,JU!$I$5107:$I$5107,WS!$A47) -> 0 | X47: =U47+V47-W47 -> 0 | Y47: =SUMIFS(JU!$H$5107:$H$5107,JU!$F$5107:$F$5107,WS!$A47) -> 0 | Z47: =SUMIFS(JU!$K$5107:$K$5107,JU!$I$5107:$I$5107,WS!$A47) -> 0 | AA47: =X47+Y47-Z47 -> 0 | AB47: =SUMIFS(JU!$H$5107:$H$5107,JU!$F$5107:$F$5107,WS!$A47) -> 0 | AC47: =SUMIFS(JU!$K$5107:$K$5107,JU!$I$5107:$I$5107,WS!$A47) -> 0 | AD47: =AA47+AB47-AC47 -> 0 | AE47: =SUMIFS(JU!$H$5107:$H$5107,JU!$F$5107:$F$5107,WS!$A47) -> 0 | AF47: =SUMIFS(JU!$K$5107:$K$5107,JU!$I$5107:$I$5107,WS!$A47) -> 0 | AG47: =AD47+AE47-AF47 -> 0 | AH47: =SUMIFS(JU!$H$5107:$H$5107,JU!$F$5107:$F$5107,WS!$A47) -> 0 | AI47: =SUMIFS(JU!$K$5107:$K$5107,JU!$I$5107:$I$5107,WS!$A47) -> 0 | AJ47: =AG47+AH47-AI47 -> 0 | AK47: =SUMIFS(JU!$H$5107:$H$5107,JU!$F$5107:$F$5107,WS!$A47) -> 0 | AL47: =SUMIFS(JU!$K$5107:$K$5107,JU!$I$5107:$I$5107,WS!$A47) -> 0 | AM47: =AJ47+AK47-AL47 -> 0
A48: 1410 | B48: Aset Dalam Penyelesaian | C48: 0 | D48: =SUMIFS(JU!$H$5:$H$178,JU!$F$5:$F$178,WS!$A48) -> 0 | E48: =SUMIFS(JU!$K$5:$K$178,JU!$I$5:$I$178,WS!$A48) -> 0 | F48: =C48+D48-E48 -> 0 | G48: =SUMIFS(JU!$H$180:$H$440,JU!$F$180:$F$440,WS!$A48) -> 0 | H48: =SUMIFS(JU!$K$180:$K$440,JU!$I$180:$I$440,WS!$A48) -> 0 | I48: =F48+G48-H48 -> 0 | J48: =SUMIFS(JU!$H$441:$H$695,JU!$F$441:$F$695,WS!$A48) -> 0 | K48: =SUMIFS(JU!$K$441:$K$695,JU!$I$441:$I$695,WS!$A48) -> 0 | L48: =I48+J48-K48 -> 0 | M48: =SUMIFS(JU!$H$696:$H$1062,JU!$F$696:$F$1062,$A48) -> 0 | N48: =SUMIFS(JU!$K$696:$K$1062,JU!$I$696:$I$1062,WS!$A48) -> 0 | O48: =L48+M48-N48 -> 0 | P48: =SUMIFS(JU!$H$1063:$H$5007,JU!$F$1063:$F$5007,WS!$A48) -> 0 | Q48: =SUMIFS(JU!$K$1063:$K$5007,JU!$I$1063:$I$5007,WS!$A48) -> 0 | R48: =O48+P48-Q48 -> 0 | S48: =SUMIFS(JU!$H$5107:$H$5107,JU!$F$5107:$F$5107,WS!$A48) -> 0 | T48: =SUMIFS(JU!$K$5107:$K$5107,JU!$I$5107:$I$5107,WS!$A48) -> 0 | U48: =R48+S48-T48 -> 0 | V48: =SUMIFS(JU!$H$5107:$H$5107,JU!$F$5107:$F$5107,WS!$A48) -> 0 | W48: =SUMIFS(JU!$K$5107:$K$5107,JU!$I$5107:$I$5107,WS!$A48) -> 0 | X48: =U48+V48-W48 -> 0 | Y48: =SUMIFS(JU!$H$5107:$H$5107,JU!$F$5107:$F$5107,WS!$A48) -> 0 | Z48: =SUMIFS(JU!$K$5107:$K$5107,JU!$I$5107:$I$5107,WS!$A48) -> 0 | AA48: =X48+Y48-Z48 -> 0 | AB48: =SUMIFS(JU!$H$5107:$H$5107,JU!$F$5107:$F$5107,WS!$A48) -> 0 | AC48: =SUMIFS(JU!$K$5107:$K$5107,JU!$I$5107:$I$5107,WS!$A48) -> 0 | AD48: =AA48+AB48-AC48 -> 0 | AE48: =SUMIFS(JU!$H$5107:$H$5107,JU!$F$5107:$F$5107,WS!$A48) -> 0 | AF48: =SUMIFS(JU!$K$5107:$K$5107,JU!$I$5107:$I$5107,WS!$A48) -> 0 | AG48: =AD48+AE48-AF48 -> 0 | AH48: =SUMIFS(JU!$H$5107:$H$5107,JU!$F$5107:$F$5107,WS!$A48) -> 0 | AI48: =SUMIFS(JU!$K$5107:$K$5107,JU!$I$5107:$I$5107,WS!$A48) -> 0 | AJ48: =AG48+AH48-AI48 -> 0 | AK48: =SUMIFS(JU!$H$5107:$H$5107,JU!$F$5107:$F$5107,WS!$A48) -> 0 | AL48: =SUMIFS(JU!$K$5107:$K$5107,JU!$I$5107:$I$5107,WS!$A48) -> 0 | AM48: =AJ48+AK48-AL48 -> 0
A49: 1411 | B49: Investasi Jangka Panjang | C49: 28912000 | D49: =SUMIFS(JU!$H$5:$H$178,JU!$F$5:$F$178,WS!$A49) -> 0 | E49: =SUMIFS(JU!$K$5:$K$178,JU!$I$5:$I$178,WS!$A49) -> 0 | F49: =C49+D49-E49 -> 28912000 | G49: =SUMIFS(JU!$H$180:$H$440,JU!$F$180:$F$440,WS!$A49) -> 0 | H49: =SUMIFS(JU!$K$180:$K$440,JU!$I$180:$I$440,WS!$A49) -> 0 | I49: =F49+G49-H49 -> 28912000 | J49: =SUMIFS(JU!$H$441:$H$695,JU!$F$441:$F$695,WS!$A49) -> 0 | K49: =SUMIFS(JU!$K$441:$K$695,JU!$I$441:$I$695,WS!$A49) -> 0 | L49: =I49+J49-K49 -> 28912000 | M49: =SUMIFS(JU!$H$696:$H$1062,JU!$F$696:$F$1062,$A49) -> 449920000 | N49: =SUMIFS(JU!$K$696:$K$1062,JU!$I$696:$I$1062,WS!$A49) -> 0 | O49: =L49+M49-N49 -> 478832000 | P49: =SUMIFS(JU!$H$1063:$H$5007,JU!$F$1063:$F$5007,WS!$A49) -> 3.7576876e+08 | Q49: =SUMIFS(JU!$K$1063:$K$5007,JU!$I$1063:$I$5007,WS!$A49) -> 0 | R49: =O49+P49-Q49 -> 8.5460076e+08 | S49: =SUMIFS(JU!$H$5107:$H$5107,JU!$F$5107:$F$5107,WS!$A49) -> 0 | T49: =SUMIFS(JU!$K$5107:$K$5107,JU!$I$5107:$I$5107,WS!$A49) -> 0 | U49: =R49+S49-T49 -> 8.5460076e+08 | V49: =SUMIFS(JU!$H$5107:$H$5107,JU!$F$5107:$F$5107,WS!$A49) -> 0 | W49: =SUMIFS(JU!$K$5107:$K$5107,JU!$I$5107:$I$5107,WS!$A49) -> 0 | X49: =U49+V49-W49 -> 8.5460076e+08 | Y49: =SUMIFS(JU!$H$5107:$H$5107,JU!$F$5107:$F$5107,WS!$A49) -> 0 | Z49: =SUMIFS(JU!$K$5107:$K$5107,JU!$I$5107:$I$5107,WS!$A49) -> 0 | AA49: =X49+Y49-Z49 -> 8.5460076e+08 | AB49: =SUMIFS(JU!$H$5107:$H$5107,JU!$F$5107:$F$5107,WS!$A49) -> 0 | AC49: =SUMIFS(JU!$K$5107:$K$5107,JU!$I$5107:$I$5107,WS!$A49) -> 0 | AD49: =AA49+AB49-AC49 -> 8.5460076e+08 | AE49: =SUMIFS(JU!$H$5107:$H$5107,JU!$F$5107:$F$5107,WS!$A49) -> 0 | AF49: =SUMIFS(JU!$K$5107:$K$5107,JU!$I$5107:$I$5107,WS!$A49) -> 0 | AG49: =AD49+AE49-AF49 -> 8.5460076e+08 | AH49: =SUMIFS(JU!$H$5107:$H$5107,JU!$F$5107:$F$5107,WS!$A49) -> 0 | AI49: =SUMIFS(JU!$K$5107:$K$5107,JU!$I$5107:$I$5107,WS!$A49) -> 0 | AJ49: =AG49+AH49-AI49 -> 8.5460076e+08 | AK49: =SUMIFS(JU!$H$5107:$H$5107,JU!$F$5107:$F$5107,WS!$A49) -> 0 | AL49: =SUMIFS(JU!$K$5107:$K$5107,JU!$I$5107:$I$5107,WS!$A49) -> 0 | AM49: =AJ49+AK49-AL49 -> 8.5460076e+08
A50: 1412 | B50: Aset Tak Berwujud | C50: 0 | D50: =SUMIFS(JU!$H$5:$H$178,JU!$F$5:$F$178,WS!$A50) -> 0 | E50: =SUMIFS(JU!$K$5:$K$178,JU!$I$5:$I$178,WS!$A50) -> 0 | F50: =C50+D50-E50 -> 0 | G50: =SUMIFS(JU!$H$180:$H$440,JU!$F$180:$F$440,WS!$A50) -> 0 | H50: =SUMIFS(JU!$K$180:$K$440,JU!$I$180:$I$440,WS!$A50) -> 0 | I50: =F50+G50-H50 -> 0 | J50: =SUMIFS(JU!$H$441:$H$695,JU!$F$441:$F$695,WS!$A50) -> 0 | K50: =SUMIFS(JU!$K$441:$K$695,JU!$I$441:$I$695,WS!$A50) -> 0 | L50: =I50+J50-K50 -> 0 | M50: =SUMIFS(JU!$H$696:$H$1062,JU!$F$696:$F$1062,$A50) -> 0 | N50: =SUMIFS(JU!$K$696:$K$1062,JU!$I$696:$I$1062,WS!$A50) -> 0 | O50: =L50+M50-N50 -> 0 | P50: =SUMIFS(JU!$H$1063:$H$5007,JU!$F$1063:$F$5007,WS!$A50) -> 0 | Q50: =SUMIFS(JU!$K$1063:$K$5007,JU!$I$1063:$I$5007,WS!$A50) -> 0 | R50: =O50+P50-Q50 -> 0 | S50: =SUMIFS(JU!$H$5107:$H$5107,JU!$F$5107:$F$5107,WS!$A50) -> 0 | T50: =SUMIFS(JU!$K$5107:$K$5107,JU!$I$5107:$I$5107,WS!$A50) -> 0 | U50: =R50+S50-T50 -> 0 | V50: =SUMIFS(JU!$H$5107:$H$5107,JU!$F$5107:$F$5107,WS!$A50) -> 0 | W50: =SUMIFS(JU!$K$5107:$K$5107,JU!$I$5107:$I$5107,WS!$A50) -> 0 | X50: =U50+V50-W50 -> 0 | Y50: =SUMIFS(JU!$H$5107:$H$5107,JU!$F$5107:$F$5107,WS!$A50) -> 0 | Z50: =SUMIFS(JU!$K$5107:$K$5107,JU!$I$5107:$I$5107,WS!$A50) -> 0 | AA50: =X50+Y50-Z50 -> 0 | AB50: =SUMIFS(JU!$H$5107:$H$5107,JU!$F$5107:$F$5107,WS!$A50) -> 0 | AC50: =SUMIFS(JU!$K$5107:$K$5107,JU!$I$5107:$I$5107,WS!$A50) -> 0 | AD50: =AA50+AB50-AC50 -> 0 | AE50: =SUMIFS(JU!$H$5107:$H$5107,JU!$F$5107:$F$5107,WS!$A50) -> 0 | AF50: =SUMIFS(JU!$K$5107:$K$5107,JU!$I$5107:$I$5107,WS!$A50) -> 0 | AG50: =AD50+AE50-AF50 -> 0 | AH50: =SUMIFS(JU!$H$5107:$H$5107,JU!$F$5107:$F$5107,WS!$A50) -> 0 | AI50: =SUMIFS(JU!$K$5107:$K$5107,JU!$I$5107:$I$5107,WS!$A50) -> 0 | AJ50: =AG50+AH50-AI50 -> 0 | AK50: =SUMIFS(JU!$H$5107:$H$5107,JU!$F$5107:$F$5107,WS!$A50) -> 0 | AL50: =SUMIFS(JU!$K$5107:$K$5107,JU!$I$5107:$I$5107,WS!$A50) -> 0 | AM50: =AJ50+AK50-AL50 -> 0
A51: Total Asel Tidak Lancar | C51: 1025412000 | D51: =SUMIFS(JU!$H$5:$H$178,JU!$F$5:$F$178,WS!$A51) -> 0 | E51: =SUMIFS(JU!$K$5:$K$178,JU!$I$5:$I$178,WS!$A51) -> 0 | F51: =SUM(F39:F50) -> 1602412000 | G51: =SUMIFS(JU!$H$180:$H$440,JU!$F$180:$F$440,WS!$A51) -> 0 | H51: =SUMIFS(JU!$K$180:$K$440,JU!$I$180:$I$440,WS!$A51) -> 0 | I51: =SUM(I39:I50) -> 1602412000 | J51: =SUMIFS(JU!$H$441:$H$695,JU!$F$441:$F$695,WS!$A51) -> 0 | K51: =SUMIFS(JU!$K$441:$K$695,JU!$I$441:$I$695,WS!$A51) -> 0 | L51: =SUM(L39:L50) -> 1619381718 | M51: =SUMIFS(JU!$H$696:$H$1062,JU!$F$696:$F$1062,$A51) -> 0 | N51: =SUMIFS(JU!$K$696:$K$1062,JU!$I$696:$I$1062,WS!$A51) -> 0 | O51: =SUM(O39:O50) -> 2156518758 | P51: =SUMIFS(JU!$H$1063:$H$5007,JU!$F$1063:$F$5007,WS!$A51) -> 0 | Q51: =SUMIFS(JU!$K$1063:$K$5007,JU!$I$1063:$I$5007,WS!$A51) -> 0 | R51: =SUM(R39:R50) -> 2.5749875e+09 | S51: =SUMIFS(JU!$H$5107:$H$5107,JU!$F$5107:$F$5107,WS!$A51) -> 0 | T51: =SUMIFS(JU!$K$5107:$K$5107,JU!$I$5107:$I$5107,WS!$A51) -> 0 | U51: =SUM(U39:U50) -> 2.5749875e+09 | V51: =SUMIFS(JU!$H$5107:$H$5107,JU!$F$5107:$F$5107,WS!$A51) -> 0 | W51: =SUMIFS(JU!$K$5107:$K$5107,JU!$I$5107:$I$5107,WS!$A51) -> 0 | X51: =SUM(X39:X50) -> 2.5749875e+09 | Y51: =SUMIFS(JU!$H$5107:$H$5107,JU!$F$5107:$F$5107,WS!$A51) -> 0 | Z51: =SUMIFS(JU!$K$5107:$K$5107,JU!$I$5107:$I$5107,WS!$A51) -> 0 | AA51: =SUM(AA39:AA50) -> 2.5749875e+09 | AB51: =SUMIFS(JU!$H$5107:$H$5107,JU!$F$5107:$F$5107,WS!$A51) -> 0 | AC51: =SUMIFS(JU!$K$5107:$K$5107,JU!$I$5107:$I$5107,WS!$A51) -> 0 | AD51: =SUM(AD39:AD50) -> 2.5749875e+09 | AE51: =SUMIFS(JU!$H$5107:$H$5107,JU!$F$5107:$F$5107,WS!$A51) -> 0 | AF51: =SUMIFS(JU!$K$5107:$K$5107,JU!$I$5107:$I$5107,WS!$A51) -> 0 | AG51: =SUM(AG39:AG50) -> 2.5749875e+09 | AH51: =SUMIFS(JU!$H$5107:$H$5107,JU!$F$5107:$F$5107,WS!$A51) -> 0 | AI51: =SUMIFS(JU!$K$5107:$K$5107,JU!$I$5107:$I$5107,WS!$A51) -> 0 | AJ51: =SUM(AJ39:AJ50) -> 2.5749875e+09 | AK51: =SUMIFS(JU!$H$5107:$H$5107,JU!$F$5107:$F$5107,WS!$A51) -> 0 | AL51: =SUMIFS(JU!$K$5107:$K$5107,JU!$I$5107:$I$5107,WS!$A51) -> 0 | AM51: =SUM(AM39:AM50) -> 2.5749875e+09
A52: Total Aset | C52: 5.4541781e+09 | D52: =SUMIFS(JU!$H$5:$H$178,JU!$F$5:$F$178,WS!$A52) -> 0 | E52: =SUMIFS(JU!$K$5:$K$178,JU!$I$5:$I$178,WS!$A52) -> 0 | F52: =F51+F37 -> 5.9156766e+09 | G52: =SUMIFS(JU!$H$180:$H$440,JU!$F$180:$F$440,WS!$A52) -> 0 | H52: =SUMIFS(JU!$K$180:$K$440,JU!$I$180:$I$440,WS!$A52) -> 0 | I52: =I51+I37 -> 7.4776924e+09 | J52: =SUMIFS(JU!$H$441:$H$695,JU!$F$441:$F$695,WS!$A52) -> 0 | K52: =SUMIFS(JU!$K$441:$K$695,JU!$I$441:$I$695,WS!$A52) -> 0 | L52: =L51+L37 -> 1.0256229e+10 | M52: =SUMIFS(JU!$H$696:$H$1062,JU!$F$696:$F$1062,$A52) -> 0 | N52: =SUMIFS(JU!$K$696:$K$1062,JU!$I$696:$I$1062,WS!$A52) -> 0 | O52: =O51+O37 -> 1.0762977e+10 | P52: =SUMIFS(JU!$H$1063:$H$5007,JU!$F$1063:$F$5007,WS!$A52) -> 0 | Q52: =SUMIFS(JU!$K$1063:$K$5007,JU!$I$1063:$I$5007,WS!$A52) -> 0 | R52: =R51+R37 -> 1.3755244e+10 | S52: =SUMIFS(JU!$H$5107:$H$5107,JU!$F$5107:$F$5107,WS!$A52) -> 0 | T52: =SUMIFS(JU!$K$5107:$K$5107,JU!$I$5107:$I$5107,WS!$A52) -> 0 | U52: =U51+U37 -> 1.3755244e+10 | V52: =SUMIFS(JU!$H$5107:$H$5107,JU!$F$5107:$F$5107,WS!$A52) -> 0 | W52: =SUMIFS(JU!$K$5107:$K$5107,JU!$I$5107:$I$5107,WS!$A52) -> 0 | X52: =X51+X37 -> 1.3755244e+10 | Y52: =SUMIFS(JU!$H$5107:$H$5107,JU!$F$5107:$F$5107,WS!$A52) -> 0 | Z52: =SUMIFS(JU!$K$5107:$K$5107,JU!$I$5107:$I$5107,WS!$A52) -> 0 | AA52: =AA51+AA37 -> 1.3755244e+10 | AB52: =SUMIFS(JU!$H$5107:$H$5107,JU!$F$5107:$F$5107,WS!$A52) -> 0 | AC52: =SUMIFS(JU!$K$5107:$K$5107,JU!$I$5107:$I$5107,WS!$A52) -> 0 | AD52: =AD51+AD37 -> 1.3755244e+10 | AE52: =SUMIFS(JU!$H$5107:$H$5107,JU!$F$5107:$F$5107,WS!$A52) -> 0 | AF52: =SUMIFS(JU!$K$5107:$K$5107,JU!$I$5107:$I$5107,WS!$A52) -> 0 | AG52: =AG51+AG37 -> 1.3755244e+10 | AH52: =SUMIFS(JU!$H$5107:$H$5107,JU!$F$5107:$F$5107,WS!$A52) -> 0 | AI52: =SUMIFS(JU!$K$5107:$K$5107,JU!$I$5107:$I$5107,WS!$A52) -> 0 | AJ52: =AJ51+AJ37 -> 1.3755244e+10 | AK52: =SUMIFS(JU!$H$5107:$H$5107,JU!$F$5107:$F$5107,WS!$A52) -> 0 | AL52: =SUMIFS(JU!$K$5107:$K$5107,JU!$I$5107:$I$5107,WS!$A52) -> 0 | AM52: =AM51+AM37 -> 1.3755244e+10
A53: Kewajiban Lancar | D53: =SUMIFS(JU!$H$5:$H$178,JU!$F$5:$F$178,WS!$A53) -> 0 | E53: =SUMIFS(JU!$K$5:$K$178,JU!$I$5:$I$178,WS!$A53) -> 0 | G53: =SUMIFS(JU!$H$180:$H$440,JU!$F$180:$F$440,WS!$A53) -> 0 | H53: =SUMIFS(JU!$K$180:$K$440,JU!$I$180:$I$440,WS!$A53) -> 0 | J53: =SUMIFS(JU!$H$441:$H$695,JU!$F$441:$F$695,WS!$A53) -> 0 | K53: =SUMIFS(JU!$K$441:$K$695,JU!$I$441:$I$695,WS!$A53) -> 0 | M53: =SUMIFS(JU!$H$696:$H$1062,JU!$F$696:$F$1062,$A53) -> 0 | N53: =SUMIFS(JU!$K$696:$K$1062,JU!$I$696:$I$1062,WS!$A53) -> 0 | P53: =SUMIFS(JU!$H$1063:$H$5007,JU!$F$1063:$F$5007,WS!$A53) -> 0 | Q53: =SUMIFS(JU!$K$1063:$K$5007,JU!$I$1063:$I$5007,WS!$A53) -> 0 | S53: =SUMIFS(JU!$H$5107:$H$5107,JU!$F$5107:$F$5107,WS!$A53) -> 0 | T53: =SUMIFS(JU!$K$5107:$K$5107,JU!$I$5107:$I$5107,WS!$A53) -> 0 | V53: =SUMIFS(JU!$H$5107:$H$5107,JU!$F$5107:$F$5107,WS!$A53) -> 0 | W53: =SUMIFS(JU!$K$5107:$K$5107,JU!$I$5107:$I$5107,WS!$A53) -> 0 | Y53: =SUMIFS(JU!$H$5107:$H$5107,JU!$F$5107:$F$5107,WS!$A53) -> 0 | Z53: =SUMIFS(JU!$K$5107:$K$5107,JU!$I$5107:$I$5107,WS!$A53) -> 0 | AB53: =SUMIFS(JU!$H$5107:$H$5107,JU!$F$5107:$F$5107,WS!$A53) -> 0 | AC53: =SUMIFS(JU!$K$5107:$K$5107,JU!$I$5107:$I$5107,WS!$A53) -> 0 | AE53: =SUMIFS(JU!$H$5107:$H$5107,JU!$F$5107:$F$5107,WS!$A53) -> 0 | AF53: =SUMIFS(JU!$K$5107:$K$5107,JU!$I$5107:$I$5107,WS!$A53) -> 0 | AH53: =SUMIFS(JU!$H$5107:$H$5107,JU!$F$5107:$F$5107,WS!$A53) -> 0 | AI53: =SUMIFS(JU!$K$5107:$K$5107,JU!$I$5107:$I$5107,WS!$A53) -> 0 | AK53: =SUMIFS(JU!$H$5107:$H$5107,JU!$F$5107:$F$5107,WS!$A53) -> 0 | AL53: =SUMIFS(JU!$K$5107:$K$5107,JU!$I$5107:$I$5107,WS!$A53) -> 0
A54: 2101 | B54: Hutang Usaha | C54: 1500000000 | D54: =SUMIFS(JU!$H$5:$H$178,JU!$F$5:$F$178,WS!$A54) -> 10000000 | E54: =SUMIFS(JU!$K$5:$K$178,JU!$I$5:$I$178,WS!$A54) -> 95259094 | F54: =C54+E54-D54 -> 1585259094 | G54: =SUMIFS(JU!$H$180:$H$440,JU!$F$180:$F$440,WS!$A54) -> 1282240200 | H54: =SUMIFS(JU!$K$180:$K$440,JU!$I$180:$I$440,WS!$A54) -> 2669000000 | I54: =F54+H54-G54 -> 2972018894 | J54: =SUMIFS(JU!$H$441:$H$695,JU!$F$441:$F$695,WS!$A54) -> 375000000 | K54: =SUMIFS(JU!$K$441:$K$695,JU!$I$441:$I$695,WS!$A54) -> 3404872500 | L54: =I54+K54-J54 -> 6001891394 | M54: =SUMIFS(JU!$H$696:$H$1062,JU!$F$696:$F$1062,$A54) -> 1771000000 | N54: =SUMIFS(JU!$K$696:$K$1062,JU!$I$696:$I$1062,WS!$A54) -> 300000000 | O54: =L54+N54-M54 -> 4530891394 | P54: =SUMIFS(JU!$H$1063:$H$5007,JU!$F$1063:$F$5007,WS!$A54) -> 1621000000 | Q54: =SUMIFS(JU!$K$1063:$K$5007,JU!$I$1063:$I$5007,WS!$A54) -> 2396000000 | R54: =O54+Q54-P54 -> 5305891394 | S54: =SUMIFS(JU!$H$5107:$H$5107,JU!$F$5107:$F$5107,WS!$A54) -> 0 | T54: =SUMIFS(JU!$K$5107:$K$5107,JU!$I$5107:$I$5107,WS!$A54) -> 0 | U54: =R54+T54-S54 -> 5305891394 | V54: =SUMIFS(JU!$H$5107:$H$5107,JU!$F$5107:$F$5107,WS!$A54) -> 0 | W54: =SUMIFS(JU!$K$5107:$K$5107,JU!$I$5107:$I$5107,WS!$A54) -> 0 | X54: =U54+W54-V54 -> 5305891394 | Y54: =SUMIFS(JU!$H$5107:$H$5107,JU!$F$5107:$F$5107,WS!$A54) -> 0 | Z54: =SUMIFS(JU!$K$5107:$K$5107,JU!$I$5107:$I$5107,WS!$A54) -> 0 | AA54: =X54+Z54-Y54 -> 5305891394 | AB54: =SUMIFS(JU!$H$5107:$H$5107,JU!$F$5107:$F$5107,WS!$A54) -> 0 | AC54: =SUMIFS(JU!$K$5107:$K$5107,JU!$I$5107:$I$5107,WS!$A54) -> 0 | AD54: =AA54+AC54-AB54 -> 5305891394 | AE54: =SUMIFS(JU!$H$5107:$H$5107,JU!$F$5107:$F$5107,WS!$A54) -> 0 | AF54: =SUMIFS(JU!$K$5107:$K$5107,JU!$I$5107:$I$5107,WS!$A54) -> 0 | AG54: =AD54+AF54-AE54 -> 5305891394 | AH54: =SUMIFS(JU!$H$5107:$H$5107,JU!$F$5107:$F$5107,WS!$A54) -> 0 | AI54: =SUMIFS(JU!$K$5107:$K$5107,JU!$I$5107:$I$5107,WS!$A54) -> 0 | AJ54: =AG54+AI54-AH54 -> 5305891394 | AK54: =SUMIFS(JU!$H$5107:$H$5107,JU!$F$5107:$F$5107,WS!$A54) -> 0 | AL54: =SUMIFS(JU!$K$5107:$K$5107,JU!$I$5107:$I$5107,WS!$A54) -> 0 | AM54: =AJ54+AL54-AK54 -> 5305891394
A55: 2102 | B55: Hutang Pajak | C55: 0 | D55: =SUMIFS(JU!$H$5:$H$178,JU!$F$5:$F$178,WS!$A55) -> 0 | E55: =SUMIFS(JU!$K$5:$K$178,JU!$I$5:$I$178,WS!$A55) -> 0 | F55: =C55+E55-D55 -> 0 | G55: =SUMIFS(JU!$H$180:$H$440,JU!$F$180:$F$440,WS!$A55) -> 0 | H55: =SUMIFS(JU!$K$180:$K$440,JU!$I$180:$I$440,WS!$A55) -> 0 | I55: =F55+H55-G55 -> 0 | J55: =SUMIFS(JU!$H$441:$H$695,JU!$F$441:$F$695,WS!$A55) -> 0 | K55: =SUMIFS(JU!$K$441:$K$695,JU!$I$441:$I$695,WS!$A55) -> 0 | L55: =I55+K55-J55 -> 0 | M55: =SUMIFS(JU!$H$696:$H$1062,JU!$F$696:$F$1062,$A55) -> 0 | N55: =SUMIFS(JU!$K$696:$K$1062,JU!$I$696:$I$1062,WS!$A55) -> 0 | O55: =L55+N55-M55 -> 0 | P55: =SUMIFS(JU!$H$1063:$H$5007,JU!$F$1063:$F$5007,WS!$A55) -> 0 | Q55: =SUMIFS(JU!$K$1063:$K$5007,JU!$I$1063:$I$5007,WS!$A55) -> 0 | R55: =O55+Q55-P55 -> 0 | S55: =SUMIFS(JU!$H$5107:$H$5107,JU!$F$5107:$F$5107,WS!$A55) -> 0 | T55: =SUMIFS(JU!$K$5107:$K$5107,JU!$I$5107:$I$5107,WS!$A55) -> 0 | U55: =R55+T55-S55 -> 0 | V55: =SUMIFS(JU!$H$5107:$H$5107,JU!$F$5107:$F$5107,WS!$A55) -> 0 | W55: =SUMIFS(JU!$K$5107:$K$5107,JU!$I$5107:$I$5107,WS!$A55) -> 0 | X55: =U55+W55-V55 -> 0 | Y55: =SUMIFS(JU!$H$5107:$H$5107,JU!$F$5107:$F$5107,WS!$A55) -> 0 | Z55: =SUMIFS(JU!$K$5107:$K$5107,JU!$I$5107:$I$5107,WS!$A55) -> 0 | AA55: =X55+Z55-Y55 -> 0 | AB55: =SUMIFS(JU!$H$5107:$H$5107,JU!$F$5107:$F$5107,WS!$A55) -> 0 | AC55: =SUMIFS(JU!$K$5107:$K$5107,JU!$I$5107:$I$5107,WS!$A55) -> 0 | AD55: =AA55+AC55-AB55 -> 0 | AE55: =SUMIFS(JU!$H$5107:$H$5107,JU!$F$5107:$F$5107,WS!$A55) -> 0 | AF55: =SUMIFS(JU!$K$5107:$K$5107,JU!$I$5107:$I$5107,WS!$A55) -> 0 | AG55: =AD55+AF55-AE55 -> 0 | AH55: =SUMIFS(JU!$H$5107:$H$5107,JU!$F$5107:$F$5107,WS!$A55) -> 0 | AI55: =SUMIFS(JU!$K$5107:$K$5107,JU!$I$5107:$I$5107,WS!$A55) -> 0 | AJ55: =AG55+AI55-AH55 -> 0 | AK55: =SUMIFS(JU!$H$5107:$H$5107,JU!$F$5107:$F$5107,WS!$A55) -> 0 | AL55: =SUMIFS(JU!$K$5107:$K$5107,JU!$I$5107:$I$5107,WS!$A55) -> 0 | AM55: =AJ55+AL55-AK55 -> 0
A56: 2103 | B56: Hutang Subkon | C56: 0 | D56: =SUMIFS(JU!$H$5:$H$178,JU!$F$5:$F$178,WS!$A56) -> 0 | E56: =SUMIFS(JU!$K$5:$K$178,JU!$I$5:$I$178,WS!$A56) -> 0 | F56: =C56+E56-D56 -> 0 | G56: =SUMIFS(JU!$H$180:$H$440,JU!$F$180:$F$440,WS!$A56) -> 0 | H56: =SUMIFS(JU!$K$180:$K$440,JU!$I$180:$I$440,WS!$A56) -> 0 | I56: =F56+H56-G56 -> 0 | J56: =SUMIFS(JU!$H$441:$H$695,JU!$F$441:$F$695,WS!$A56) -> 0 | K56: =SUMIFS(JU!$K$441:$K$695,JU!$I$441:$I$695,WS!$A56) -> 0 | L56: =I56+K56-J56 -> 0 | M56: =SUMIFS(JU!$H$696:$H$1062,JU!$F$696:$F$1062,$A56) -> 0 | N56: =SUMIFS(JU!$K$696:$K$1062,JU!$I$696:$I$1062,WS!$A56) -> 0 | O56: =L56+N56-M56 -> 0 | P56: =SUMIFS(JU!$H$1063:$H$5007,JU!$F$1063:$F$5007,WS!$A56) -> 0 | Q56: =SUMIFS(JU!$K$1063:$K$5007,JU!$I$1063:$I$5007,WS!$A56) -> 0 | R56: =O56+Q56-P56 -> 0 | S56: =SUMIFS(JU!$H$5107:$H$5107,JU!$F$5107:$F$5107,WS!$A56) -> 0 | T56: =SUMIFS(JU!$K$5107:$K$5107,JU!$I$5107:$I$5107,WS!$A56) -> 0 | U56: =R56+T56-S56 -> 0 | V56: =SUMIFS(JU!$H$5107:$H$5107,JU!$F$5107:$F$5107,WS!$A56) -> 0 | W56: =SUMIFS(JU!$K$5107:$K$5107,JU!$I$5107:$I$5107,WS!$A56) -> 0 | X56: =U56+W56-V56 -> 0 | Y56: =SUMIFS(JU!$H$5107:$H$5107,JU!$F$5107:$F$5107,WS!$A56) -> 0 | Z56: =SUMIFS(JU!$K$5107:$K$5107,JU!$I$5107:$I$5107,WS!$A56) -> 0 | AA56: =X56+Z56-Y56 -> 0 | AB56: =SUMIFS(JU!$H$5107:$H$5107,JU!$F$5107:$F$5107,WS!$A56) -> 0 | AC56: =SUMIFS(JU!$K$5107:$K$5107,JU!$I$5107:$I$5107,WS!$A56) -> 0 | AD56: =AA56+AC56-AB56 -> 0 | AE56: =SUMIFS(JU!$H$5107:$H$5107,JU!$F$5107:$F$5107,WS!$A56) -> 0 | AF56: =SUMIFS(JU!$K$5107:$K$5107,JU!$I$5107:$I$5107,WS!$A56) -> 0 | AG56: =AD56+AF56-AE56 -> 0 | AH56: =SUMIFS(JU!$H$5107:$H$5107,JU!$F$5107:$F$5107,WS!$A56) -> 0 | AI56: =SUMIFS(JU!$K$5107:$K$5107,JU!$I$5107:$I$5107,WS!$A56) -> 0 | AJ56: =AG56+AI56-AH56 -> 0 | AK56: =SUMIFS(JU!$H$5107:$H$5107,JU!$F$5107:$F$5107,WS!$A56) -> 0 | AL56: =SUMIFS(JU!$K$5107:$K$5107,JU!$I$5107:$I$5107,WS!$A56) -> 0 | AM56: =AJ56+AL56-AK56 -> 0
A57: 2104 | B57: Hutang Bunga | C57: 0 | D57: =SUMIFS(JU!$H$5:$H$178,JU!$F$5:$F$178,WS!$A57) -> 0 | E57: =SUMIFS(JU!$K$5:$K$178,JU!$I$5:$I$178,WS!$A57) -> 0 | F57: =C57+E57-D57 -> 0 | G57: =SUMIFS(JU!$H$180:$H$440,JU!$F$180:$F$440,WS!$A57) -> 0 | H57: =SUMIFS(JU!$K$180:$K$440,JU!$I$180:$I$440,WS!$A57) -> 0 | I57: =F57+H57-G57 -> 0 | J57: =SUMIFS(JU!$H$441:$H$695,JU!$F$441:$F$695,WS!$A57) -> 0 | K57: =SUMIFS(JU!$K$441:$K$695,JU!$I$441:$I$695,WS!$A57) -> 0 | L57: =I57+K57-J57 -> 0 | M57: =SUMIFS(JU!$H$696:$H$1062,JU!$F$696:$F$1062,$A57) -> 0 | N57: =SUMIFS(JU!$K$696:$K$1062,JU!$I$696:$I$1062,WS!$A57) -> 0 | O57: =L57+N57-M57 -> 0 | P57: =SUMIFS(JU!$H$1063:$H$5007,JU!$F$1063:$F$5007,WS!$A57) -> 0 | Q57: =SUMIFS(JU!$K$1063:$K$5007,JU!$I$1063:$I$5007,WS!$A57) -> 0 | R57: =O57+Q57-P57 -> 0 | S57: =SUMIFS(JU!$H$5107:$H$5107,JU!$F$5107:$F$5107,WS!$A57) -> 0 | T57: =SUMIFS(JU!$K$5107:$K$5107,JU!$I$5107:$I$5107,WS!$A57) -> 0 | U57: =R57+T57-S57 -> 0 | V57: =SUMIFS(JU!$H$5107:$H$5107,JU!$F$5107:$F$5107,WS!$A57) -> 0 | W57: =SUMIFS(JU!$K$5107:$K$5107,JU!$I$5107:$I$5107,WS!$A57) -> 0 | X57: =U57+W57-V57 -> 0 | Y57: =SUMIFS(JU!$H$5107:$H$5107,JU!$F$5107:$F$5107,WS!$A57) -> 0 | Z57: =SUMIFS(JU!$K$5107:$K$5107,JU!$I$5107:$I$5107,WS!$A57) -> 0 | AA57: =X57+Z57-Y57 -> 0 | AB57: =SUMIFS(JU!$H$5107:$H$5107,JU!$F$5107:$F$5107,WS!$A57) -> 0 | AC57: =SUMIFS(JU!$K$5107:$K$5107,JU!$I$5107:$I$5107,WS!$A57) -> 0 | AD57: =AA57+AC57-AB57 -> 0 | AE57: =SUMIFS(JU!$H$5107:$H$5107,JU!$F$5107:$F$5107,WS!$A57) -> 0 | AF57: =SUMIFS(JU!$K$5107:$K$5107,JU!$I$5107:$I$5107,WS!$A57) -> 0 | AG57: =AD57+AF57-AE57 -> 0 | AH57: =SUMIFS(JU!$H$5107:$H$5107,JU!$F$5107:$F$5107,WS!$A57) -> 0 | AI57: =SUMIFS(JU!$K$5107:$K$5107,JU!$I$5107:$I$5107,WS!$A57) -> 0 | AJ57: =AG57+AI57-AH57 -> 0 | AK57: =SUMIFS(JU!$H$5107:$H$5107,JU!$F$5107:$F$5107,WS!$A57) -> 0 | AL57: =SUMIFS(JU!$K$5107:$K$5107,JU!$I$5107:$I$5107,WS!$A57) -> 0 | AM57: =AJ57+AL57-AK57 -> 0
A58: 2105 | B58: Uang Muka Penjualan Properti | C58: 0 | D58: =SUMIFS(JU!$H$5:$H$178,JU!$F$5:$F$178,WS!$A58) -> 0 | E58: =SUMIFS(JU!$K$5:$K$178,JU!$I$5:$I$178,WS!$A58) -> 0 | F58: =C58+E58-D58 -> 0 | G58: =SUMIFS(JU!$H$180:$H$440,JU!$F$180:$F$440,WS!$A58) -> 0 | H58: =SUMIFS(JU!$K$180:$K$440,JU!$I$180:$I$440,WS!$A58) -> 0 | I58: =F58+H58-G58 -> 0 | J58: =SUMIFS(JU!$H$441:$H$695,JU!$F$441:$F$695,WS!$A58) -> 0 | K58: =SUMIFS(JU!$K$441:$K$695,JU!$I$441:$I$695,WS!$A58) -> 0 | L58: =I58+K58-J58 -> 0 | M58: =SUMIFS(JU!$H$696:$H$1062,JU!$F$696:$F$1062,$A58) -> 0 | N58: =SUMIFS(JU!$K$696:$K$1062,JU!$I$696:$I$1062,WS!$A58) -> 0 | O58: =L58+N58-M58 -> 0 | P58: =SUMIFS(JU!$H$1063:$H$5007,JU!$F$1063:$F$5007,WS!$A58) -> 0 | Q58: =SUMIFS(JU!$K$1063:$K$5007,JU!$I$1063:$I$5007,WS!$A58) -> 0 | R58: =O58+Q58-P58 -> 0 | S58: =SUMIFS(JU!$H$5107:$H$5107,JU!$F$5107:$F$5107,WS!$A58) -> 0 | T58: =SUMIFS(JU!$K$5107:$K$5107,JU!$I$5107:$I$5107,WS!$A58) -> 0 | U58: =R58+T58-S58 -> 0 | V58: =SUMIFS(JU!$H$5107:$H$5107,JU!$F$5107:$F$5107,WS!$A58) -> 0 | W58: =SUMIFS(JU!$K$5107:$K$5107,JU!$I$5107:$I$5107,WS!$A58) -> 0 | X58: =U58+W58-V58 -> 0 | Y58: =SUMIFS(JU!$H$5107:$H$5107,JU!$F$5107:$F$5107,WS!$A58) -> 0 | Z58: =SUMIFS(JU!$K$5107:$K$5107,JU!$I$5107:$I$5107,WS!$A58) -> 0 | AA58: =X58+Z58-Y58 -> 0 | AB58: =SUMIFS(JU!$H$5107:$H$5107,JU!$F$5107:$F$5107,WS!$A58) -> 0 | AC58: =SUMIFS(JU!$K$5107:$K$5107,JU!$I$5107:$I$5107,WS!$A58) -> 0 | AD58: =AA58+AC58-AB58 -> 0 | AE58: =SUMIFS(JU!$H$5107:$H$5107,JU!$F$5107:$F$5107,WS!$A58) -> 0 | AF58: =SUMIFS(JU!$K$5107:$K$5107,JU!$I$5107:$I$5107,WS!$A58) -> 0 | AG58: =AD58+AF58-AE58 -> 0 | AH58: =SUMIFS(JU!$H$5107:$H$5107,JU!$F$5107:$F$5107,WS!$A58) -> 0 | AI58: =SUMIFS(JU!$K$5107:$K$5107,JU!$I$5107:$I$5107,WS!$A58) -> 0 | AJ58: =AG58+AI58-AH58 -> 0 | AK58: =SUMIFS(JU!$H$5107:$H$5107,JU!$F$5107:$F$5107,WS!$A58) -> 0 | AL58: =SUMIFS(JU!$K$5107:$K$5107,JU!$I$5107:$I$5107,WS!$A58) -> 0 | AM58: =AJ58+AL58-AK58 -> 0
A59: 2106 | B59: Uang Muka Penjualan Konveksi | C59: 0 | D59: =SUMIFS(JU!$H$5:$H$178,JU!$F$5:$F$178,WS!$A59) -> 0 | E59: =SUMIFS(JU!$K$5:$K$178,JU!$I$5:$I$178,WS!$A59) -> 0 | F59: =C59+E59-D59 -> 0 | G59: =SUMIFS(JU!$H$180:$H$440,JU!$F$180:$F$440,WS!$A59) -> 0 | H59: =SUMIFS(JU!$K$180:$K$440,JU!$I$180:$I$440,WS!$A59) -> 0 | I59: =F59+H59-G59 -> 0 | J59: =SUMIFS(JU!$H$441:$H$695,JU!$F$441:$F$695,WS!$A59) -> 0 | K59: =SUMIFS(JU!$K$441:$K$695,JU!$I$441:$I$695,WS!$A59) -> 0 | L59: =I59+K59-J59 -> 0 | M59: =SUMIFS(JU!$H$696:$H$1062,JU!$F$696:$F$1062,$A59) -> 0 | N59: =SUMIFS(JU!$K$696:$K$1062,JU!$I$696:$I$1062,WS!$A59) -> 0 | O59: =L59+N59-M59 -> 0 | P59: =SUMIFS(JU!$H$1063:$H$5007,JU!$F$1063:$F$5007,WS!$A59) -> 0 | Q59: =SUMIFS(JU!$K$1063:$K$5007,JU!$I$1063:$I$5007,WS!$A59) -> 0 | R59: =O59+Q59-P59 -> 0 | S59: =SUMIFS(JU!$H$5107:$H$5107,JU!$F$5107:$F$5107,WS!$A59) -> 0 | T59: =SUMIFS(JU!$K$5107:$K$5107,JU!$I$5107:$I$5107,WS!$A59) -> 0 | U59: =R59+T59-S59 -> 0 | V59: =SUMIFS(JU!$H$5107:$H$5107,JU!$F$5107:$F$5107,WS!$A59) -> 0 | W59: =SUMIFS(JU!$K$5107:$K$5107,JU!$I$5107:$I$5107,WS!$A59) -> 0 | X59: =U59+W59-V59 -> 0 | Y59: =SUMIFS(JU!$H$5107:$H$5107,JU!$F$5107:$F$5107,WS!$A59) -> 0 | Z59: =SUMIFS(JU!$K$5107:$K$5107,JU!$I$5107:$I$5107,WS!$A59) -> 0 | AA59: =X59+Z59-Y59 -> 0 | AB59: =SUMIFS(JU!$H$5107:$H$5107,JU!$F$5107:$F$5107,WS!$A59) -> 0 | AC59: =SUMIFS(JU!$K$5107:$K$5107,JU!$I$5107:$I$5107,WS!$A59) -> 0 | AD59: =AA59+AC59-AB59 -> 0 | AE59: =SUMIFS(JU!$H$5107:$H$5107,JU!$F$5107:$F$5107,WS!$A59) -> 0 | AF59: =SUMIFS(JU!$K$5107:$K$5107,JU!$I$5107:$I$5107,WS!$A59) -> 0 | AG59: =AD59+AF59-AE59 -> 0 | AH59: =SUMIFS(JU!$H$5107:$H$5107,JU!$F$5107:$F$5107,WS!$A59) -> 0 | AI59: =SUMIFS(JU!$K$5107:$K$5107,JU!$I$5107:$I$5107,WS!$A59) -> 0 | AJ59: =AG59+AI59-AH59 -> 0 | AK59: =SUMIFS(JU!$H$5107:$H$5107,JU!$F$5107:$F$5107,WS!$A59) -> 0 | AL59: =SUMIFS(JU!$K$5107:$K$5107,JU!$I$5107:$I$5107,WS!$A59) -> 0 | AM59: =AJ59+AL59-AK59 -> 0
A60: 2107 | B60: Biaya yang Masih Harus Dibayar | C60: 0 | D60: =SUMIFS(JU!$H$5:$H$178,JU!$F$5:$F$178,WS!$A60) -> 1204131000 | E60: =SUMIFS(JU!$K$5:$K$178,JU!$I$5:$I$178,WS!$A60) -> 1639131000 | F60: =C60+E60-D60 -> 435000000 | G60: =SUMIFS(JU!$H$180:$H$440,JU!$F$180:$F$440,WS!$A60) -> 2538234500 | H60: =SUMIFS(JU!$K$180:$K$440,JU!$I$180:$I$440,WS!$A60) -> 2759525000 | I60: =F60+H60-G60 -> 656290500 | J60: =SUMIFS(JU!$H$441:$H$695,JU!$F$441:$F$695,WS!$A60) -> 1189546166 | K60: =SUMIFS(JU!$K$441:$K$695,JU!$I$441:$I$695,WS!$A60) -> 844546166 | L60: =I60+K60-J60 -> 311290500 | M60: =SUMIFS(JU!$H$696:$H$1062,JU!$F$696:$F$1062,$A60) -> 2373762912 | N60: =SUMIFS(JU!$K$696:$K$1062,JU!$I$696:$I$1062,WS!$A60) -> 2246762500 | O60: =L60+N60-M60 -> 184290088 | P60: =SUMIFS(JU!$H$1063:$H$5007,JU!$F$1063:$F$5007,WS!$A60) -> 627462550 | Q60: =SUMIFS(JU!$K$1063:$K$5007,JU!$I$1063:$I$5007,WS!$A60) -> 625877500 | R60: =O60+Q60-P60 -> 182705038 | S60: =SUMIFS(JU!$H$5107:$H$5107,JU!$F$5107:$F$5107,WS!$A60) -> 0 | T60: =SUMIFS(JU!$K$5107:$K$5107,JU!$I$5107:$I$5107,WS!$A60) -> 0 | U60: =R60+T60-S60 -> 182705038 | V60: =SUMIFS(JU!$H$5107:$H$5107,JU!$F$5107:$F$5107,WS!$A60) -> 0 | W60: =SUMIFS(JU!$K$5107:$K$5107,JU!$I$5107:$I$5107,WS!$A60) -> 0 | X60: =U60+W60-V60 -> 182705038 | Y60: =SUMIFS(JU!$H$5107:$H$5107,JU!$F$5107:$F$5107,WS!$A60) -> 0 | Z60: =SUMIFS(JU!$K$5107:$K$5107,JU!$I$5107:$I$5107,WS!$A60) -> 0 | AA60: =X60+Z60-Y60 -> 182705038 | AB60: =SUMIFS(JU!$H$5107:$H$5107,JU!$F$5107:$F$5107,WS!$A60) -> 0 | AC60: =SUMIFS(JU!$K$5107:$K$5107,JU!$I$5107:$I$5107,WS!$A60) -> 0 | AD60: =AA60+AC60-AB60 -> 182705038 | AE60: =SUMIFS(JU!$H$5107:$H$5107,JU!$F$5107:$F$5107,WS!$A60) -> 0 | AF60: =SUMIFS(JU!$K$5107:$K$5107,JU!$I$5107:$I$5107,WS!$A60) -> 0 | AG60: =AD60+AF60-AE60 -> 182705038 | AH60: =SUMIFS(JU!$H$5107:$H$5107,JU!$F$5107:$F$5107,WS!$A60) -> 0 | AI60: =SUMIFS(JU!$K$5107:$K$5107,JU!$I$5107:$I$5107,WS!$A60) -> 0 | AJ60: =AG60+AI60-AH60 -> 182705038 | AK60: =SUMIFS(JU!$H$5107:$H$5107,JU!$F$5107:$F$5107,WS!$A60) -> 0 | AL60: =SUMIFS(JU!$K$5107:$K$5107,JU!$I$5107:$I$5107,WS!$A60) -> 0 | AM60: =AJ60+AL60-AK60 -> 182705038
A61: 2108 | B61: Hutang Jangka Pendek ke Bank | C61: 22716000 | D61: =SUMIFS(JU!$H$5:$H$178,JU!$F$5:$F$178,WS!$A61) -> 0 | E61: =SUMIFS(JU!$K$5:$K$178,JU!$I$5:$I$178,WS!$A61) -> 0 | F61: =C61+E61-D61 -> 22716000 | G61: =SUMIFS(JU!$H$180:$H$440,JU!$F$180:$F$440,WS!$A61) -> 5832000 | H61: =SUMIFS(JU!$K$180:$K$440,JU!$I$180:$I$440,WS!$A61) -> 0 | I61: =F61+H61-G61 -> 16884000 | J61: =SUMIFS(JU!$H$441:$H$695,JU!$F$441:$F$695,WS!$A61) -> 0 | K61: =SUMIFS(JU!$K$441:$K$695,JU!$I$441:$I$695,WS!$A61) -> 0 | L61: =I61+K61-J61 -> 16884000 | M61: =SUMIFS(JU!$H$696:$H$1062,JU!$F$696:$F$1062,$A61) -> 30504400 | N61: =SUMIFS(JU!$K$696:$K$1062,JU!$I$696:$I$1062,WS!$A61) -> 284320000 | O61: =L61+N61-M61 -> 270699600 | P61: =SUMIFS(JU!$H$1063:$H$5007,JU!$F$1063:$F$5007,WS!$A61) -> 21700000 | Q61: =SUMIFS(JU!$K$1063:$K$5007,JU!$I$1063:$I$5007,WS!$A61) -> 48981532 | R61: =O61+Q61-P61 -> 2.9798113e+08 | S61: =SUMIFS(JU!$H$5107:$H$5107,JU!$F$5107:$F$5107,WS!$A61) -> 0 | T61: =SUMIFS(JU!$K$5107:$K$5107,JU!$I$5107:$I$5107,WS!$A61) -> 0 | U61: =R61+T61-S61 -> 2.9798113e+08 | V61: =SUMIFS(JU!$H$5107:$H$5107,JU!$F$5107:$F$5107,WS!$A61) -> 0 | W61: =SUMIFS(JU!$K$5107:$K$5107,JU!$I$5107:$I$5107,WS!$A61) -> 0 | X61: =U61+W61-V61 -> 2.9798113e+08 | Y61: =SUMIFS(JU!$H$5107:$H$5107,JU!$F$5107:$F$5107,WS!$A61) -> 0 | Z61: =SUMIFS(JU!$K$5107:$K$5107,JU!$I$5107:$I$5107,WS!$A61) -> 0 | AA61: =X61+Z61-Y61 -> 2.9798113e+08 | AB61: =SUMIFS(JU!$H$5107:$H$5107,JU!$F$5107:$F$5107,WS!$A61) -> 0 | AC61: =SUMIFS(JU!$K$5107:$K$5107,JU!$I$5107:$I$5107,WS!$A61) -> 0 | AD61: =AA61+AC61-AB61 -> 2.9798113e+08 | AE61: =SUMIFS(JU!$H$5107:$H$5107,JU!$F$5107:$F$5107,WS!$A61) -> 0 | AF61: =SUMIFS(JU!$K$5107:$K$5107,JU!$I$5107:$I$5107,WS!$A61) -> 0 | AG61: =AD61+AF61-AE61 -> 2.9798113e+08 | AH61: =SUMIFS(JU!$H$5107:$H$5107,JU!$F$5107:$F$5107,WS!$A61) -> 0 | AI61: =SUMIFS(JU!$K$5107:$K$5107,JU!$I$5107:$I$5107,WS!$A61) -> 0 | AJ61: =AG61+AI61-AH61 -> 2.9798113e+08 | AK61: =SUMIFS(JU!$H$5107:$H$5107,JU!$F$5107:$F$5107,WS!$A61) -> 0 | AL61: =SUMIFS(JU!$K$5107:$K$5107,JU!$I$5107:$I$5107,WS!$A61) -> 0 | AM61: =AJ61+AL61-AK61 -> 2.9798113e+08
A62: Total Kewajiban Lancar | C62: 1522716000 | D62: =SUMIFS(JU!$H$5:$H$178,JU!$F$5:$F$178,WS!$A62) -> 0 | E62: =SUMIFS(JU!$K$5:$K$178,JU!$I$5:$I$178,WS!$A62) -> 0 | F62: =SUM(F54:F61) -> 2042975094 | G62: =SUMIFS(JU!$H$180:$H$440,JU!$F$180:$F$440,WS!$A62) -> 0 | H62: =SUMIFS(JU!$K$180:$K$440,JU!$I$180:$I$440,WS!$A62) -> 0 | I62: =SUM(I54:I61) -> 3645193394 | J62: =SUMIFS(JU!$H$441:$H$695,JU!$F$441:$F$695,WS!$A62) -> 0 | K62: =SUMIFS(JU!$K$441:$K$695,JU!$I$441:$I$695,WS!$A62) -> 0 | L62: =SUM(L54:L61) -> 6330065894 | M62: =SUMIFS(JU!$H$696:$H$1062,JU!$F$696:$F$1062,$A62) -> 0 | N62: =SUMIFS(JU!$K$696:$K$1062,JU!$I$696:$I$1062,WS!$A62) -> 0 | O62: =SUM(O54:O61) -> 4985881082 | P62: =SUMIFS(JU!$H$1063:$H$5007,JU!$F$1063:$F$5007,WS!$A62) -> 0 | Q62: =SUMIFS(JU!$K$1063:$K$5007,JU!$I$1063:$I$5007,WS!$A62) -> 0 | R62: =SUM(R54:R61) -> 5.7865776e+09 | S62: =SUMIFS(JU!$H$5107:$H$5107,JU!$F$5107:$F$5107,WS!$A62) -> 0 | T62: =SUMIFS(JU!$K$5107:$K$5107,JU!$I$5107:$I$5107,WS!$A62) -> 0 | U62: =SUM(U54:U61) -> 5.7865776e+09 | V62: =SUMIFS(JU!$H$5107:$H$5107,JU!$F$5107:$F$5107,WS!$A62) -> 0 | W62: =SUMIFS(JU!$K$5107:$K$5107,JU!$I$5107:$I$5107,WS!$A62) -> 0 | X62: =SUM(X54:X61) -> 5.7865776e+09 | Y62: =SUMIFS(JU!$H$5107:$H$5107,JU!$F$5107:$F$5107,WS!$A62) -> 0 | Z62: =SUMIFS(JU!$K$5107:$K$5107,JU!$I$5107:$I$5107,WS!$A62) -> 0 | AA62: =SUM(AA54:AA61) -> 5.7865776e+09 | AB62: =SUMIFS(JU!$H$5107:$H$5107,JU!$F$5107:$F$5107,WS!$A62) -> 0 | AC62: =SUMIFS(JU!$K$5107:$K$5107,JU!$I$5107:$I$5107,WS!$A62) -> 0 | AD62: =SUM(AD54:AD61) -> 5.7865776e+09 | AE62: =SUMIFS(JU!$H$5107:$H$5107,JU!$F$5107:$F$5107,WS!$A62) -> 0 | AF62: =SUMIFS(JU!$K$5107:$K$5107,JU!$I$5107:$I$5107,WS!$A62) -> 0 | AG62: =SUM(AG54:AG61) -> 5.7865776e+09 | AH62: =SUMIFS(JU!$H$5107:$H$5107,JU!$F$5107:$F$5107,WS!$A62) -> 0 | AI62: =SUMIFS(JU!$K$5107:$K$5107,JU!$I$5107:$I$5107,WS!$A62) -> 0 | AJ62: =SUM(AJ54:AJ61) -> 5.7865776e+09 | AK62: =SUMIFS(JU!$H$5107:$H$5107,JU!$F$5107:$F$5107,WS!$A62) -> 0 | AL62: =SUMIFS(JU!$K$5107:$K$5107,JU!$I$5107:$I$5107,WS!$A62) -> 0 | AM62: =SUM(AM54:AM61) -> 5.7865776e+09
A63: Kewajiban Jangka Panjang | D63: =SUMIFS(JU!$H$5:$H$178,JU!$F$5:$F$178,WS!$A63) -> 0 | E63: =SUMIFS(JU!$K$5:$K$178,JU!$I$5:$I$178,WS!$A63) -> 0 | G63: =SUMIFS(JU!$H$180:$H$440,JU!$F$180:$F$440,WS!$A63) -> 0 | H63: =SUMIFS(JU!$K$180:$K$440,JU!$I$180:$I$440,WS!$A63) -> 0 | J63: =SUMIFS(JU!$H$441:$H$695,JU!$F$441:$F$695,WS!$A63) -> 0 | K63: =SUMIFS(JU!$K$441:$K$695,JU!$I$441:$I$695,WS!$A63) -> 0 | M63: =SUMIFS(JU!$H$696:$H$1062,JU!$F$696:$F$1062,$A63) -> 0 | N63: =SUMIFS(JU!$K$696:$K$1062,JU!$I$696:$I$1062,WS!$A63) -> 0 | P63: =SUMIFS(JU!$H$1063:$H$5007,JU!$F$1063:$F$5007,WS!$A63) -> 0 | Q63: =SUMIFS(JU!$K$1063:$K$5007,JU!$I$1063:$I$5007,WS!$A63) -> 0 | S63: =SUMIFS(JU!$H$5107:$H$5107,JU!$F$5107:$F$5107,WS!$A63) -> 0 | T63: =SUMIFS(JU!$K$5107:$K$5107,JU!$I$5107:$I$5107,WS!$A63) -> 0 | V63: =SUMIFS(JU!$H$5107:$H$5107,JU!$F$5107:$F$5107,WS!$A63) -> 0 | W63: =SUMIFS(JU!$K$5107:$K$5107,JU!$I$5107:$I$5107,WS!$A63) -> 0 | Y63: =SUMIFS(JU!$H$5107:$H$5107,JU!$F$5107:$F$5107,WS!$A63) -> 0 | Z63: =SUMIFS(JU!$K$5107:$K$5107,JU!$I$5107:$I$5107,WS!$A63) -> 0 | AB63: =SUMIFS(JU!$H$5107:$H$5107,JU!$F$5107:$F$5107,WS!$A63) -> 0 | AC63: =SUMIFS(JU!$K$5107:$K$5107,JU!$I$5107:$I$5107,WS!$A63) -> 0 | AE63: =SUMIFS(JU!$H$5107:$H$5107,JU!$F$5107:$F$5107,WS!$A63) -> 0 | AF63: =SUMIFS(JU!$K$5107:$K$5107,JU!$I$5107:$I$5107,WS!$A63) -> 0 | AH63: =SUMIFS(JU!$H$5107:$H$5107,JU!$F$5107:$F$5107,WS!$A63) -> 0 | AI63: =SUMIFS(JU!$K$5107:$K$5107,JU!$I$5107:$I$5107,WS!$A63) -> 0 | AK63: =SUMIFS(JU!$H$5107:$H$5107,JU!$F$5107:$F$5107,WS!$A63) -> 0 | AL63: =SUMIFS(JU!$K$5107:$K$5107,JU!$I$5107:$I$5107,WS!$A63) -> 0
A64: 2201 | B64: Hutang Bank Jangka Panjang | C64: 788370000 | D64: =SUMIFS(JU!$H$5:$H$178,JU!$F$5:$F$178,WS!$A64) -> 48000000 | E64: =SUMIFS(JU!$K$5:$K$178,JU!$I$5:$I$178,WS!$A64) -> 0 | F64: =C64+E64-D64 -> 740370000 | G64: =SUMIFS(JU!$H$180:$H$440,JU!$F$180:$F$440,WS!$A64) -> 24000000 | H64: =SUMIFS(JU!$K$180:$K$440,JU!$I$180:$I$440,WS!$A64) -> 0 | I64: =F64+H64-G64 -> 716370000 | J64: =SUMIFS(JU!$H$441:$H$695,JU!$F$441:$F$695,WS!$A64) -> 24000000 | K64: =SUMIFS(JU!$K$441:$K$695,JU!$I$441:$I$695,WS!$A64) -> 0 | L64: =I64+K64-J64 -> 692370000 | M64: =SUMIFS(JU!$H$696:$H$1062,JU!$F$696:$F$1062,$A64) -> 24000000 | N64: =SUMIFS(JU!$K$696:$K$1062,JU!$I$696:$I$1062,WS!$A64) -> 680000000 | O64: =L64+N64-M64 -> 1348370000 | P64: =SUMIFS(JU!$H$1063:$H$5007,JU!$F$1063:$F$5007,WS!$A64) -> 36520578 | Q64: =SUMIFS(JU!$K$1063:$K$5007,JU!$I$1063:$I$5007,WS!$A64) -> 326787224 | R64: =O64+Q64-P64 -> 1638636646 | S64: =SUMIFS(JU!$H$5107:$H$5107,JU!$F$5107:$F$5107,WS!$A64) -> 0 | T64: =SUMIFS(JU!$K$5107:$K$5107,JU!$I$5107:$I$5107,WS!$A64) -> 0 | U64: =R64+T64-S64 -> 1638636646 | V64: =SUMIFS(JU!$H$5107:$H$5107,JU!$F$5107:$F$5107,WS!$A64) -> 0 | W64: =SUMIFS(JU!$K$5107:$K$5107,JU!$I$5107:$I$5107,WS!$A64) -> 0 | X64: =U64+W64-V64 -> 1638636646 | Y64: =SUMIFS(JU!$H$5107:$H$5107,JU!$F$5107:$F$5107,WS!$A64) -> 0 | Z64: =SUMIFS(JU!$K$5107:$K$5107,JU!$I$5107:$I$5107,WS!$A64) -> 0 | AA64: =X64+Z64-Y64 -> 1638636646 | AB64: =SUMIFS(JU!$H$5107:$H$5107,JU!$F$5107:$F$5107,WS!$A64) -> 0 | AC64: =SUMIFS(JU!$K$5107:$K$5107,JU!$I$5107:$I$5107,WS!$A64) -> 0 | AD64: =AA64+AC64-AB64 -> 1638636646 | AE64: =SUMIFS(JU!$H$5107:$H$5107,JU!$F$5107:$F$5107,WS!$A64) -> 0 | AF64: =SUMIFS(JU!$K$5107:$K$5107,JU!$I$5107:$I$5107,WS!$A64) -> 0 | AG64: =AD64+AF64-AE64 -> 1638636646 | AH64: =SUMIFS(JU!$H$5107:$H$5107,JU!$F$5107:$F$5107,WS!$A64) -> 0 | AI64: =SUMIFS(JU!$K$5107:$K$5107,JU!$I$5107:$I$5107,WS!$A64) -> 0 | AJ64: =AG64+AI64-AH64 -> 1638636646 | AK64: =SUMIFS(JU!$H$5107:$H$5107,JU!$F$5107:$F$5107,WS!$A64) -> 0 | AL64: =SUMIFS(JU!$K$5107:$K$5107,JU!$I$5107:$I$5107,WS!$A64) -> 0 | AM64: =AJ64+AL64-AK64 -> 1638636646
A65: 2202 | B65: Hutang Obligasi | C65: 0 | D65: =SUMIFS(JU!$H$5:$H$178,JU!$F$5:$F$178,WS!$A65) -> 0 | E65: =SUMIFS(JU!$K$5:$K$178,JU!$I$5:$I$178,WS!$A65) -> 0 | F65: =C65+E65-D65 -> 0 | G65: =SUMIFS(JU!$H$180:$H$440,JU!$F$180:$F$440,WS!$A65) -> 0 | H65: =SUMIFS(JU!$K$180:$K$440,JU!$I$180:$I$440,WS!$A65) -> 0 | I65: =F65+H65-G65 -> 0 | J65: =SUMIFS(JU!$H$441:$H$695,JU!$F$441:$F$695,WS!$A65) -> 0 | K65: =SUMIFS(JU!$K$441:$K$695,JU!$I$441:$I$695,WS!$A65) -> 0 | L65: =I65+K65-J65 -> 0 | M65: =SUMIFS(JU!$H$696:$H$1062,JU!$F$696:$F$1062,$A65) -> 0 | N65: =SUMIFS(JU!$K$696:$K$1062,JU!$I$696:$I$1062,WS!$A65) -> 0 | O65: =L65+N65-M65 -> 0 | P65: =SUMIFS(JU!$H$1063:$H$5007,JU!$F$1063:$F$5007,WS!$A65) -> 0 | Q65: =SUMIFS(JU!$K$1063:$K$5007,JU!$I$1063:$I$5007,WS!$A65) -> 0 | R65: =O65+Q65-P65 -> 0 | S65: =SUMIFS(JU!$H$5107:$H$5107,JU!$F$5107:$F$5107,WS!$A65) -> 0 | T65: =SUMIFS(JU!$K$5107:$K$5107,JU!$I$5107:$I$5107,WS!$A65) -> 0 | U65: =R65+T65-S65 -> 0 | V65: =SUMIFS(JU!$H$5107:$H$5107,JU!$F$5107:$F$5107,WS!$A65) -> 0 | W65: =SUMIFS(JU!$K$5107:$K$5107,JU!$I$5107:$I$5107,WS!$A65) -> 0 | X65: =U65+W65-V65 -> 0 | Y65: =SUMIFS(JU!$H$5107:$H$5107,JU!$F$5107:$F$5107,WS!$A65) -> 0 | Z65: =SUMIFS(JU!$K$5107:$K$5107,JU!$I$5107:$I$5107,WS!$A65) -> 0 | AA65: =X65+Z65-Y65 -> 0 | AB65: =SUMIFS(JU!$H$5107:$H$5107,JU!$F$5107:$F$5107,WS!$A65) -> 0 | AC65: =SUMIFS(JU!$K$5107:$K$5107,JU!$I$5107:$I$5107,WS!$A65) -> 0 | AD65: =AA65+AC65-AB65 -> 0 | AE65: =SUMIFS(JU!$H$5107:$H$5107,JU!$F$5107:$F$5107,WS!$A65) -> 0 | AF65: =SUMIFS(JU!$K$5107:$K$5107,JU!$I$5107:$I$5107,WS!$A65) -> 0 | AG65: =AD65+AF65-AE65 -> 0 | AH65: =SUMIFS(JU!$H$5107:$H$5107,JU!$F$5107:$F$5107,WS!$A65) -> 0 | AI65: =SUMIFS(JU!$K$5107:$K$5107,JU!$I$5107:$I$5107,WS!$A65) -> 0 | AJ65: =AG65+AI65-AH65 -> 0 | AK65: =SUMIFS(JU!$H$5107:$H$5107,JU!$F$5107:$F$5107,WS!$A65) -> 0 | AL65: =SUMIFS(JU!$K$5107:$K$5107,JU!$I$5107:$I$5107,WS!$A65) -> 0 | AM65: =AJ65+AL65-AK65 -> 0
A66: 2203 | B66: Hutang Pembiayaan Leasing | C66: 0 | D66: =SUMIFS(JU!$H$5:$H$178,JU!$F$5:$F$178,WS!$A66) -> 0 | E66: =SUMIFS(JU!$K$5:$K$178,JU!$I$5:$I$178,WS!$A66) -> 0 | F66: =C66+E66-D66 -> 0 | G66: =SUMIFS(JU!$H$180:$H$440,JU!$F$180:$F$440,WS!$A66) -> 0 | H66: =SUMIFS(JU!$K$180:$K$440,JU!$I$180:$I$440,WS!$A66) -> 0 | I66: =F66+H66-G66 -> 0 | J66: =SUMIFS(JU!$H$441:$H$695,JU!$F$441:$F$695,WS!$A66) -> 0 | K66: =SUMIFS(JU!$K$441:$K$695,JU!$I$441:$I$695,WS!$A66) -> 0 | L66: =I66+K66-J66 -> 0 | M66: =SUMIFS(JU!$H$696:$H$1062,JU!$F$696:$F$1062,$A66) -> 0 | N66: =SUMIFS(JU!$K$696:$K$1062,JU!$I$696:$I$1062,WS!$A66) -> 0 | O66: =L66+N66-M66 -> 0 | P66: =SUMIFS(JU!$H$1063:$H$5007,JU!$F$1063:$F$5007,WS!$A66) -> 0 | Q66: =SUMIFS(JU!$K$1063:$K$5007,JU!$I$1063:$I$5007,WS!$A66) -> 0 | R66: =O66+Q66-P66 -> 0 | S66: =SUMIFS(JU!$H$5107:$H$5107,JU!$F$5107:$F$5107,WS!$A66) -> 0 | T66: =SUMIFS(JU!$K$5107:$K$5107,JU!$I$5107:$I$5107,WS!$A66) -> 0 | U66: =R66+T66-S66 -> 0 | V66: =SUMIFS(JU!$H$5107:$H$5107,JU!$F$5107:$F$5107,WS!$A66) -> 0 | W66: =SUMIFS(JU!$K$5107:$K$5107,JU!$I$5107:$I$5107,WS!$A66) -> 0 | X66: =U66+W66-V66 -> 0 | Y66: =SUMIFS(JU!$H$5107:$H$5107,JU!$F$5107:$F$5107,WS!$A66) -> 0 | Z66: =SUMIFS(JU!$K$5107:$K$5107,JU!$I$5107:$I$5107,WS!$A66) -> 0 | AA66: =X66+Z66-Y66 -> 0 | AB66: =SUMIFS(JU!$H$5107:$H$5107,JU!$F$5107:$F$5107,WS!$A66) -> 0 | AC66: =SUMIFS(JU!$K$5107:$K$5107,JU!$I$5107:$I$5107,WS!$A66) -> 0 | AD66: =AA66+AC66-AB66 -> 0 | AE66: =SUMIFS(JU!$H$5107:$H$5107,JU!$F$5107:$F$5107,WS!$A66) -> 0 | AF66: =SUMIFS(JU!$K$5107:$K$5107,JU!$I$5107:$I$5107,WS!$A66) -> 0 | AG66: =AD66+AF66-AE66 -> 0 | AH66: =SUMIFS(JU!$H$5107:$H$5107,JU!$F$5107:$F$5107,WS!$A66) -> 0 | AI66: =SUMIFS(JU!$K$5107:$K$5107,JU!$I$5107:$I$5107,WS!$A66) -> 0 | AJ66: =AG66+AI66-AH66 -> 0 | AK66: =SUMIFS(JU!$H$5107:$H$5107,JU!$F$5107:$F$5107,WS!$A66) -> 0 | AL66: =SUMIFS(JU!$K$5107:$K$5107,JU!$I$5107:$I$5107,WS!$A66) -> 0 | AM66: =AJ66+AL66-AK66 -> 0
A67: 2204 | B67: Hutang Afiliasi | C67: -398000000 | D67: =SUMIFS(JU!$H$5:$H$178,JU!$F$5:$F$178,WS!$A67) -> 15000000 | E67: =SUMIFS(JU!$K$5:$K$178,JU!$I$5:$I$178,WS!$A67) -> 63000000 | F67: =C67+E67-D67 -> -350000000 | G67: =SUMIFS(JU!$H$180:$H$440,JU!$F$180:$F$440,WS!$A67) -> 0 | H67: =SUMIFS(JU!$K$180:$K$440,JU!$I$180:$I$440,WS!$A67) -> 0 | I67: =F67+H67-G67 -> -350000000 | J67: =SUMIFS(JU!$H$441:$H$695,JU!$F$441:$F$695,WS!$A67) -> 0 | K67: =SUMIFS(JU!$K$441:$K$695,JU!$I$441:$I$695,WS!$A67) -> 0 | L67: =I67+K67-J67 -> -350000000 | M67: =SUMIFS(JU!$H$696:$H$1062,JU!$F$696:$F$1062,$A67) -> 0 | N67: =SUMIFS(JU!$K$696:$K$1062,JU!$I$696:$I$1062,WS!$A67) -> 0 | O67: =L67+N67-M67 -> -350000000 | P67: =SUMIFS(JU!$H$1063:$H$5007,JU!$F$1063:$F$5007,WS!$A67) -> 0 | Q67: =SUMIFS(JU!$K$1063:$K$5007,JU!$I$1063:$I$5007,WS!$A67) -> 0 | R67: =O67+Q67-P67 -> -350000000 | S67: =SUMIFS(JU!$H$5107:$H$5107,JU!$F$5107:$F$5107,WS!$A67) -> 0 | T67: =SUMIFS(JU!$K$5107:$K$5107,JU!$I$5107:$I$5107,WS!$A67) -> 0 | U67: =R67+T67-S67 -> -350000000 | V67: =SUMIFS(JU!$H$5107:$H$5107,JU!$F$5107:$F$5107,WS!$A67) -> 0 | W67: =SUMIFS(JU!$K$5107:$K$5107,JU!$I$5107:$I$5107,WS!$A67) -> 0 | X67: =U67+W67-V67 -> -350000000 | Y67: =SUMIFS(JU!$H$5107:$H$5107,JU!$F$5107:$F$5107,WS!$A67) -> 0 | Z67: =SUMIFS(JU!$K$5107:$K$5107,JU!$I$5107:$I$5107,WS!$A67) -> 0 | AA67: =X67+Z67-Y67 -> -350000000 | AB67: =SUMIFS(JU!$H$5107:$H$5107,JU!$F$5107:$F$5107,WS!$A67) -> 0 | AC67: =SUMIFS(JU!$K$5107:$K$5107,JU!$I$5107:$I$5107,WS!$A67) -> 0 | AD67: =AA67+AC67-AB67 -> -350000000 | AE67: =SUMIFS(JU!$H$5107:$H$5107,JU!$F$5107:$F$5107,WS!$A67) -> 0 | AF67: =SUMIFS(JU!$K$5107:$K$5107,JU!$I$5107:$I$5107,WS!$A67) -> 0 | AG67: =AD67+AF67-AE67 -> -350000000 | AH67: =SUMIFS(JU!$H$5107:$H$5107,JU!$F$5107:$F$5107,WS!$A67) -> 0 | AI67: =SUMIFS(JU!$K$5107:$K$5107,JU!$I$5107:$I$5107,WS!$A67) -> 0 | AJ67: =AG67+AI67-AH67 -> -350000000 | AK67: =SUMIFS(JU!$H$5107:$H$5107,JU!$F$5107:$F$5107,WS!$A67) -> 0 | AL67: =SUMIFS(JU!$K$5107:$K$5107,JU!$I$5107:$I$5107,WS!$A67) -> 0 | AM67: =AJ67+AL67-AK67 -> -350000000
A68: 2205 | B68: Liabilitas Imbalan Kerja | C68: 0 | D68: =SUMIFS(JU!$H$5:$H$178,JU!$F$5:$F$178,WS!$A68) -> 0 | E68: =SUMIFS(JU!$K$5:$K$178,JU!$I$5:$I$178,WS!$A68) -> 0 | F68: =C68+E68-D68 -> 0 | G68: =SUMIFS(JU!$H$180:$H$440,JU!$F$180:$F$440,WS!$A68) -> 0 | H68: =SUMIFS(JU!$K$180:$K$440,JU!$I$180:$I$440,WS!$A68) -> 0 | I68: =F68+H68-G68 -> 0 | J68: =SUMIFS(JU!$H$441:$H$695,JU!$F$441:$F$695,WS!$A68) -> 0 | K68: =SUMIFS(JU!$K$441:$K$695,JU!$I$441:$I$695,WS!$A68) -> 0 | L68: =I68+K68-J68 -> 0 | M68: =SUMIFS(JU!$H$696:$H$1062,JU!$F$696:$F$1062,$A68) -> 0 | N68: =SUMIFS(JU!$K$696:$K$1062,JU!$I$696:$I$1062,WS!$A68) -> 0 | O68: =L68+N68-M68 -> 0 | P68: =SUMIFS(JU!$H$1063:$H$5007,JU!$F$1063:$F$5007,WS!$A68) -> 0 | Q68: =SUMIFS(JU!$K$1063:$K$5007,JU!$I$1063:$I$5007,WS!$A68) -> 0 | R68: =O68+Q68-P68 -> 0 | S68: =SUMIFS(JU!$H$5107:$H$5107,JU!$F$5107:$F$5107,WS!$A68) -> 0 | T68: =SUMIFS(JU!$K$5107:$K$5107,JU!$I$5107:$I$5107,WS!$A68) -> 0 | U68: =R68+T68-S68 -> 0 | V68: =SUMIFS(JU!$H$5107:$H$5107,JU!$F$5107:$F$5107,WS!$A68) -> 0 | W68: =SUMIFS(JU!$K$5107:$K$5107,JU!$I$5107:$I$5107,WS!$A68) -> 0 | X68: =U68+W68-V68 -> 0 | Y68: =SUMIFS(JU!$H$5107:$H$5107,JU!$F$5107:$F$5107,WS!$A68) -> 0 | Z68: =SUMIFS(JU!$K$5107:$K$5107,JU!$I$5107:$I$5107,WS!$A68) -> 0 | AA68: =X68+Z68-Y68 -> 0 | AB68: =SUMIFS(JU!$H$5107:$H$5107,JU!$F$5107:$F$5107,WS!$A68) -> 0 | AC68: =SUMIFS(JU!$K$5107:$K$5107,JU!$I$5107:$I$5107,WS!$A68) -> 0 | AD68: =AA68+AC68-AB68 -> 0 | AE68: =SUMIFS(JU!$H$5107:$H$5107,JU!$F$5107:$F$5107,WS!$A68) -> 0 | AF68: =SUMIFS(JU!$K$5107:$K$5107,JU!$I$5107:$I$5107,WS!$A68) -> 0 | AG68: =AD68+AF68-AE68 -> 0 | AH68: =SUMIFS(JU!$H$5107:$H$5107,JU!$F$5107:$F$5107,WS!$A68) -> 0 | AI68: =SUMIFS(JU!$K$5107:$K$5107,JU!$I$5107:$I$5107,WS!$A68) -> 0 | AJ68: =AG68+AI68-AH68 -> 0 | AK68: =SUMIFS(JU!$H$5107:$H$5107,JU!$F$5107:$F$5107,WS!$A68) -> 0 | AL68: =SUMIFS(JU!$K$5107:$K$5107,JU!$I$5107:$I$5107,WS!$A68) -> 0 | AM68: =AJ68+AL68-AK68 -> 0
A69: Total Kewajiban Jangka Panjang | C69: 390370000 | D69: =SUMIFS(JU!$H$5:$H$178,JU!$F$5:$F$178,WS!$A69) -> 0 | E69: =SUMIFS(JU!$K$5:$K$178,JU!$I$5:$I$178,WS!$A69) -> 0 | F69: =SUM(F64:F68) -> 390370000 | G69: =SUMIFS(JU!$H$180:$H$440,JU!$F$180:$F$440,WS!$A69) -> 0 | H69: =SUMIFS(JU!$K$180:$K$440,JU!$I$180:$I$440,WS!$A69) -> 0 | I69: =SUM(I64:I68) -> 366370000 | J69: =SUMIFS(JU!$H$441:$H$695,JU!$F$441:$F$695,WS!$A69) -> 0 | K69: =SUMIFS(JU!$K$441:$K$695,JU!$I$441:$I$695,WS!$A69) -> 0 | L69: =SUM(L64:L68) -> 342370000 | M69: =SUMIFS(JU!$H$696:$H$1062,JU!$F$696:$F$1062,$A69) -> 0 | N69: =SUMIFS(JU!$K$696:$K$1062,JU!$I$696:$I$1062,WS!$A69) -> 0 | O69: =SUM(O64:O68) -> 998370000 | P69: =SUMIFS(JU!$H$1063:$H$5007,JU!$F$1063:$F$5007,WS!$A69) -> 0 | Q69: =SUMIFS(JU!$K$1063:$K$5007,JU!$I$1063:$I$5007,WS!$A69) -> 0 | R69: =SUM(R64:R68) -> 1288636646 | S69: =SUMIFS(JU!$H$5107:$H$5107,JU!$F$5107:$F$5107,WS!$A69) -> 0 | T69: =SUMIFS(JU!$K$5107:$K$5107,JU!$I$5107:$I$5107,WS!$A69) -> 0 | U69: =SUM(U64:U68) -> 1288636646 | V69: =SUMIFS(JU!$H$5107:$H$5107,JU!$F$5107:$F$5107,WS!$A69) -> 0 | W69: =SUMIFS(JU!$K$5107:$K$5107,JU!$I$5107:$I$5107,WS!$A69) -> 0 | X69: =SUM(X64:X68) -> 1288636646 | Y69: =SUMIFS(JU!$H$5107:$H$5107,JU!$F$5107:$F$5107,WS!$A69) -> 0 | Z69: =SUMIFS(JU!$K$5107:$K$5107,JU!$I$5107:$I$5107,WS!$A69) -> 0 | AA69: =SUM(AA64:AA68) -> 1288636646 | AB69: =SUMIFS(JU!$H$5107:$H$5107,JU!$F$5107:$F$5107,WS!$A69) -> 0 | AC69: =SUMIFS(JU!$K$5107:$K$5107,JU!$I$5107:$I$5107,WS!$A69) -> 0 | AD69: =SUM(AD64:AD68) -> 1288636646 | AE69: =SUMIFS(JU!$H$5107:$H$5107,JU!$F$5107:$F$5107,WS!$A69) -> 0 | AF69: =SUMIFS(JU!$K$5107:$K$5107,JU!$I$5107:$I$5107,WS!$A69) -> 0 | AG69: =SUM(AG64:AG68) -> 1288636646 | AH69: =SUMIFS(JU!$H$5107:$H$5107,JU!$F$5107:$F$5107,WS!$A69) -> 0 | AI69: =SUMIFS(JU!$K$5107:$K$5107,JU!$I$5107:$I$5107,WS!$A69) -> 0 | AJ69: =SUM(AJ64:AJ68) -> 1288636646 | AK69: =SUMIFS(JU!$H$5107:$H$5107,JU!$F$5107:$F$5107,WS!$A69) -> 0 | AL69: =SUMIFS(JU!$K$5107:$K$5107,JU!$I$5107:$I$5107,WS!$A69) -> 0 | AM69: =SUM(AM64:AM68) -> 1288636646
A70: Total Kewajiban | C70: 1913086000 | D70: =SUMIFS(JU!$H$5:$H$178,JU!$F$5:$F$178,WS!$A70) -> 0 | E70: =SUMIFS(JU!$K$5:$K$178,JU!$I$5:$I$178,WS!$A70) -> 0 | F70: =F69+F62 -> 2433345094 | G70: =SUMIFS(JU!$H$180:$H$440,JU!$F$180:$F$440,WS!$A70) -> 0 | H70: =SUMIFS(JU!$K$180:$K$440,JU!$I$180:$I$440,WS!$A70) -> 0 | I70: =I69+I62 -> 4011563394 | J70: =SUMIFS(JU!$H$441:$H$695,JU!$F$441:$F$695,WS!$A70) -> 0 | K70: =SUMIFS(JU!$K$441:$K$695,JU!$I$441:$I$695,WS!$A70) -> 0 | L70: =L69+L62 -> 6672435894 | M70: =SUMIFS(JU!$H$696:$H$1062,JU!$F$696:$F$1062,$A70) -> 0 | N70: =SUMIFS(JU!$K$696:$K$1062,JU!$I$696:$I$1062,WS!$A70) -> 0 | O70: =O69+O62 -> 5984251082 | P70: =SUMIFS(JU!$H$1063:$H$5007,JU!$F$1063:$F$5007,WS!$A70) -> 0 | Q70: =SUMIFS(JU!$K$1063:$K$5007,JU!$I$1063:$I$5007,WS!$A70) -> 0 | R70: =R69+R62 -> 7.0752142e+09 | S70: =SUMIFS(JU!$H$5107:$H$5107,JU!$F$5107:$F$5107,WS!$A70) -> 0 | T70: =SUMIFS(JU!$K$5107:$K$5107,JU!$I$5107:$I$5107,WS!$A70) -> 0 | U70: =U69+U62 -> 7.0752142e+09 | V70: =SUMIFS(JU!$H$5107:$H$5107,JU!$F$5107:$F$5107,WS!$A70) -> 0 | W70: =SUMIFS(JU!$K$5107:$K$5107,JU!$I$5107:$I$5107,WS!$A70) -> 0 | X70: =X69+X62 -> 7.0752142e+09 | Y70: =SUMIFS(JU!$H$5107:$H$5107,JU!$F$5107:$F$5107,WS!$A70) -> 0 | Z70: =SUMIFS(JU!$K$5107:$K$5107,JU!$I$5107:$I$5107,WS!$A70) -> 0 | AA70: =AA69+AA62 -> 7.0752142e+09 | AB70: =SUMIFS(JU!$H$5107:$H$5107,JU!$F$5107:$F$5107,WS!$A70) -> 0 | AC70: =SUMIFS(JU!$K$5107:$K$5107,JU!$I$5107:$I$5107,WS!$A70) -> 0 | AD70: =AD69+AD62 -> 7.0752142e+09 | AE70: =SUMIFS(JU!$H$5107:$H$5107,JU!$F$5107:$F$5107,WS!$A70) -> 0 | AF70: =SUMIFS(JU!$K$5107:$K$5107,JU!$I$5107:$I$5107,WS!$A70) -> 0 | AG70: =AG69+AG62 -> 7.0752142e+09 | AH70: =SUMIFS(JU!$H$5107:$H$5107,JU!$F$5107:$F$5107,WS!$A70) -> 0 | AI70: =SUMIFS(JU!$K$5107:$K$5107,JU!$I$5107:$I$5107,WS!$A70) -> 0 | AJ70: =AJ69+AJ62 -> 7.0752142e+09 | AK70: =SUMIFS(JU!$H$5107:$H$5107,JU!$F$5107:$F$5107,WS!$A70) -> 0 | AL70: =SUMIFS(JU!$K$5107:$K$5107,JU!$I$5107:$I$5107,WS!$A70) -> 0 | AM70: =AM69+AM62 -> 7.0752142e+09
A71: Ekuitas | D71: =SUMIFS(JU!$H$5:$H$178,JU!$F$5:$F$178,WS!$A71) -> 0 | E71: =SUMIFS(JU!$K$5:$K$178,JU!$I$5:$I$178,WS!$A71) -> 0 | G71: =SUMIFS(JU!$H$180:$H$440,JU!$F$180:$F$440,WS!$A71) -> 0 | H71: =SUMIFS(JU!$K$180:$K$440,JU!$I$180:$I$440,WS!$A71) -> 0 | J71: =SUMIFS(JU!$H$441:$H$695,JU!$F$441:$F$695,WS!$A71) -> 0 | K71: =SUMIFS(JU!$K$441:$K$695,JU!$I$441:$I$695,WS!$A71) -> 0 | M71: =SUMIFS(JU!$H$696:$H$1062,JU!$F$696:$F$1062,$A71) -> 0 | N71: =SUMIFS(JU!$K$696:$K$1062,JU!$I$696:$I$1062,WS!$A71) -> 0 | P71: =SUMIFS(JU!$H$1063:$H$5007,JU!$F$1063:$F$5007,WS!$A71) -> 0 | Q71: =SUMIFS(JU!$K$1063:$K$5007,JU!$I$1063:$I$5007,WS!$A71) -> 0 | S71: =SUMIFS(JU!$H$5107:$H$5107,JU!$F$5107:$F$5107,WS!$A71) -> 0 | T71: =SUMIFS(JU!$K$5107:$K$5107,JU!$I$5107:$I$5107,WS!$A71) -> 0 | V71: =SUMIFS(JU!$H$5107:$H$5107,JU!$F$5107:$F$5107,WS!$A71) -> 0 | W71: =SUMIFS(JU!$K$5107:$K$5107,JU!$I$5107:$I$5107,WS!$A71) -> 0 | Y71: =SUMIFS(JU!$H$5107:$H$5107,JU!$F$5107:$F$5107,WS!$A71) -> 0 | Z71: =SUMIFS(JU!$K$5107:$K$5107,JU!$I$5107:$I$5107,WS!$A71) -> 0 | AB71: =SUMIFS(JU!$H$5107:$H$5107,JU!$F$5107:$F$5107,WS!$A71) -> 0 | AC71: =SUMIFS(JU!$K$5107:$K$5107,JU!$I$5107:$I$5107,WS!$A71) -> 0 | AE71: =SUMIFS(JU!$H$5107:$H$5107,JU!$F$5107:$F$5107,WS!$A71) -> 0 | AF71: =SUMIFS(JU!$K$5107:$K$5107,JU!$I$5107:$I$5107,WS!$A71) -> 0 | AH71: =SUMIFS(JU!$H$5107:$H$5107,JU!$F$5107:$F$5107,WS!$A71) -> 0 | AI71: =SUMIFS(JU!$K$5107:$K$5107,JU!$I$5107:$I$5107,WS!$A71) -> 0 | AK71: =SUMIFS(JU!$H$5107:$H$5107,JU!$F$5107:$F$5107,WS!$A71) -> 0 | AL71: =SUMIFS(JU!$K$5107:$K$5107,JU!$I$5107:$I$5107,WS!$A71) -> 0
A72: 3101 | B72: Modal Disetor | C72: 0 | D72: =SUMIFS(JU!$H$5:$H$178,JU!$F$5:$F$178,WS!$A72) -> 0 | E72: =SUMIFS(JU!$K$5:$K$178,JU!$I$5:$I$178,WS!$A72) -> 0 | F72: =C72+E72-D72 -> 0 | G72: =SUMIFS(JU!$H$180:$H$440,JU!$F$180:$F$440,WS!$A72) -> 0 | H72: =SUMIFS(JU!$K$180:$K$440,JU!$I$180:$I$440,WS!$A72) -> 0 | I72: =F72+H72-G72 -> 0 | J72: =SUMIFS(JU!$H$441:$H$695,JU!$F$441:$F$695,WS!$A72) -> 0 | K72: =SUMIFS(JU!$K$441:$K$695,JU!$I$441:$I$695,WS!$A72) -> 0 | L72: =I72+K72-J72 -> 0 | M72: =SUMIFS(JU!$H$696:$H$1062,JU!$F$696:$F$1062,$A72) -> 0 | N72: =SUMIFS(JU!$K$696:$K$1062,JU!$I$696:$I$1062,WS!$A72) -> 0 | O72: =L72+N72-M72 -> 0 | P72: =SUMIFS(JU!$H$1063:$H$5007,JU!$F$1063:$F$5007,WS!$A72) -> 0 | Q72: =SUMIFS(JU!$K$1063:$K$5007,JU!$I$1063:$I$5007,WS!$A72) -> 0 | R72: =O72+Q72-P72 -> 0 | S72: =SUMIFS(JU!$H$5107:$H$5107,JU!$F$5107:$F$5107,WS!$A72) -> 0 | T72: =SUMIFS(JU!$K$5107:$K$5107,JU!$I$5107:$I$5107,WS!$A72) -> 0 | U72: =R72+T72-S72 -> 0 | V72: =SUMIFS(JU!$H$5107:$H$5107,JU!$F$5107:$F$5107,WS!$A72) -> 0 | W72: =SUMIFS(JU!$K$5107:$K$5107,JU!$I$5107:$I$5107,WS!$A72) -> 0 | X72: =U72+W72-V72 -> 0 | Y72: =SUMIFS(JU!$H$5107:$H$5107,JU!$F$5107:$F$5107,WS!$A72) -> 0 | Z72: =SUMIFS(JU!$K$5107:$K$5107,JU!$I$5107:$I$5107,WS!$A72) -> 0 | AA72: =X72+Z72-Y72 -> 0 | AB72: =SUMIFS(JU!$H$5107:$H$5107,JU!$F$5107:$F$5107,WS!$A72) -> 0 | AC72: =SUMIFS(JU!$K$5107:$K$5107,JU!$I$5107:$I$5107,WS!$A72) -> 0 | AD72: =AA72+AC72-AB72 -> 0 | AE72: =SUMIFS(JU!$H$5107:$H$5107,JU!$F$5107:$F$5107,WS!$A72) -> 0 | AF72: =SUMIFS(JU!$K$5107:$K$5107,JU!$I$5107:$I$5107,WS!$A72) -> 0 | AG72: =AD72+AF72-AE72 -> 0 | AH72: =SUMIFS(JU!$H$5107:$H$5107,JU!$F$5107:$F$5107,WS!$A72) -> 0 | AI72: =SUMIFS(JU!$K$5107:$K$5107,JU!$I$5107:$I$5107,WS!$A72) -> 0 | AJ72: =AG72+AI72-AH72 -> 0 | AK72: =SUMIFS(JU!$H$5107:$H$5107,JU!$F$5107:$F$5107,WS!$A72) -> 0 | AL72: =SUMIFS(JU!$K$5107:$K$5107,JU!$I$5107:$I$5107,WS!$A72) -> 0 | AM72: =AJ72+AL72-AK72 -> 0
A73: 3102 | B73: Tambahan Modal Disetor | C73: 0 | D73: =SUMIFS(JU!$H$5:$H$178,JU!$F$5:$F$178,WS!$A73) -> 0 | E73: =SUMIFS(JU!$K$5:$K$178,JU!$I$5:$I$178,WS!$A73) -> 0 | F73: =C73+E73-D73 -> 0 | G73: =SUMIFS(JU!$H$180:$H$440,JU!$F$180:$F$440,WS!$A73) -> 0 | H73: =SUMIFS(JU!$K$180:$K$440,JU!$I$180:$I$440,WS!$A73) -> 0 | I73: =F73+H73-G73 -> 0 | J73: =SUMIFS(JU!$H$441:$H$695,JU!$F$441:$F$695,WS!$A73) -> 0 | K73: =SUMIFS(JU!$K$441:$K$695,JU!$I$441:$I$695,WS!$A73) -> 0 | L73: =I73+K73-J73 -> 0 | M73: =SUMIFS(JU!$H$696:$H$1062,JU!$F$696:$F$1062,$A73) -> 0 | N73: =SUMIFS(JU!$K$696:$K$1062,JU!$I$696:$I$1062,WS!$A73) -> 0 | O73: =L73+N73-M73 -> 0 | P73: =SUMIFS(JU!$H$1063:$H$5007,JU!$F$1063:$F$5007,WS!$A73) -> 0 | Q73: =SUMIFS(JU!$K$1063:$K$5007,JU!$I$1063:$I$5007,WS!$A73) -> 0 | R73: =O73+Q73-P73 -> 0 | S73: =SUMIFS(JU!$H$5107:$H$5107,JU!$F$5107:$F$5107,WS!$A73) -> 0 | T73: =SUMIFS(JU!$K$5107:$K$5107,JU!$I$5107:$I$5107,WS!$A73) -> 0 | U73: =R73+T73-S73 -> 0 | V73: =SUMIFS(JU!$H$5107:$H$5107,JU!$F$5107:$F$5107,WS!$A73) -> 0 | W73: =SUMIFS(JU!$K$5107:$K$5107,JU!$I$5107:$I$5107,WS!$A73) -> 0 | X73: =U73+W73-V73 -> 0 | Y73: =SUMIFS(JU!$H$5107:$H$5107,JU!$F$5107:$F$5107,WS!$A73) -> 0 | Z73: =SUMIFS(JU!$K$5107:$K$5107,JU!$I$5107:$I$5107,WS!$A73) -> 0 | AA73: =X73+Z73-Y73 -> 0 | AB73: =SUMIFS(JU!$H$5107:$H$5107,JU!$F$5107:$F$5107,WS!$A73) -> 0 | AC73: =SUMIFS(JU!$K$5107:$K$5107,JU!$I$5107:$I$5107,WS!$A73) -> 0 | AD73: =AA73+AC73-AB73 -> 0 | AE73: =SUMIFS(JU!$H$5107:$H$5107,JU!$F$5107:$F$5107,WS!$A73) -> 0 | AF73: =SUMIFS(JU!$K$5107:$K$5107,JU!$I$5107:$I$5107,WS!$A73) -> 0 | AG73: =AD73+AF73-AE73 -> 0 | AH73: =SUMIFS(JU!$H$5107:$H$5107,JU!$F$5107:$F$5107,WS!$A73) -> 0 | AI73: =SUMIFS(JU!$K$5107:$K$5107,JU!$I$5107:$I$5107,WS!$A73) -> 0 | AJ73: =AG73+AI73-AH73 -> 0 | AK73: =SUMIFS(JU!$H$5107:$H$5107,JU!$F$5107:$F$5107,WS!$A73) -> 0 | AL73: =SUMIFS(JU!$K$5107:$K$5107,JU!$I$5107:$I$5107,WS!$A73) -> 0 | AM73: =AJ73+AL73-AK73 -> 0
A74: 3103 | B74: Laba Ditahan | C74: 3.5410921e+09 | D74: =SUMIFS(JU!$H$5:$H$178,JU!$F$5:$F$178,WS!$A74) -> 0 | E74: =SUMIFS(JU!$K$5:$K$178,JU!$I$5:$I$178,WS!$A74) -> 0 | F74: =C74+E74-D74 -> 3.5410921e+09 | G74: =SUMIFS(JU!$H$180:$H$440,JU!$F$180:$F$440,WS!$A74) -> 0 | H74: =SUMIFS(JU!$K$180:$K$440,JU!$I$180:$I$440,WS!$A74) -> 0 | I74: =F74+F75 -> 3.4823315e+09 | J74: =SUMIFS(JU!$H$441:$H$695,JU!$F$441:$F$695,WS!$A74) -> 0 | K74: =SUMIFS(JU!$K$441:$K$695,JU!$I$441:$I$695,WS!$A74) -> 0 | L74: =I74+I75 -> 3.466129e+09 | M74: =SUMIFS(JU!$H$696:$H$1062,JU!$F$696:$F$1062,$A74) -> 0 | N74: =SUMIFS(JU!$K$696:$K$1062,JU!$I$696:$I$1062,WS!$A74) -> 0 | O74: =L74+L75 -> 3.5837932e+09 | P74: =SUMIFS(JU!$H$1063:$H$5007,JU!$F$1063:$F$5007,WS!$A74) -> 0 | Q74: =SUMIFS(JU!$K$1063:$K$5007,JU!$I$1063:$I$5007,WS!$A74) -> 0 | R74: =O74+O75 -> 4.7787257e+09 | S74: =SUMIFS(JU!$H$5107:$H$5107,JU!$F$5107:$F$5107,WS!$A74) -> 0 | T74: =SUMIFS(JU!$K$5107:$K$5107,JU!$I$5107:$I$5107,WS!$A74) -> 0 | U74: =R74+R75 -> 6.6800298e+09 | V74: =SUMIFS(JU!$H$5107:$H$5107,JU!$F$5107:$F$5107,WS!$A74) -> 0 | W74: =SUMIFS(JU!$K$5107:$K$5107,JU!$I$5107:$I$5107,WS!$A74) -> 0 | X74: =U74+U75 -> 6.6800298e+09 | Y74: =SUMIFS(JU!$H$5107:$H$5107,JU!$F$5107:$F$5107,WS!$A74) -> 0 | Z74: =SUMIFS(JU!$K$5107:$K$5107,JU!$I$5107:$I$5107,WS!$A74) -> 0 | AA74: =X74+X75 -> 6.6800298e+09 | AB74: =SUMIFS(JU!$H$5107:$H$5107,JU!$F$5107:$F$5107,WS!$A74) -> 0 | AC74: =SUMIFS(JU!$K$5107:$K$5107,JU!$I$5107:$I$5107,WS!$A74) -> 0 | AD74: =AA74+AA75 -> 6.6800298e+09 | AE74: =SUMIFS(JU!$H$5107:$H$5107,JU!$F$5107:$F$5107,WS!$A74) -> 0 | AF74: =SUMIFS(JU!$K$5107:$K$5107,JU!$I$5107:$I$5107,WS!$A74) -> 0 | AG74: =AD74+AD75 -> 6.6800298e+09 | AH74: =SUMIFS(JU!$H$5107:$H$5107,JU!$F$5107:$F$5107,WS!$A74) -> 0 | AI74: =SUMIFS(JU!$K$5107:$K$5107,JU!$I$5107:$I$5107,WS!$A74) -> 0 | AJ74: =AG74+AG75 -> 6.6800298e+09 | AK74: =SUMIFS(JU!$H$5107:$H$5107,JU!$F$5107:$F$5107,WS!$A74) -> 0 | AL74: =SUMIFS(JU!$K$5107:$K$5107,JU!$I$5107:$I$5107,WS!$A74) -> 0 | AM74: =AJ74+AJ75 -> 6.6800298e+09 | AN74: 2870516042
A75: 3104 | B75: Laba Tahun Berjalan | D75: =SUMIFS(JU!$H$5:$H$178,JU!$F$5:$F$178,WS!$A75) -> 0 | E75: =SUMIFS(JU!$K$5:$K$178,JU!$I$5:$I$178,WS!$A75) -> 0 | F75: =F3 -> -58760634 | G75: =SUMIFS(JU!$H$180:$H$440,JU!$F$180:$F$440,WS!$A75) -> 0 | H75: =SUMIFS(JU!$K$180:$K$440,JU!$I$180:$I$440,WS!$A75) -> 0 | I75: =I3 -> -16202453 | J75: =SUMIFS(JU!$H$441:$H$695,JU!$F$441:$F$695,WS!$A75) -> 0 | K75: =SUMIFS(JU!$K$441:$K$695,JU!$I$441:$I$695,WS!$A75) -> 0 | L75: =L3 -> 117664143 | M75: =SUMIFS(JU!$H$696:$H$1062,JU!$F$696:$F$1062,$A75) -> 0 | N75: =SUMIFS(JU!$K$696:$K$1062,JU!$I$696:$I$1062,WS!$A75) -> 0 | O75: =O3 -> 1194932519 | P75: =SUMIFS(JU!$H$1063:$H$5007,JU!$F$1063:$F$5007,WS!$A75) -> 0 | Q75: =SUMIFS(JU!$K$1063:$K$5007,JU!$I$1063:$I$5007,WS!$A75) -> 0 | R75: =R3 -> 1901304172 | S75: =SUMIFS(JU!$H$5107:$H$5107,JU!$F$5107:$F$5107,WS!$A75) -> 0 | T75: =SUMIFS(JU!$K$5107:$K$5107,JU!$I$5107:$I$5107,WS!$A75) -> 0 | U75: =U3 -> 0 | V75: =SUMIFS(JU!$H$5107:$H$5107,JU!$F$5107:$F$5107,WS!$A75) -> 0 | W75: =SUMIFS(JU!$K$5107:$K$5107,JU!$I$5107:$I$5107,WS!$A75) -> 0 | X75: =X3 -> 0 | Y75: =SUMIFS(JU!$H$5107:$H$5107,JU!$F$5107:$F$5107,WS!$A75) -> 0 | Z75: =SUMIFS(JU!$K$5107:$K$5107,JU!$I$5107:$I$5107,WS!$A75) -> 0 | AA75: =AA3 -> 0 | AB75: =SUMIFS(JU!$H$5107:$H$5107,JU!$F$5107:$F$5107,WS!$A75) -> 0 | AC75: =SUMIFS(JU!$K$5107:$K$5107,JU!$I$5107:$I$5107,WS!$A75) -> 0 | AD75: =AD3 -> 0 | AE75: =SUMIFS(JU!$H$5107:$H$5107,JU!$F$5107:$F$5107,WS!$A75) -> 0 | AF75: =SUMIFS(JU!$K$5107:$K$5107,JU!$I$5107:$I$5107,WS!$A75) -> 0 | AG75: =AG3 -> 0 | AH75: =SUMIFS(JU!$H$5107:$H$5107,JU!$F$5107:$F$5107,WS!$A75) -> 0 | AI75: =SUMIFS(JU!$K$5107:$K$5107,JU!$I$5107:$I$5107,WS!$A75) -> 0 | AJ75: =AJ3 -> 0 | AK75: =SUMIFS(JU!$H$5107:$H$5107,JU!$F$5107:$F$5107,WS!$A75) -> 0 | AL75: =SUMIFS(JU!$K$5107:$K$5107,JU!$I$5107:$I$5107,WS!$A75) -> 0 | AM75: =AM3 -> 0 | AN75: =AN74-AD74-AD75 -> -3.8095138e+09 | AO75: =150000*29 -> 4350000
A76: 3105 | B76: Dividen | C76: 0 | D76: =SUMIFS(JU!$H$5:$H$178,JU!$F$5:$F$178,WS!$A76) -> 0 | E76: =SUMIFS(JU!$K$5:$K$178,JU!$I$5:$I$178,WS!$A76) -> 0 | F76: =C76+E76-D76 -> 0 | G76: =SUMIFS(JU!$H$180:$H$440,JU!$F$180:$F$440,WS!$A76) -> 0 | H76: =SUMIFS(JU!$K$180:$K$440,JU!$I$180:$I$440,WS!$A76) -> 0 | I76: =F76+H76-G76 -> 0 | J76: =SUMIFS(JU!$H$441:$H$695,JU!$F$441:$F$695,WS!$A76) -> 0 | K76: =SUMIFS(JU!$K$441:$K$695,JU!$I$441:$I$695,WS!$A76) -> 0 | L76: =I76+K76-J76 -> 0 | M76: =SUMIFS(JU!$H$696:$H$1062,JU!$F$696:$F$1062,$A76) -> 0 | N76: =SUMIFS(JU!$K$696:$K$1062,JU!$I$696:$I$1062,WS!$A76) -> 0 | O76: =L76+N76-M76 -> 0 | P76: =SUMIFS(JU!$H$1063:$H$5007,JU!$F$1063:$F$5007,WS!$A76) -> 0 | Q76: =SUMIFS(JU!$K$1063:$K$5007,JU!$I$1063:$I$5007,WS!$A76) -> 0 | R76: =O76+Q76-P76 -> 0 | S76: =SUMIFS(JU!$H$5107:$H$5107,JU!$F$5107:$F$5107,WS!$A76) -> 0 | T76: =SUMIFS(JU!$K$5107:$K$5107,JU!$I$5107:$I$5107,WS!$A76) -> 0 | U76: =R76+T76-S76 -> 0 | V76: =SUMIFS(JU!$H$5107:$H$5107,JU!$F$5107:$F$5107,WS!$A76) -> 0 | W76: =SUMIFS(JU!$K$5107:$K$5107,JU!$I$5107:$I$5107,WS!$A76) -> 0 | X76: =U76+W76-V76 -> 0 | Y76: =SUMIFS(JU!$H$5107:$H$5107,JU!$F$5107:$F$5107,WS!$A76) -> 0 | Z76: =SUMIFS(JU!$K$5107:$K$5107,JU!$I$5107:$I$5107,WS!$A76) -> 0 | AA76: =X76+Z76-Y76 -> 0 | AB76: =SUMIFS(JU!$H$5107:$H$5107,JU!$F$5107:$F$5107,WS!$A76) -> 0 | AC76: =SUMIFS(JU!$K$5107:$K$5107,JU!$I$5107:$I$5107,WS!$A76) -> 0 | AD76: =AA76+AC76-AB76 -> 0 | AE76: =SUMIFS(JU!$H$5107:$H$5107,JU!$F$5107:$F$5107,WS!$A76) -> 0 | AF76: =SUMIFS(JU!$K$5107:$K$5107,JU!$I$5107:$I$5107,WS!$A76) -> 0 | AG76: =AD76+AF76-AE76 -> 0 | AH76: =SUMIFS(JU!$H$5107:$H$5107,JU!$F$5107:$F$5107,WS!$A76) -> 0 | AI76: =SUMIFS(JU!$K$5107:$K$5107,JU!$I$5107:$I$5107,WS!$A76) -> 0 | AJ76: =AG76+AI76-AH76 -> 0 | AK76: =SUMIFS(JU!$H$5107:$H$5107,JU!$F$5107:$F$5107,WS!$A76) -> 0 | AL76: =SUMIFS(JU!$K$5107:$K$5107,JU!$I$5107:$I$5107,WS!$A76) -> 0 | AM76: =AJ76+AL76-AK76 -> 0
A77: Total Ekuitas | C77: 3.5410921e+09 | D77: =SUMIFS(JU!$H$5:$H$178,JU!$F$5:$F$178,WS!$A77) -> 0 | E77: =SUMIFS(JU!$K$5:$K$178,JU!$I$5:$I$178,WS!$A77) -> 0 | F77: =SUM(F72:F76) -> 3.4823315e+09 | G77: =SUMIFS(JU!$H$180:$H$440,JU!$F$180:$F$440,WS!$A77) -> 0 | H77: =SUMIFS(JU!$K$180:$K$440,JU!$I$180:$I$440,WS!$A77) -> 0 | I77: =SUM(I72:I76) -> 3.466129e+09 | J77: =SUMIFS(JU!$H$441:$H$695,JU!$F$441:$F$695,WS!$A77) -> 0 | K77: =SUMIFS(JU!$K$441:$K$695,JU!$I$441:$I$695,WS!$A77) -> 0 | L77: =SUM(L72:L76) -> 3.5837932e+09 | M77: =SUMIFS(JU!$H$696:$H$1062,JU!$F$696:$F$1062,$A77) -> 0 | N77: =SUMIFS(JU!$K$696:$K$1062,JU!$I$696:$I$1062,WS!$A77) -> 0 | O77: =SUM(O72:O76) -> 4.7787257e+09 | P77: =SUMIFS(JU!$H$1063:$H$5007,JU!$F$1063:$F$5007,WS!$A77) -> 0 | Q77: =SUMIFS(JU!$K$1063:$K$5007,JU!$I$1063:$I$5007,WS!$A77) -> 0 | R77: =SUM(R72:R76) -> 6.6800298e+09 | S77: =SUMIFS(JU!$H$5107:$H$5107,JU!$F$5107:$F$5107,WS!$A77) -> 0 | T77: =SUMIFS(JU!$K$5107:$K$5107,JU!$I$5107:$I$5107,WS!$A77) -> 0 | U77: =SUM(U72:U76) -> 6.6800298e+09 | V77: =SUMIFS(JU!$H$5107:$H$5107,JU!$F$5107:$F$5107,WS!$A77) -> 0 | W77: =SUMIFS(JU!$K$5107:$K$5107,JU!$I$5107:$I$5107,WS!$A77) -> 0 | X77: =SUM(X72:X76) -> 6.6800298e+09 | Y77: =SUMIFS(JU!$H$5107:$H$5107,JU!$F$5107:$F$5107,WS!$A77) -> 0 | Z77: =SUMIFS(JU!$K$5107:$K$5107,JU!$I$5107:$I$5107,WS!$A77) -> 0 | AA77: =SUM(AA72:AA76) -> 6.6800298e+09 | AB77: =SUMIFS(JU!$H$5107:$H$5107,JU!$F$5107:$F$5107,WS!$A77) -> 0 | AC77: =SUMIFS(JU!$K$5107:$K$5107,JU!$I$5107:$I$5107,WS!$A77) -> 0 | AD77: =SUM(AD72:AD76) -> 6.6800298e+09 | AE77: =SUMIFS(JU!$H$5107:$H$5107,JU!$F$5107:$F$5107,WS!$A77) -> 0 | AF77: =SUMIFS(JU!$K$5107:$K$5107,JU!$I$5107:$I$5107,WS!$A77) -> 0 | AG77: =SUM(AG72:AG76) -> 6.6800298e+09 | AH77: =SUMIFS(JU!$H$5107:$H$5107,JU!$F$5107:$F$5107,WS!$A77) -> 0 | AI77: =SUMIFS(JU!$K$5107:$K$5107,JU!$I$5107:$I$5107,WS!$A77) -> 0 | AJ77: =SUM(AJ72:AJ76) -> 6.6800298e+09 | AK77: =SUMIFS(JU!$H$5107:$H$5107,JU!$F$5107:$F$5107,WS!$A77) -> 0 | AL77: =SUMIFS(JU!$K$5107:$K$5107,JU!$I$5107:$I$5107,WS!$A77) -> 0 | AM77: =SUM(AM72:AM76) -> 6.6800298e+09
A78: Total Kewajiban & Ekuitas | C78: 5.4541781e+09 | D78: =SUMIFS(JU!$H$5:$H$178,JU!$F$5:$F$178,WS!$A78) -> 0 | E78: =SUMIFS(JU!$K$5:$K$178,JU!$I$5:$I$178,WS!$A78) -> 0 | F78: =F77+F70 -> 5.9156766e+09 | G78: =SUMIFS(JU!$H$180:$H$440,JU!$F$180:$F$440,WS!$A78) -> 0 | H78: =SUMIFS(JU!$K$180:$K$440,JU!$I$180:$I$440,WS!$A78) -> 0 | I78: =I77+I70 -> 7.4776924e+09 | J78: =SUMIFS(JU!$H$441:$H$695,JU!$F$441:$F$695,WS!$A78) -> 0 | K78: =SUMIFS(JU!$K$441:$K$695,JU!$I$441:$I$695,WS!$A78) -> 0 | L78: =L77+L70 -> 1.0256229e+10 | M78: =SUMIFS(JU!$H$696:$H$1062,JU!$F$696:$F$1062,$A78) -> 0 | N78: =SUMIFS(JU!$K$696:$K$1062,JU!$I$696:$I$1062,WS!$A78) -> 0 | O78: =O77+O70 -> 1.0762977e+10 | P78: =SUMIFS(JU!$H$1063:$H$5007,JU!$F$1063:$F$5007,WS!$A78) -> 0 | Q78: =SUMIFS(JU!$K$1063:$K$5007,JU!$I$1063:$I$5007,WS!$A78) -> 0 | R78: =R77+R70 -> 1.3755244e+10 | S78: =SUMIFS(JU!$H$5107:$H$5107,JU!$F$5107:$F$5107,WS!$A78) -> 0 | T78: =SUMIFS(JU!$K$5107:$K$5107,JU!$I$5107:$I$5107,WS!$A78) -> 0 | U78: =U77+U70 -> 1.3755244e+10 | V78: =SUMIFS(JU!$H$5107:$H$5107,JU!$F$5107:$F$5107,WS!$A78) -> 0 | W78: =SUMIFS(JU!$K$5107:$K$5107,JU!$I$5107:$I$5107,WS!$A78) -> 0 | X78: =X77+X70 -> 1.3755244e+10 | Y78: =SUMIFS(JU!$H$5107:$H$5107,JU!$F$5107:$F$5107,WS!$A78) -> 0 | Z78: =SUMIFS(JU!$K$5107:$K$5107,JU!$I$5107:$I$5107,WS!$A78) -> 0 | AA78: =AA77+AA70 -> 1.3755244e+10 | AB78: =SUMIFS(JU!$H$5107:$H$5107,JU!$F$5107:$F$5107,WS!$A78) -> 0 | AC78: =SUMIFS(JU!$K$5107:$K$5107,JU!$I$5107:$I$5107,WS!$A78) -> 0 | AD78: =AD77+AD70 -> 1.3755244e+10 | AE78: =SUMIFS(JU!$H$5107:$H$5107,JU!$F$5107:$F$5107,WS!$A78) -> 0 | AF78: =SUMIFS(JU!$K$5107:$K$5107,JU!$I$5107:$I$5107,WS!$A78) -> 0 | AG78: =AG77+AG70 -> 1.3755244e+10 | AH78: =SUMIFS(JU!$H$5107:$H$5107,JU!$F$5107:$F$5107,WS!$A78) -> 0 | AI78: =SUMIFS(JU!$K$5107:$K$5107,JU!$I$5107:$I$5107,WS!$A78) -> 0 | AJ78: =AJ77+AJ70 -> 1.3755244e+10 | AK78: =SUMIFS(JU!$H$5107:$H$5107,JU!$F$5107:$F$5107,WS!$A78) -> 0 | AL78: =SUMIFS(JU!$K$5107:$K$5107,JU!$I$5107:$I$5107,WS!$A78) -> 0 | AM78: =AM77+AM70 -> 1.3755244e+10
B79: Control | C79: 0 | D79: =SUMIFS(JU!$H$5:$H$178,JU!$F$5:$F$178,WS!$A79) -> 0 | E79: =SUMIFS(JU!$K$5:$K$178,JU!$I$5:$I$178,WS!$A79) -> 0 | F79: =F78-F52 -> 0 | G79: =SUMIFS(JU!$H$180:$H$440,JU!$F$180:$F$440,WS!$A79) -> 0 | H79: =SUMIFS(JU!$K$180:$K$440,JU!$I$180:$I$440,WS!$A79) -> 0 | I79: =I78-I52 -> 0 | J79: =SUMIFS(JU!$H$441:$H$695,JU!$F$441:$F$695,WS!$A79) -> 0 | K79: =SUMIFS(JU!$K$441:$K$695,JU!$I$441:$I$695,WS!$A79) -> 0 | L79: =L78-L52 -> 0 | M79: =SUMIFS(JU!$H$696:$H$1062,JU!$F$696:$F$1062,$A79) -> 0 | N79: =SUMIFS(JU!$K$696:$K$1062,JU!$I$696:$I$1062,WS!$A79) -> 0 | O79: =O78-O52 -> 0 | P79: =SUMIFS(JU!$H$1063:$H$5007,JU!$F$1063:$F$5007,WS!$A79) -> 0 | Q79: =SUMIFS(JU!$K$1063:$K$5007,JU!$I$1063:$I$5007,WS!$A79) -> 0 | R79: =R78-R52 -> 0 | S79: =SUMIFS(JU!$H$5107:$H$5107,JU!$F$5107:$F$5107,WS!$A79) -> 0 | T79: =SUMIFS(JU!$K$5107:$K$5107,JU!$I$5107:$I$5107,WS!$A79) -> 0 | U79: =U78-U52 -> 0 | V79: =SUMIFS(JU!$H$5107:$H$5107,JU!$F$5107:$F$5107,WS!$A79) -> 0 | W79: =SUMIFS(JU!$K$5107:$K$5107,JU!$I$5107:$I$5107,WS!$A79) -> 0 | X79: =X78-X52 -> 0 | Y79: =SUMIFS(JU!$H$5107:$H$5107,JU!$F$5107:$F$5107,WS!$A79) -> 0 | Z79: =SUMIFS(JU!$K$5107:$K$5107,JU!$I$5107:$I$5107,WS!$A79) -> 0 | AA79: =AA78-AA52 -> 0 | AB79: =SUMIFS(JU!$H$5107:$H$5107,JU!$F$5107:$F$5107,WS!$A79) -> 0 | AC79: =SUMIFS(JU!$K$5107:$K$5107,JU!$I$5107:$I$5107,WS!$A79) -> 0 | AD79: =AD78-AD52 -> 0 | AE79: =SUMIFS(JU!$H$5107:$H$5107,JU!$F$5107:$F$5107,WS!$A79) -> 0 | AF79: =SUMIFS(JU!$K$5107:$K$5107,JU!$I$5107:$I$5107,WS!$A79) -> 0 | AG79: =AG78-AG52 -> 0 | AH79: =SUMIFS(JU!$H$5107:$H$5107,JU!$F$5107:$F$5107,WS!$A79) -> 0 | AI79: =SUMIFS(JU!$K$5107:$K$5107,JU!$I$5107:$I$5107,WS!$A79) -> 0 | AJ79: =AJ78-AJ52 -> 0 | AK79: =SUMIFS(JU!$H$5107:$H$5107,JU!$F$5107:$F$5107,WS!$A79) -> 0 | AL79: =SUMIFS(JU!$K$5107:$K$5107,JU!$I$5107:$I$5107,WS!$A79) -> 0 | AM79: =AM78-AM52 -> 0
A80: Pendapatan Penjualan | D80: =SUMIFS(JU!$H$5:$H$178,JU!$F$5:$F$178,WS!$A80) -> 0 | E80: =SUMIFS(JU!$K$5:$K$178,JU!$I$5:$I$178,WS!$A80) -> 0 | G80: =SUMIFS(JU!$H$180:$H$440,JU!$F$180:$F$440,WS!$A80) -> 0 | H80: =SUMIFS(JU!$K$180:$K$440,JU!$I$180:$I$440,WS!$A80) -> 0 | J80: =SUMIFS(JU!$H$441:$H$695,JU!$F$441:$F$695,WS!$A80) -> 0 | K80: =SUMIFS(JU!$K$441:$K$695,JU!$I$441:$I$695,WS!$A80) -> 0 | M80: =SUMIFS(JU!$H$696:$H$1062,JU!$F$696:$F$1062,$A80) -> 0 | N80: =SUMIFS(JU!$K$696:$K$1062,JU!$I$696:$I$1062,WS!$A80) -> 0 | P80: =SUMIFS(JU!$H$1063:$H$5007,JU!$F$1063:$F$5007,WS!$A80) -> 0 | Q80: =SUMIFS(JU!$K$1063:$K$5007,JU!$I$1063:$I$5007,WS!$A80) -> 0 | S80: =SUMIFS(JU!$H$5107:$H$5107,JU!$F$5107:$F$5107,WS!$A80) -> 0 | T80: =SUMIFS(JU!$K$5107:$K$5107,JU!$I$5107:$I$5107,WS!$A80) -> 0 | V80: =SUMIFS(JU!$H$5107:$H$5107,JU!$F$5107:$F$5107,WS!$A80) -> 0 | W80: =SUMIFS(JU!$K$5107:$K$5107,JU!$I$5107:$I$5107,WS!$A80) -> 0 | Y80: =SUMIFS(JU!$H$5107:$H$5107,JU!$F$5107:$F$5107,WS!$A80) -> 0 | Z80: =SUMIFS(JU!$K$5107:$K$5107,JU!$I$5107:$I$5107,WS!$A80) -> 0 | AB80: =SUMIFS(JU!$H$5107:$H$5107,JU!$F$5107:$F$5107,WS!$A80) -> 0 | AC80: =SUMIFS(JU!$K$5107:$K$5107,JU!$I$5107:$I$5107,WS!$A80) -> 0 | AE80: =SUMIFS(JU!$H$5107:$H$5107,JU!$F$5107:$F$5107,WS!$A80) -> 0 | AF80: =SUMIFS(JU!$K$5107:$K$5107,JU!$I$5107:$I$5107,WS!$A80) -> 0 | AH80: =SUMIFS(JU!$H$5107:$H$5107,JU!$F$5107:$F$5107,WS!$A80) -> 0 | AI80: =SUMIFS(JU!$K$5107:$K$5107,JU!$I$5107:$I$5107,WS!$A80) -> 0 | AK80: =SUMIFS(JU!$H$5107:$H$5107,JU!$F$5107:$F$5107,WS!$A80) -> 0 | AL80: =SUMIFS(JU!$K$5107:$K$5107,JU!$I$5107:$I$5107,WS!$A80) -> 0
A81: 4101 | B81: Pendapatan Penjualan Tanah | D81: =SUMIFS(JU!$H$5:$H$178,JU!$F$5:$F$178,WS!$A81) -> 0 | E81: =SUMIFS(JU!$K$5:$K$178,JU!$I$5:$I$178,WS!$A81) -> 85000000 | F81: =E81-D81 -> 85000000 | G81: =SUMIFS(JU!$H$180:$H$440,JU!$F$180:$F$440,WS!$A81) -> 0 | H81: =SUMIFS(JU!$K$180:$K$440,JU!$I$180:$I$440,WS!$A81) -> 34500000 | I81: =H81-G81 -> 34500000 | J81: =SUMIFS(JU!$H$441:$H$695,JU!$F$441:$F$695,WS!$A81) -> 0 | K81: =SUMIFS(JU!$K$441:$K$695,JU!$I$441:$I$695,WS!$A81) -> 10000000 | L81: =K81-J81 -> 10000000 | M81: =SUMIFS(JU!$H$696:$H$1062,JU!$F$696:$F$1062,$A81) -> 0 | N81: =SUMIFS(JU!$K$696:$K$1062,JU!$I$696:$I$1062,WS!$A81) -> 2000000 | O81: =N81-M81 -> 2000000 | P81: =SUMIFS(JU!$H$1063:$H$5007,JU!$F$1063:$F$5007,WS!$A81) -> 0 | Q81: =SUMIFS(JU!$K$1063:$K$5007,JU!$I$1063:$I$5007,WS!$A81) -> 36000000 | R81: =Q81-P81 -> 36000000 | S81: =SUMIFS(JU!$H$5107:$H$5107,JU!$F$5107:$F$5107,WS!$A81) -> 0 | T81: =SUMIFS(JU!$K$5107:$K$5107,JU!$I$5107:$I$5107,WS!$A81) -> 0 | U81: =T81-S81 -> 0 | V81: =SUMIFS(JU!$H$5107:$H$5107,JU!$F$5107:$F$5107,WS!$A81) -> 0 | W81: =SUMIFS(JU!$K$5107:$K$5107,JU!$I$5107:$I$5107,WS!$A81) -> 0 | X81: =W81-V81 -> 0 | Y81: =SUMIFS(JU!$H$5107:$H$5107,JU!$F$5107:$F$5107,WS!$A81) -> 0 | Z81: =SUMIFS(JU!$K$5107:$K$5107,JU!$I$5107:$I$5107,WS!$A81) -> 0 | AA81: =Z81-Y81 -> 0 | AB81: =SUMIFS(JU!$H$5107:$H$5107,JU!$F$5107:$F$5107,WS!$A81) -> 0 | AC81: =SUMIFS(JU!$K$5107:$K$5107,JU!$I$5107:$I$5107,WS!$A81) -> 0 | AD81: =AC81-AB81 -> 0 | AE81: =SUMIFS(JU!$H$5107:$H$5107,JU!$F$5107:$F$5107,WS!$A81) -> 0 | AF81: =SUMIFS(JU!$K$5107:$K$5107,JU!$I$5107:$I$5107,WS!$A81) -> 0 | AG81: =AF81-AE81 -> 0 | AH81: =SUMIFS(JU!$H$5107:$H$5107,JU!$F$5107:$F$5107,WS!$A81) -> 0 | AI81: =SUMIFS(JU!$K$5107:$K$5107,JU!$I$5107:$I$5107,WS!$A81) -> 0 | AJ81: =AI81-AH81 -> 0 | AK81: =SUMIFS(JU!$H$5107:$H$5107,JU!$F$5107:$F$5107,WS!$A81) -> 0 | AL81: =SUMIFS(JU!$K$5107:$K$5107,JU!$I$5107:$I$5107,WS!$A81) -> 0 | AM81: =AL81-AK81 -> 0 | AN81: =F81+I81+L81+O81+R81+U81+X81+AA81+AD81+AG81+AJ81+AM81 -> 167500000 | AP81: =AG81+AD81+AA81+X81+U81+R81+O81+L81+I81+F81 -> 167500000
A82: 4102 | B82: Pendapatan Penjualan Rumah | D82: =SUMIFS(JU!$H$5:$H$178,JU!$F$5:$F$178,WS!$A82) -> 79000000 | E82: =SUMIFS(JU!$K$5:$K$178,JU!$I$5:$I$178,WS!$A82) -> 113000000 | F82: =E82-D82 -> 34000000 | G82: =SUMIFS(JU!$H$180:$H$440,JU!$F$180:$F$440,WS!$A82) -> 26500000 | H82: =SUMIFS(JU!$K$180:$K$440,JU!$I$180:$I$440,WS!$A82) -> 603000000 | I82: =H82-G82 -> 576500000 | J82: =SUMIFS(JU!$H$441:$H$695,JU!$F$441:$F$695,WS!$A82) -> 35500000 | K82: =SUMIFS(JU!$K$441:$K$695,JU!$I$441:$I$695,WS!$A82) -> 603500000 | L82: =K82-J82 -> 568000000 | M82: =SUMIFS(JU!$H$696:$H$1062,JU!$F$696:$F$1062,$A82) -> 72000000 | N82: =SUMIFS(JU!$K$696:$K$1062,JU!$I$696:$I$1062,WS!$A82) -> 2341900000 | O82: =N82-M82 -> 2269900000 | P82: =SUMIFS(JU!$H$1063:$H$5007,JU!$F$1063:$F$5007,WS!$A82) -> 94500000 | Q82: =SUMIFS(JU!$K$1063:$K$5007,JU!$I$1063:$I$5007,WS!$A82) -> 2931100000 | R82: =Q82-P82 -> 2836600000 | S82: =SUMIFS(JU!$H$5107:$H$5107,JU!$F$5107:$F$5107,WS!$A82) -> 0 | T82: =SUMIFS(JU!$K$5107:$K$5107,JU!$I$5107:$I$5107,WS!$A82) -> 0 | U82: =T82-S82 -> 0 | V82: =SUMIFS(JU!$H$5107:$H$5107,JU!$F$5107:$F$5107,WS!$A82) -> 0 | W82: =SUMIFS(JU!$K$5107:$K$5107,JU!$I$5107:$I$5107,WS!$A82) -> 0 | X82: =W82-V82 -> 0 | Y82: =SUMIFS(JU!$H$5107:$H$5107,JU!$F$5107:$F$5107,WS!$A82) -> 0 | Z82: =SUMIFS(JU!$K$5107:$K$5107,JU!$I$5107:$I$5107,WS!$A82) -> 0 | AA82: =Z82-Y82 -> 0 | AB82: =SUMIFS(JU!$H$5107:$H$5107,JU!$F$5107:$F$5107,WS!$A82) -> 0 | AC82: =SUMIFS(JU!$K$5107:$K$5107,JU!$I$5107:$I$5107,WS!$A82) -> 0 | AD82: =AC82-AB82 -> 0 | AE82: =SUMIFS(JU!$H$5107:$H$5107,JU!$F$5107:$F$5107,WS!$A82) -> 0 | AF82: =SUMIFS(JU!$K$5107:$K$5107,JU!$I$5107:$I$5107,WS!$A82) -> 0 | AG82: =AF82-AE82 -> 0 | AH82: =SUMIFS(JU!$H$5107:$H$5107,JU!$F$5107:$F$5107,WS!$A82) -> 0 | AI82: =SUMIFS(JU!$K$5107:$K$5107,JU!$I$5107:$I$5107,WS!$A82) -> 0 | AJ82: =AI82-AH82 -> 0 | AK82: =SUMIFS(JU!$H$5107:$H$5107,JU!$F$5107:$F$5107,WS!$A82) -> 0 | AL82: =SUMIFS(JU!$K$5107:$K$5107,JU!$I$5107:$I$5107,WS!$A82) -> 0 | AM82: =AL82-AK82 -> 0 | AN82: =F82+I82+L82+O82+R82+U82+X82+AA82+AD82+AG82+AJ82+AM82 -> 6285000000 | AP82: =AG82+AD82+AA82+X82+U82+R82+O82+L82+I82+F82 -> 6285000000
A83: 4103 | B83: Pendapatan Penjualan Ruko/Apartemen | D83: =SUMIFS(JU!$H$5:$H$178,JU!$F$5:$F$178,WS!$A83) -> 0 | E83: =SUMIFS(JU!$K$5:$K$178,JU!$I$5:$I$178,WS!$A83) -> 0 | F83: =E83-D83 -> 0 | G83: =SUMIFS(JU!$H$180:$H$440,JU!$F$180:$F$440,WS!$A83) -> 52600000 | H83: =SUMIFS(JU!$K$180:$K$440,JU!$I$180:$I$440,WS!$A83) -> 235000000 | I83: =H83-G83 -> 182400000 | J83: =SUMIFS(JU!$H$441:$H$695,JU!$F$441:$F$695,WS!$A83) -> 40000000 | K83: =SUMIFS(JU!$K$441:$K$695,JU!$I$441:$I$695,WS!$A83) -> 0 | L83: =K83-J83 -> -40000000 | M83: =SUMIFS(JU!$H$696:$H$1062,JU!$F$696:$F$1062,$A83) -> 0 | N83: =SUMIFS(JU!$K$696:$K$1062,JU!$I$696:$I$1062,WS!$A83) -> 0 | O83: =N83-M83 -> 0 | P83: =SUMIFS(JU!$H$1063:$H$5007,JU!$F$1063:$F$5007,WS!$A83) -> 0 | Q83: =SUMIFS(JU!$K$1063:$K$5007,JU!$I$1063:$I$5007,WS!$A83) -> 285000000 | R83: =Q83-P83 -> 285000000 | S83: =SUMIFS(JU!$H$5107:$H$5107,JU!$F$5107:$F$5107,WS!$A83) -> 0 | T83: =SUMIFS(JU!$K$5107:$K$5107,JU!$I$5107:$I$5107,WS!$A83) -> 0 | U83: =T83-S83 -> 0 | V83: =SUMIFS(JU!$H$5107:$H$5107,JU!$F$5107:$F$5107,WS!$A83) -> 0 | W83: =SUMIFS(JU!$K$5107:$K$5107,JU!$I$5107:$I$5107,WS!$A83) -> 0 | X83: =W83-V83 -> 0 | Y83: =SUMIFS(JU!$H$5107:$H$5107,JU!$F$5107:$F$5107,WS!$A83) -> 0 | Z83: =SUMIFS(JU!$K$5107:$K$5107,JU!$I$5107:$I$5107,WS!$A83) -> 0 | AA83: =Z83-Y83 -> 0 | AB83: =SUMIFS(JU!$H$5107:$H$5107,JU!$F$5107:$F$5107,WS!$A83) -> 0 | AC83: =SUMIFS(JU!$K$5107:$K$5107,JU!$I$5107:$I$5107,WS!$A83) -> 0 | AD83: =AC83-AB83 -> 0 | AE83: =SUMIFS(JU!$H$5107:$H$5107,JU!$F$5107:$F$5107,WS!$A83) -> 0 | AF83: =SUMIFS(JU!$K$5107:$K$5107,JU!$I$5107:$I$5107,WS!$A83) -> 0 | AG83: =AF83-AE83 -> 0 | AH83: =SUMIFS(JU!$H$5107:$H$5107,JU!$F$5107:$F$5107,WS!$A83) -> 0 | AI83: =SUMIFS(JU!$K$5107:$K$5107,JU!$I$5107:$I$5107,WS!$A83) -> 0 | AJ83: =AI83-AH83 -> 0 | AK83: =SUMIFS(JU!$H$5107:$H$5107,JU!$F$5107:$F$5107,WS!$A83) -> 0 | AL83: =SUMIFS(JU!$K$5107:$K$5107,JU!$I$5107:$I$5107,WS!$A83) -> 0 | AM83: =AL83-AK83 -> 0 | AN83: =F83+I83+L83+O83+R83+U83+X83+AA83+AD83+AG83+AJ83+AM83 -> 427400000 | AP83: =AG83+AD83+AA83+X83+U83+R83+O83+L83+I83+F83 -> 427400000
A84: 4104 | B84: Pendapatan Jasa Konstruksi | D84: =SUMIFS(JU!$H$5:$H$178,JU!$F$5:$F$178,WS!$A84) -> 0 | E84: =SUMIFS(JU!$K$5:$K$178,JU!$I$5:$I$178,WS!$A84) -> 0 | F84: =E84-D84 -> 0 | G84: =SUMIFS(JU!$H$180:$H$440,JU!$F$180:$F$440,WS!$A84) -> 0 | H84: =SUMIFS(JU!$K$180:$K$440,JU!$I$180:$I$440,WS!$A84) -> 0 | I84: =H84-G84 -> 0 | J84: =SUMIFS(JU!$H$441:$H$695,JU!$F$441:$F$695,WS!$A84) -> 0 | K84: =SUMIFS(JU!$K$441:$K$695,JU!$I$441:$I$695,WS!$A84) -> 0 | L84: =K84-J84 -> 0 | M84: =SUMIFS(JU!$H$696:$H$1062,JU!$F$696:$F$1062,$A84) -> 0 | N84: =SUMIFS(JU!$K$696:$K$1062,JU!$I$696:$I$1062,WS!$A84) -> 0 | O84: =N84-M84 -> 0 | P84: =SUMIFS(JU!$H$1063:$H$5007,JU!$F$1063:$F$5007,WS!$A84) -> 0 | Q84: =SUMIFS(JU!$K$1063:$K$5007,JU!$I$1063:$I$5007,WS!$A84) -> 0 | R84: =Q84-P84 -> 0 | S84: =SUMIFS(JU!$H$5107:$H$5107,JU!$F$5107:$F$5107,WS!$A84) -> 0 | T84: =SUMIFS(JU!$K$5107:$K$5107,JU!$I$5107:$I$5107,WS!$A84) -> 0 | U84: =T84-S84 -> 0 | V84: =SUMIFS(JU!$H$5107:$H$5107,JU!$F$5107:$F$5107,WS!$A84) -> 0 | W84: =SUMIFS(JU!$K$5107:$K$5107,JU!$I$5107:$I$5107,WS!$A84) -> 0 | X84: =W84-V84 -> 0 | Y84: =SUMIFS(JU!$H$5107:$H$5107,JU!$F$5107:$F$5107,WS!$A84) -> 0 | Z84: =SUMIFS(JU!$K$5107:$K$5107,JU!$I$5107:$I$5107,WS!$A84) -> 0 | AA84: =Z84-Y84 -> 0 | AB84: =SUMIFS(JU!$H$5107:$H$5107,JU!$F$5107:$F$5107,WS!$A84) -> 0 | AC84: =SUMIFS(JU!$K$5107:$K$5107,JU!$I$5107:$I$5107,WS!$A84) -> 0 | AD84: =AC84-AB84 -> 0 | AE84: =SUMIFS(JU!$H$5107:$H$5107,JU!$F$5107:$F$5107,WS!$A84) -> 0 | AF84: =SUMIFS(JU!$K$5107:$K$5107,JU!$I$5107:$I$5107,WS!$A84) -> 0 | AG84: =AF84-AE84 -> 0 | AH84: =SUMIFS(JU!$H$5107:$H$5107,JU!$F$5107:$F$5107,WS!$A84) -> 0 | AI84: =SUMIFS(JU!$K$5107:$K$5107,JU!$I$5107:$I$5107,WS!$A84) -> 0 | AJ84: =AI84-AH84 -> 0 | AK84: =SUMIFS(JU!$H$5107:$H$5107,JU!$F$5107:$F$5107,WS!$A84) -> 0 | AL84: =SUMIFS(JU!$K$5107:$K$5107,JU!$I$5107:$I$5107,WS!$A84) -> 0 | AM84: =AL84-AK84 -> 0 | AN84: =F84+I84+L84+O84+R84+U84+X84+AA84+AD84+AG84+AJ84+AM84 -> 0 | AP84: =AG84+AD84+AA84+X84+U84+R84+O84+L84+I84+F84 -> 0
A85: 4105 | B85: Pendapatan Sewa Properti | D85: =SUMIFS(JU!$H$5:$H$178,JU!$F$5:$F$178,WS!$A85) -> 0 | E85: =SUMIFS(JU!$K$5:$K$178,JU!$I$5:$I$178,WS!$A85) -> 0 | F85: =E85-D85 -> 0 | G85: =SUMIFS(JU!$H$180:$H$440,JU!$F$180:$F$440,WS!$A85) -> 0 | H85: =SUMIFS(JU!$K$180:$K$440,JU!$I$180:$I$440,WS!$A85) -> 0 | I85: =H85-G85 -> 0 | J85: =SUMIFS(JU!$H$441:$H$695,JU!$F$441:$F$695,WS!$A85) -> 0 | K85: =SUMIFS(JU!$K$441:$K$695,JU!$I$441:$I$695,WS!$A85) -> 0 | L85: =K85-J85 -> 0 | M85: =SUMIFS(JU!$H$696:$H$1062,JU!$F$696:$F$1062,$A85) -> 0 | N85: =SUMIFS(JU!$K$696:$K$1062,JU!$I$696:$I$1062,WS!$A85) -> 0 | O85: =N85-M85 -> 0 | P85: =SUMIFS(JU!$H$1063:$H$5007,JU!$F$1063:$F$5007,WS!$A85) -> 0 | Q85: =SUMIFS(JU!$K$1063:$K$5007,JU!$I$1063:$I$5007,WS!$A85) -> 0 | R85: =Q85-P85 -> 0 | S85: =SUMIFS(JU!$H$5107:$H$5107,JU!$F$5107:$F$5107,WS!$A85) -> 0 | T85: =SUMIFS(JU!$K$5107:$K$5107,JU!$I$5107:$I$5107,WS!$A85) -> 0 | U85: =T85-S85 -> 0 | V85: =SUMIFS(JU!$H$5107:$H$5107,JU!$F$5107:$F$5107,WS!$A85) -> 0 | W85: =SUMIFS(JU!$K$5107:$K$5107,JU!$I$5107:$I$5107,WS!$A85) -> 0 | X85: =W85-V85 -> 0 | Y85: =SUMIFS(JU!$H$5107:$H$5107,JU!$F$5107:$F$5107,WS!$A85) -> 0 | Z85: =SUMIFS(JU!$K$5107:$K$5107,JU!$I$5107:$I$5107,WS!$A85) -> 0 | AA85: =Z85-Y85 -> 0 | AB85: =SUMIFS(JU!$H$5107:$H$5107,JU!$F$5107:$F$5107,WS!$A85) -> 0 | AC85: =SUMIFS(JU!$K$5107:$K$5107,JU!$I$5107:$I$5107,WS!$A85) -> 0 | AD85: =AC85-AB85 -> 0 | AE85: =SUMIFS(JU!$H$5107:$H$5107,JU!$F$5107:$F$5107,WS!$A85) -> 0 | AF85: =SUMIFS(JU!$K$5107:$K$5107,JU!$I$5107:$I$5107,WS!$A85) -> 0 | AG85: =AF85-AE85 -> 0 | AH85: =SUMIFS(JU!$H$5107:$H$5107,JU!$F$5107:$F$5107,WS!$A85) -> 0 | AI85: =SUMIFS(JU!$K$5107:$K$5107,JU!$I$5107:$I$5107,WS!$A85) -> 0 | AJ85: =AI85-AH85 -> 0 | AK85: =SUMIFS(JU!$H$5107:$H$5107,JU!$F$5107:$F$5107,WS!$A85) -> 0 | AL85: =SUMIFS(JU!$K$5107:$K$5107,JU!$I$5107:$I$5107,WS!$A85) -> 0 | AM85: =AL85-AK85 -> 0 | AN85: =F85+I85+L85+O85+R85+U85+X85+AA85+AD85+AG85+AJ85+AM85 -> 0 | AP85: =AG85+AD85+AA85+X85+U85+R85+O85+L85+I85+F85 -> 0
A86: 4106 | B86: Pendapatan Penjualan Baju Konveksi | D86: =SUMIFS(JU!$H$5:$H$178,JU!$F$5:$F$178,WS!$A86) -> 0 | E86: =SUMIFS(JU!$K$5:$K$178,JU!$I$5:$I$178,WS!$A86) -> 0 | F86: =E86-D86 -> 0 | G86: =SUMIFS(JU!$H$180:$H$440,JU!$F$180:$F$440,WS!$A86) -> 0 | H86: =SUMIFS(JU!$K$180:$K$440,JU!$I$180:$I$440,WS!$A86) -> 0 | I86: =H86-G86 -> 0 | J86: =SUMIFS(JU!$H$441:$H$695,JU!$F$441:$F$695,WS!$A86) -> 0 | K86: =SUMIFS(JU!$K$441:$K$695,JU!$I$441:$I$695,WS!$A86) -> 0 | L86: =K86-J86 -> 0 | M86: =SUMIFS(JU!$H$696:$H$1062,JU!$F$696:$F$1062,$A86) -> 0 | N86: =SUMIFS(JU!$K$696:$K$1062,JU!$I$696:$I$1062,WS!$A86) -> 0 | O86: =N86-M86 -> 0 | P86: =SUMIFS(JU!$H$1063:$H$5007,JU!$F$1063:$F$5007,WS!$A86) -> 0 | Q86: =SUMIFS(JU!$K$1063:$K$5007,JU!$I$1063:$I$5007,WS!$A86) -> 0 | R86: =Q86-P86 -> 0 | S86: =SUMIFS(JU!$H$5107:$H$5107,JU!$F$5107:$F$5107,WS!$A86) -> 0 | T86: =SUMIFS(JU!$K$5107:$K$5107,JU!$I$5107:$I$5107,WS!$A86) -> 0 | U86: =T86-S86 -> 0 | V86: =SUMIFS(JU!$H$5107:$H$5107,JU!$F$5107:$F$5107,WS!$A86) -> 0 | W86: =SUMIFS(JU!$K$5107:$K$5107,JU!$I$5107:$I$5107,WS!$A86) -> 0 | X86: =W86-V86 -> 0 | Y86: =SUMIFS(JU!$H$5107:$H$5107,JU!$F$5107:$F$5107,WS!$A86) -> 0 | Z86: =SUMIFS(JU!$K$5107:$K$5107,JU!$I$5107:$I$5107,WS!$A86) -> 0 | AA86: =Z86-Y86 -> 0 | AB86: =SUMIFS(JU!$H$5107:$H$5107,JU!$F$5107:$F$5107,WS!$A86) -> 0 | AC86: =SUMIFS(JU!$K$5107:$K$5107,JU!$I$5107:$I$5107,WS!$A86) -> 0 | AD86: =AC86-AB86 -> 0 | AE86: =SUMIFS(JU!$H$5107:$H$5107,JU!$F$5107:$F$5107,WS!$A86) -> 0 | AF86: =SUMIFS(JU!$K$5107:$K$5107,JU!$I$5107:$I$5107,WS!$A86) -> 0 | AG86: =AF86-AE86 -> 0 | AH86: =SUMIFS(JU!$H$5107:$H$5107,JU!$F$5107:$F$5107,WS!$A86) -> 0 | AI86: =SUMIFS(JU!$K$5107:$K$5107,JU!$I$5107:$I$5107,WS!$A86) -> 0 | AJ86: =AI86-AH86 -> 0 | AK86: =SUMIFS(JU!$H$5107:$H$5107,JU!$F$5107:$F$5107,WS!$A86) -> 0 | AL86: =SUMIFS(JU!$K$5107:$K$5107,JU!$I$5107:$I$5107,WS!$A86) -> 0 | AM86: =AL86-AK86 -> 0 | AN86: =F86+I86+L86+O86+R86+U86+X86+AA86+AD86+AG86+AJ86+AM86 -> 0 | AP86: =AG86+AD86+AA86+X86+U86+R86+O86+L86+I86+F86 -> 0
A87: 4107 | B87: Pendapatan Penjualan atas Pemesanan Custom | D87: =SUMIFS(JU!$H$5:$H$178,JU!$F$5:$F$178,WS!$A87) -> 0 | E87: =SUMIFS(JU!$K$5:$K$178,JU!$I$5:$I$178,WS!$A87) -> 0 | F87: =E87-D87 -> 0 | G87: =SUMIFS(JU!$H$180:$H$440,JU!$F$180:$F$440,WS!$A87) -> 0 | H87: =SUMIFS(JU!$K$180:$K$440,JU!$I$180:$I$440,WS!$A87) -> 0 | I87: =H87-G87 -> 0 | J87: =SUMIFS(JU!$H$441:$H$695,JU!$F$441:$F$695,WS!$A87) -> 0 | K87: =SUMIFS(JU!$K$441:$K$695,JU!$I$441:$I$695,WS!$A87) -> 0 | L87: =K87-J87 -> 0 | M87: =SUMIFS(JU!$H$696:$H$1062,JU!$F$696:$F$1062,$A87) -> 0 | N87: =SUMIFS(JU!$K$696:$K$1062,JU!$I$696:$I$1062,WS!$A87) -> 0 | O87: =N87-M87 -> 0 | P87: =SUMIFS(JU!$H$1063:$H$5007,JU!$F$1063:$F$5007,WS!$A87) -> 0 | Q87: =SUMIFS(JU!$K$1063:$K$5007,JU!$I$1063:$I$5007,WS!$A87) -> 0 | R87: =Q87-P87 -> 0 | S87: =SUMIFS(JU!$H$5107:$H$5107,JU!$F$5107:$F$5107,WS!$A87) -> 0 | T87: =SUMIFS(JU!$K$5107:$K$5107,JU!$I$5107:$I$5107,WS!$A87) -> 0 | U87: =T87-S87 -> 0 | V87: =SUMIFS(JU!$H$5107:$H$5107,JU!$F$5107:$F$5107,WS!$A87) -> 0 | W87: =SUMIFS(JU!$K$5107:$K$5107,JU!$I$5107:$I$5107,WS!$A87) -> 0 | X87: =W87-V87 -> 0 | Y87: =SUMIFS(JU!$H$5107:$H$5107,JU!$F$5107:$F$5107,WS!$A87) -> 0 | Z87: =SUMIFS(JU!$K$5107:$K$5107,JU!$I$5107:$I$5107,WS!$A87) -> 0 | AA87: =Z87-Y87 -> 0 | AB87: =SUMIFS(JU!$H$5107:$H$5107,JU!$F$5107:$F$5107,WS!$A87) -> 0 | AC87: =SUMIFS(JU!$K$5107:$K$5107,JU!$I$5107:$I$5107,WS!$A87) -> 0 | AD87: =AC87-AB87 -> 0 | AE87: =SUMIFS(JU!$H$5107:$H$5107,JU!$F$5107:$F$5107,WS!$A87) -> 0 | AF87: =SUMIFS(JU!$K$5107:$K$5107,JU!$I$5107:$I$5107,WS!$A87) -> 0 | AG87: =AF87-AE87 -> 0 | AH87: =SUMIFS(JU!$H$5107:$H$5107,JU!$F$5107:$F$5107,WS!$A87) -> 0 | AI87: =SUMIFS(JU!$K$5107:$K$5107,JU!$I$5107:$I$5107,WS!$A87) -> 0 | AJ87: =AI87-AH87 -> 0 | AK87: =SUMIFS(JU!$H$5107:$H$5107,JU!$F$5107:$F$5107,WS!$A87) -> 0 | AL87: =SUMIFS(JU!$K$5107:$K$5107,JU!$I$5107:$I$5107,WS!$A87) -> 0 | AM87: =AL87-AK87 -> 0 | AN87: =F87+I87+L87+O87+R87+U87+X87+AA87+AD87+AG87+AJ87+AM87 -> 0 | AP87: =AG87+AD87+AA87+X87+U87+R87+O87+L87+I87+F87 -> 0
A88: 4108 | B88: Pendapatan Jasa Percetakan | D88: =SUMIFS(JU!$H$5:$H$178,JU!$F$5:$F$178,WS!$A88) -> 0 | E88: =SUMIFS(JU!$K$5:$K$178,JU!$I$5:$I$178,WS!$A88) -> 0 | F88: =E88-D88 -> 0 | G88: =SUMIFS(JU!$H$180:$H$440,JU!$F$180:$F$440,WS!$A88) -> 0 | H88: =SUMIFS(JU!$K$180:$K$440,JU!$I$180:$I$440,WS!$A88) -> 0 | I88: =H88-G88 -> 0 | J88: =SUMIFS(JU!$H$441:$H$695,JU!$F$441:$F$695,WS!$A88) -> 0 | K88: =SUMIFS(JU!$K$441:$K$695,JU!$I$441:$I$695,WS!$A88) -> 0 | L88: =K88-J88 -> 0 | M88: =SUMIFS(JU!$H$696:$H$1062,JU!$F$696:$F$1062,$A88) -> 0 | N88: =SUMIFS(JU!$K$696:$K$1062,JU!$I$696:$I$1062,WS!$A88) -> 0 | O88: =N88-M88 -> 0 | P88: =SUMIFS(JU!$H$1063:$H$5007,JU!$F$1063:$F$5007,WS!$A88) -> 0 | Q88: =SUMIFS(JU!$K$1063:$K$5007,JU!$I$1063:$I$5007,WS!$A88) -> 0 | R88: =Q88-P88 -> 0 | S88: =SUMIFS(JU!$H$5107:$H$5107,JU!$F$5107:$F$5107,WS!$A88) -> 0 | T88: =SUMIFS(JU!$K$5107:$K$5107,JU!$I$5107:$I$5107,WS!$A88) -> 0 | U88: =T88-S88 -> 0 | V88: =SUMIFS(JU!$H$5107:$H$5107,JU!$F$5107:$F$5107,WS!$A88) -> 0 | W88: =SUMIFS(JU!$K$5107:$K$5107,JU!$I$5107:$I$5107,WS!$A88) -> 0 | X88: =W88-V88 -> 0 | Y88: =SUMIFS(JU!$H$5107:$H$5107,JU!$F$5107:$F$5107,WS!$A88) -> 0 | Z88: =SUMIFS(JU!$K$5107:$K$5107,JU!$I$5107:$I$5107,WS!$A88) -> 0 | AA88: =Z88-Y88 -> 0 | AB88: =SUMIFS(JU!$H$5107:$H$5107,JU!$F$5107:$F$5107,WS!$A88) -> 0 | AC88: =SUMIFS(JU!$K$5107:$K$5107,JU!$I$5107:$I$5107,WS!$A88) -> 0 | AD88: =AC88-AB88 -> 0 | AE88: =SUMIFS(JU!$H$5107:$H$5107,JU!$F$5107:$F$5107,WS!$A88) -> 0 | AF88: =SUMIFS(JU!$K$5107:$K$5107,JU!$I$5107:$I$5107,WS!$A88) -> 0 | AG88: =AF88-AE88 -> 0 | AH88: =SUMIFS(JU!$H$5107:$H$5107,JU!$F$5107:$F$5107,WS!$A88) -> 0 | AI88: =SUMIFS(JU!$K$5107:$K$5107,JU!$I$5107:$I$5107,WS!$A88) -> 0 | AJ88: =AI88-AH88 -> 0 | AK88: =SUMIFS(JU!$H$5107:$H$5107,JU!$F$5107:$F$5107,WS!$A88) -> 0 | AL88: =SUMIFS(JU!$K$5107:$K$5107,JU!$I$5107:$I$5107,WS!$A88) -> 0 | AM88: =AL88-AK88 -> 0 | AN88: =F88+I88+L88+O88+R88+U88+X88+AA88+AD88+AG88+AJ88+AM88 -> 0 | AP88: =AG88+AD88+AA88+X88+U88+R88+O88+L88+I88+F88 -> 0
A89: 4109 | B89: Pendapatan Jasa Konveksi | D89: =SUMIFS(JU!$H$5:$H$178,JU!$F$5:$F$178,WS!$A89) -> 0 | E89: =SUMIFS(JU!$K$5:$K$178,JU!$I$5:$I$178,WS!$A89) -> 0 | F89: =E89-D89 -> 0 | G89: =SUMIFS(JU!$H$180:$H$440,JU!$F$180:$F$440,WS!$A89) -> 0 | H89: =SUMIFS(JU!$K$180:$K$440,JU!$I$180:$I$440,WS!$A89) -> 0 | I89: =H89-G89 -> 0 | J89: =SUMIFS(JU!$H$441:$H$695,JU!$F$441:$F$695,WS!$A89) -> 0 | K89: =SUMIFS(JU!$K$441:$K$695,JU!$I$441:$I$695,WS!$A89) -> 0 | L89: =K89-J89 -> 0 | M89: =SUMIFS(JU!$H$696:$H$1062,JU!$F$696:$F$1062,$A89) -> 0 | N89: =SUMIFS(JU!$K$696:$K$1062,JU!$I$696:$I$1062,WS!$A89) -> 0 | O89: =N89-M89 -> 0 | P89: =SUMIFS(JU!$H$1063:$H$5007,JU!$F$1063:$F$5007,WS!$A89) -> 0 | Q89: =SUMIFS(JU!$K$1063:$K$5007,JU!$I$1063:$I$5007,WS!$A89) -> 0 | R89: =Q89-P89 -> 0 | S89: =SUMIFS(JU!$H$5107:$H$5107,JU!$F$5107:$F$5107,WS!$A89) -> 0 | T89: =SUMIFS(JU!$K$5107:$K$5107,JU!$I$5107:$I$5107,WS!$A89) -> 0 | U89: =T89-S89 -> 0 | V89: =SUMIFS(JU!$H$5107:$H$5107,JU!$F$5107:$F$5107,WS!$A89) -> 0 | W89: =SUMIFS(JU!$K$5107:$K$5107,JU!$I$5107:$I$5107,WS!$A89) -> 0 | X89: =W89-V89 -> 0 | Y89: =SUMIFS(JU!$H$5107:$H$5107,JU!$F$5107:$F$5107,WS!$A89) -> 0 | Z89: =SUMIFS(JU!$K$5107:$K$5107,JU!$I$5107:$I$5107,WS!$A89) -> 0 | AA89: =Z89-Y89 -> 0 | AB89: =SUMIFS(JU!$H$5107:$H$5107,JU!$F$5107:$F$5107,WS!$A89) -> 0 | AC89: =SUMIFS(JU!$K$5107:$K$5107,JU!$I$5107:$I$5107,WS!$A89) -> 0 | AD89: =AC89-AB89 -> 0 | AE89: =SUMIFS(JU!$H$5107:$H$5107,JU!$F$5107:$F$5107,WS!$A89) -> 0 | AF89: =SUMIFS(JU!$K$5107:$K$5107,JU!$I$5107:$I$5107,WS!$A89) -> 0 | AG89: =AF89-AE89 -> 0 | AH89: =SUMIFS(JU!$H$5107:$H$5107,JU!$F$5107:$F$5107,WS!$A89) -> 0 | AI89: =SUMIFS(JU!$K$5107:$K$5107,JU!$I$5107:$I$5107,WS!$A89) -> 0 | AJ89: =AI89-AH89 -> 0 | AK89: =SUMIFS(JU!$H$5107:$H$5107,JU!$F$5107:$F$5107,WS!$A89) -> 0 | AL89: =SUMIFS(JU!$K$5107:$K$5107,JU!$I$5107:$I$5107,WS!$A89) -> 0 | AM89: =AL89-AK89 -> 0 | AN89: =F89+I89+L89+O89+R89+U89+X89+AA89+AD89+AG89+AJ89+AM89 -> 0 | AP89: =AG89+AD89+AA89+X89+U89+R89+O89+L89+I89+F89 -> 0
A90: 4110 | B90: Pendapatan Penjualan Baju Brand | D90: =SUMIFS(JU!$H$5:$H$178,JU!$F$5:$F$178,WS!$A90) -> 0 | E90: =SUMIFS(JU!$K$5:$K$178,JU!$I$5:$I$178,WS!$A90) -> 0 | F90: =E90-D90 -> 0 | G90: =SUMIFS(JU!$H$180:$H$440,JU!$F$180:$F$440,WS!$A90) -> 0 | H90: =SUMIFS(JU!$K$180:$K$440,JU!$I$180:$I$440,WS!$A90) -> 0 | I90: =H90-G90 -> 0 | J90: =SUMIFS(JU!$H$441:$H$695,JU!$F$441:$F$695,WS!$A90) -> 0 | K90: =SUMIFS(JU!$K$441:$K$695,JU!$I$441:$I$695,WS!$A90) -> 0 | L90: =K90-J90 -> 0 | M90: =SUMIFS(JU!$H$696:$H$1062,JU!$F$696:$F$1062,$A90) -> 0 | N90: =SUMIFS(JU!$K$696:$K$1062,JU!$I$696:$I$1062,WS!$A90) -> 0 | O90: =N90-M90 -> 0 | P90: =SUMIFS(JU!$H$1063:$H$5007,JU!$F$1063:$F$5007,WS!$A90) -> 0 | Q90: =SUMIFS(JU!$K$1063:$K$5007,JU!$I$1063:$I$5007,WS!$A90) -> 0 | R90: =Q90-P90 -> 0 | S90: =SUMIFS(JU!$H$5107:$H$5107,JU!$F$5107:$F$5107,WS!$A90) -> 0 | T90: =SUMIFS(JU!$K$5107:$K$5107,JU!$I$5107:$I$5107,WS!$A90) -> 0 | U90: =T90-S90 -> 0 | V90: =SUMIFS(JU!$H$5107:$H$5107,JU!$F$5107:$F$5107,WS!$A90) -> 0 | W90: =SUMIFS(JU!$K$5107:$K$5107,JU!$I$5107:$I$5107,WS!$A90) -> 0 | X90: =W90-V90 -> 0 | Y90: =SUMIFS(JU!$H$5107:$H$5107,JU!$F$5107:$F$5107,WS!$A90) -> 0 | Z90: =SUMIFS(JU!$K$5107:$K$5107,JU!$I$5107:$I$5107,WS!$A90) -> 0 | AA90: =Z90-Y90 -> 0 | AB90: =SUMIFS(JU!$H$5107:$H$5107,JU!$F$5107:$F$5107,WS!$A90) -> 0 | AC90: =SUMIFS(JU!$K$5107:$K$5107,JU!$I$5107:$I$5107,WS!$A90) -> 0 | AD90: =AC90-AB90 -> 0 | AE90: =SUMIFS(JU!$H$5107:$H$5107,JU!$F$5107:$F$5107,WS!$A90) -> 0 | AF90: =SUMIFS(JU!$K$5107:$K$5107,JU!$I$5107:$I$5107,WS!$A90) -> 0 | AG90: =AF90-AE90 -> 0 | AH90: =SUMIFS(JU!$H$5107:$H$5107,JU!$F$5107:$F$5107,WS!$A90) -> 0 | AI90: =SUMIFS(JU!$K$5107:$K$5107,JU!$I$5107:$I$5107,WS!$A90) -> 0 | AJ90: =AI90-AH90 -> 0 | AK90: =SUMIFS(JU!$H$5107:$H$5107,JU!$F$5107:$F$5107,WS!$A90) -> 0 | AL90: =SUMIFS(JU!$K$5107:$K$5107,JU!$I$5107:$I$5107,WS!$A90) -> 0 | AM90: =AL90-AK90 -> 0 | AN90: =F90+I90+L90+O90+R90+U90+X90+AA90+AD90+AG90+AJ90+AM90 -> 0 | AP90: =AG90+AD90+AA90+X90+U90+R90+O90+L90+I90+F90 -> 0
A91: Total Pendapatan Penjualan | C91: =SUM(C81:C90) -> 0 | D91: =SUMIFS(JU!$H$5:$H$178,JU!$F$5:$F$178,WS!$A91) -> 0 | E91: =SUMIFS(JU!$K$5:$K$178,JU!$I$5:$I$178,WS!$A91) -> 0 | F91: =SUM(F81:F90) -> 119000000 | G91: =SUMIFS(JU!$H$180:$H$440,JU!$F$180:$F$440,WS!$A91) -> 0 | H91: =SUMIFS(JU!$K$180:$K$440,JU!$I$180:$I$440,WS!$A91) -> 0 | I91: =SUM(I81:I90) -> 793400000 | J91: =SUMIFS(JU!$H$441:$H$695,JU!$F$441:$F$695,WS!$A91) -> 0 | K91: =SUMIFS(JU!$K$441:$K$695,JU!$I$441:$I$695,WS!$A91) -> 0 | L91: =SUM(L81:L90) -> 538000000 | M91: =SUMIFS(JU!$H$696:$H$1062,JU!$F$696:$F$1062,$A91) -> 0 | N91: =SUMIFS(JU!$K$696:$K$1062,JU!$I$696:$I$1062,WS!$A91) -> 0 | O91: =SUM(O81:O90) -> 2271900000 | P91: =SUMIFS(JU!$H$1063:$H$5007,JU!$F$1063:$F$5007,WS!$A91) -> 0 | Q91: =SUMIFS(JU!$K$1063:$K$5007,JU!$I$1063:$I$5007,WS!$A91) -> 0 | R91: =SUM(R81:R90) -> 3157600000 | S91: =SUMIFS(JU!$H$5107:$H$5107,JU!$F$5107:$F$5107,WS!$A91) -> 0 | T91: =SUMIFS(JU!$K$5107:$K$5107,JU!$I$5107:$I$5107,WS!$A91) -> 0 | U91: =SUM(U81:U90) -> 0 | V91: =SUMIFS(JU!$H$5107:$H$5107,JU!$F$5107:$F$5107,WS!$A91) -> 0 | W91: =SUMIFS(JU!$K$5107:$K$5107,JU!$I$5107:$I$5107,WS!$A91) -> 0 | X91: =SUM(X81:X90) -> 0 | Y91: =SUMIFS(JU!$H$5107:$H$5107,JU!$F$5107:$F$5107,WS!$A91) -> 0 | Z91: =SUMIFS(JU!$K$5107:$K$5107,JU!$I$5107:$I$5107,WS!$A91) -> 0 | AA91: =SUM(AA81:AA90) -> 0 | AB91: =SUMIFS(JU!$H$5107:$H$5107,JU!$F$5107:$F$5107,WS!$A91) -> 0 | AC91: =SUMIFS(JU!$K$5107:$K$5107,JU!$I$5107:$I$5107,WS!$A91) -> 0 | AD91: =SUM(AD81:AD90) -> 0 | AE91: =SUMIFS(JU!$H$5107:$H$5107,JU!$F$5107:$F$5107,WS!$A91) -> 0 | AF91: =SUMIFS(JU!$K$5107:$K$5107,JU!$I$5107:$I$5107,WS!$A91) -> 0 | AG91: =SUM(AG81:AG90) -> 0 | AH91: =SUMIFS(JU!$H$5107:$H$5107,JU!$F$5107:$F$5107,WS!$A91) -> 0 | AI91: =SUMIFS(JU!$K$5107:$K$5107,JU!$I$5107:$I$5107,WS!$A91) -> 0 | AJ91: =SUM(AJ81:AJ90) -> 0 | AK91: =SUMIFS(JU!$H$5107:$H$5107,JU!$F$5107:$F$5107,WS!$A91) -> 0 | AL91: =SUMIFS(JU!$K$5107:$K$5107,JU!$I$5107:$I$5107,WS!$A91) -> 0 | AM91: =SUM(AM81:AM90) -> 0 | AN91: =F91+I91+L91+O91+R91+U91+X91+AA91+AD91+AG91+AJ91+AM91 -> 6879900000 | AP91: =AG91+AD91+AA91+X91+U91+R91+O91+L91+I91+F91 -> 6879900000
A92: Pendapatan Lain-Lain | D92: =SUMIFS(JU!$H$5:$H$178,JU!$F$5:$F$178,WS!$A92) -> 0 | E92: =SUMIFS(JU!$K$5:$K$178,JU!$I$5:$I$178,WS!$A92) -> 0 | G92: =SUMIFS(JU!$H$180:$H$440,JU!$F$180:$F$440,WS!$A92) -> 0 | H92: =SUMIFS(JU!$K$180:$K$440,JU!$I$180:$I$440,WS!$A92) -> 0 | J92: =SUMIFS(JU!$H$441:$H$695,JU!$F$441:$F$695,WS!$A92) -> 0 | K92: =SUMIFS(JU!$K$441:$K$695,JU!$I$441:$I$695,WS!$A92) -> 0 | M92: =SUMIFS(JU!$H$696:$H$1062,JU!$F$696:$F$1062,$A92) -> 0 | N92: =SUMIFS(JU!$K$696:$K$1062,JU!$I$696:$I$1062,WS!$A92) -> 0 | P92: =SUMIFS(JU!$H$1063:$H$5007,JU!$F$1063:$F$5007,WS!$A92) -> 0 | Q92: =SUMIFS(JU!$K$1063:$K$5007,JU!$I$1063:$I$5007,WS!$A92) -> 0 | S92: =SUMIFS(JU!$H$5107:$H$5107,JU!$F$5107:$F$5107,WS!$A92) -> 0 | T92: =SUMIFS(JU!$K$5107:$K$5107,JU!$I$5107:$I$5107,WS!$A92) -> 0 | V92: =SUMIFS(JU!$H$5107:$H$5107,JU!$F$5107:$F$5107,WS!$A92) -> 0 | W92: =SUMIFS(JU!$K$5107:$K$5107,JU!$I$5107:$I$5107,WS!$A92) -> 0 | Y92: =SUMIFS(JU!$H$5107:$H$5107,JU!$F$5107:$F$5107,WS!$A92) -> 0 | Z92: =SUMIFS(JU!$K$5107:$K$5107,JU!$I$5107:$I$5107,WS!$A92) -> 0 | AB92: =SUMIFS(JU!$H$5107:$H$5107,JU!$F$5107:$F$5107,WS!$A92) -> 0 | AC92: =SUMIFS(JU!$K$5107:$K$5107,JU!$I$5107:$I$5107,WS!$A92) -> 0 | AE92: =SUMIFS(JU!$H$5107:$H$5107,JU!$F$5107:$F$5107,WS!$A92) -> 0 | AF92: =SUMIFS(JU!$K$5107:$K$5107,JU!$I$5107:$I$5107,WS!$A92) -> 0 | AH92: =SUMIFS(JU!$H$5107:$H$5107,JU!$F$5107:$F$5107,WS!$A92) -> 0 | AI92: =SUMIFS(JU!$K$5107:$K$5107,JU!$I$5107:$I$5107,WS!$A92) -> 0 | AK92: =SUMIFS(JU!$H$5107:$H$5107,JU!$F$5107:$F$5107,WS!$A92) -> 0 | AL92: =SUMIFS(JU!$K$5107:$K$5107,JU!$I$5107:$I$5107,WS!$A92) -> 0 | AN92: =F92+I92+L92+O92+R92+U92+X92+AA92+AD92+AG92+AJ92+AM92 -> 0 | AP92: =AG92+AD92+AA92+X92+U92+R92+O92+L92+I92+F92 -> 0
A93: 4201 | B93: Pendapatan Administrasi | D93: =SUMIFS(JU!$H$5:$H$178,JU!$F$5:$F$178,WS!$A93) -> 0 | E93: =SUMIFS(JU!$K$5:$K$178,JU!$I$5:$I$178,WS!$A93) -> 0 | F93: =E93-D93 -> 0 | G93: =SUMIFS(JU!$H$180:$H$440,JU!$F$180:$F$440,WS!$A93) -> 0 | H93: =SUMIFS(JU!$K$180:$K$440,JU!$I$180:$I$440,WS!$A93) -> 0 | I93: =H93-G93 -> 0 | J93: =SUMIFS(JU!$H$441:$H$695,JU!$F$441:$F$695,WS!$A93) -> 0 | K93: =SUMIFS(JU!$K$441:$K$695,JU!$I$441:$I$695,WS!$A93) -> 0 | L93: =K93-J93 -> 0 | M93: =SUMIFS(JU!$H$696:$H$1062,JU!$F$696:$F$1062,$A93) -> 0 | N93: =SUMIFS(JU!$K$696:$K$1062,JU!$I$696:$I$1062,WS!$A93) -> 0 | O93: =N93-M93 -> 0 | P93: =SUMIFS(JU!$H$1063:$H$5007,JU!$F$1063:$F$5007,WS!$A93) -> 0 | Q93: =SUMIFS(JU!$K$1063:$K$5007,JU!$I$1063:$I$5007,WS!$A93) -> 0 | R93: =Q93-P93 -> 0 | S93: =SUMIFS(JU!$H$5107:$H$5107,JU!$F$5107:$F$5107,WS!$A93) -> 0 | T93: =SUMIFS(JU!$K$5107:$K$5107,JU!$I$5107:$I$5107,WS!$A93) -> 0 | U93: =T93-S93 -> 0 | V93: =SUMIFS(JU!$H$5107:$H$5107,JU!$F$5107:$F$5107,WS!$A93) -> 0 | W93: =SUMIFS(JU!$K$5107:$K$5107,JU!$I$5107:$I$5107,WS!$A93) -> 0 | X93: =W93-V93 -> 0 | Y93: =SUMIFS(JU!$H$5107:$H$5107,JU!$F$5107:$F$5107,WS!$A93) -> 0 | Z93: =SUMIFS(JU!$K$5107:$K$5107,JU!$I$5107:$I$5107,WS!$A93) -> 0 | AA93: =Z93-Y93 -> 0 | AB93: =SUMIFS(JU!$H$5107:$H$5107,JU!$F$5107:$F$5107,WS!$A93) -> 0 | AC93: =SUMIFS(JU!$K$5107:$K$5107,JU!$I$5107:$I$5107,WS!$A93) -> 0 | AD93: =AC93-AB93 -> 0 | AE93: =SUMIFS(JU!$H$5107:$H$5107,JU!$F$5107:$F$5107,WS!$A93) -> 0 | AF93: =SUMIFS(JU!$K$5107:$K$5107,JU!$I$5107:$I$5107,WS!$A93) -> 0 | AG93: =AF93-AE93 -> 0 | AH93: =SUMIFS(JU!$H$5107:$H$5107,JU!$F$5107:$F$5107,WS!$A93) -> 0 | AI93: =SUMIFS(JU!$K$5107:$K$5107,JU!$I$5107:$I$5107,WS!$A93) -> 0 | AJ93: =AI93-AH93 -> 0 | AK93: =SUMIFS(JU!$H$5107:$H$5107,JU!$F$5107:$F$5107,WS!$A93) -> 0 | AL93: =SUMIFS(JU!$K$5107:$K$5107,JU!$I$5107:$I$5107,WS!$A93) -> 0 | AM93: =AL93-AK93 -> 0 | AN93: =F93+I93+L93+O93+R93+U93+X93+AA93+AD93+AG93+AJ93+AM93 -> 0 | AP93: =AG93+AD93+AA93+X93+U93+R93+O93+L93+I93+F93 -> 0
A94: 4202 | B94: Pendapatan Bunga | D94: =SUMIFS(JU!$H$5:$H$178,JU!$F$5:$F$178,WS!$A94) -> 0 | E94: =SUMIFS(JU!$K$5:$K$178,JU!$I$5:$I$178,WS!$A94) -> 0 | F94: =E94-D94 -> 0 | G94: =SUMIFS(JU!$H$180:$H$440,JU!$F$180:$F$440,WS!$A94) -> 0 | H94: =SUMIFS(JU!$K$180:$K$440,JU!$I$180:$I$440,WS!$A94) -> 293644 | I94: =H94-G94 -> 293644 | J94: =SUMIFS(JU!$H$441:$H$695,JU!$F$441:$F$695,WS!$A94) -> 0 | K94: =SUMIFS(JU!$K$441:$K$695,JU!$I$441:$I$695,WS!$A94) -> 0 | L94: =K94-J94 -> 0 | M94: =SUMIFS(JU!$H$696:$H$1062,JU!$F$696:$F$1062,$A94) -> 0 | N94: =SUMIFS(JU!$K$696:$K$1062,JU!$I$696:$I$1062,WS!$A94) -> 0 | O94: =N94-M94 -> 0 | P94: =SUMIFS(JU!$H$1063:$H$5007,JU!$F$1063:$F$5007,WS!$A94) -> 0 | Q94: =SUMIFS(JU!$K$1063:$K$5007,JU!$I$1063:$I$5007,WS!$A94) -> 0 | R94: =Q94-P94 -> 0 | S94: =SUMIFS(JU!$H$5107:$H$5107,JU!$F$5107:$F$5107,WS!$A94) -> 0 | T94: =SUMIFS(JU!$K$5107:$K$5107,JU!$I$5107:$I$5107,WS!$A94) -> 0 | U94: =T94-S94 -> 0 | V94: =SUMIFS(JU!$H$5107:$H$5107,JU!$F$5107:$F$5107,WS!$A94) -> 0 | W94: =SUMIFS(JU!$K$5107:$K$5107,JU!$I$5107:$I$5107,WS!$A94) -> 0 | X94: =W94-V94 -> 0 | Y94: =SUMIFS(JU!$H$5107:$H$5107,JU!$F$5107:$F$5107,WS!$A94) -> 0 | Z94: =SUMIFS(JU!$K$5107:$K$5107,JU!$I$5107:$I$5107,WS!$A94) -> 0 | AA94: =Z94-Y94 -> 0 | AB94: =SUMIFS(JU!$H$5107:$H$5107,JU!$F$5107:$F$5107,WS!$A94) -> 0 | AC94: =SUMIFS(JU!$K$5107:$K$5107,JU!$I$5107:$I$5107,WS!$A94) -> 0 | AD94: =AC94-AB94 -> 0 | AE94: =SUMIFS(JU!$H$5107:$H$5107,JU!$F$5107:$F$5107,WS!$A94) -> 0 | AF94: =SUMIFS(JU!$K$5107:$K$5107,JU!$I$5107:$I$5107,WS!$A94) -> 0 | AG94: =AF94-AE94 -> 0 | AH94: =SUMIFS(JU!$H$5107:$H$5107,JU!$F$5107:$F$5107,WS!$A94) -> 0 | AI94: =SUMIFS(JU!$K$5107:$K$5107,JU!$I$5107:$I$5107,WS!$A94) -> 0 | AJ94: =AI94-AH94 -> 0 | AK94: =SUMIFS(JU!$H$5107:$H$5107,JU!$F$5107:$F$5107,WS!$A94) -> 0 | AL94: =SUMIFS(JU!$K$5107:$K$5107,JU!$I$5107:$I$5107,WS!$A94) -> 0 | AM94: =AL94-AK94 -> 0 | AN94: =F94+I94+L94+O94+R94+U94+X94+AA94+AD94+AG94+AJ94+AM94 -> 293644 | AP94: =AG94+AD94+AA94+X94+U94+R94+O94+L94+I94+F94 -> 293644
A95: 4203 | B95: Keuntungan Penjualan Aset | D95: =SUMIFS(JU!$H$5:$H$178,JU!$F$5:$F$178,WS!$A95) -> 0 | E95: =SUMIFS(JU!$K$5:$K$178,JU!$I$5:$I$178,WS!$A95) -> 0 | F95: =E95-D95 -> 0 | G95: =SUMIFS(JU!$H$180:$H$440,JU!$F$180:$F$440,WS!$A95) -> 0 | H95: =SUMIFS(JU!$K$180:$K$440,JU!$I$180:$I$440,WS!$A95) -> 0 | I95: =H95-G95 -> 0 | J95: =SUMIFS(JU!$H$441:$H$695,JU!$F$441:$F$695,WS!$A95) -> 0 | K95: =SUMIFS(JU!$K$441:$K$695,JU!$I$441:$I$695,WS!$A95) -> 0 | L95: =K95-J95 -> 0 | M95: =SUMIFS(JU!$H$696:$H$1062,JU!$F$696:$F$1062,$A95) -> 0 | N95: =SUMIFS(JU!$K$696:$K$1062,JU!$I$696:$I$1062,WS!$A95) -> 0 | O95: =N95-M95 -> 0 | P95: =SUMIFS(JU!$H$1063:$H$5007,JU!$F$1063:$F$5007,WS!$A95) -> 0 | Q95: =SUMIFS(JU!$K$1063:$K$5007,JU!$I$1063:$I$5007,WS!$A95) -> 0 | R95: =Q95-P95 -> 0 | S95: =SUMIFS(JU!$H$5107:$H$5107,JU!$F$5107:$F$5107,WS!$A95) -> 0 | T95: =SUMIFS(JU!$K$5107:$K$5107,JU!$I$5107:$I$5107,WS!$A95) -> 0 | U95: =T95-S95 -> 0 | V95: =SUMIFS(JU!$H$5107:$H$5107,JU!$F$5107:$F$5107,WS!$A95) -> 0 | W95: =SUMIFS(JU!$K$5107:$K$5107,JU!$I$5107:$I$5107,WS!$A95) -> 0 | X95: =W95-V95 -> 0 | Y95: =SUMIFS(JU!$H$5107:$H$5107,JU!$F$5107:$F$5107,WS!$A95) -> 0 | Z95: =SUMIFS(JU!$K$5107:$K$5107,JU!$I$5107:$I$5107,WS!$A95) -> 0 | AA95: =Z95-Y95 -> 0 | AB95: =SUMIFS(JU!$H$5107:$H$5107,JU!$F$5107:$F$5107,WS!$A95) -> 0 | AC95: =SUMIFS(JU!$K$5107:$K$5107,JU!$I$5107:$I$5107,WS!$A95) -> 0 | AD95: =AC95-AB95 -> 0 | AE95: =SUMIFS(JU!$H$5107:$H$5107,JU!$F$5107:$F$5107,WS!$A95) -> 0 | AF95: =SUMIFS(JU!$K$5107:$K$5107,JU!$I$5107:$I$5107,WS!$A95) -> 0 | AG95: =AF95-AE95 -> 0 | AH95: =SUMIFS(JU!$H$5107:$H$5107,JU!$F$5107:$F$5107,WS!$A95) -> 0 | AI95: =SUMIFS(JU!$K$5107:$K$5107,JU!$I$5107:$I$5107,WS!$A95) -> 0 | AJ95: =AI95-AH95 -> 0 | AK95: =SUMIFS(JU!$H$5107:$H$5107,JU!$F$5107:$F$5107,WS!$A95) -> 0 | AL95: =SUMIFS(JU!$K$5107:$K$5107,JU!$I$5107:$I$5107,WS!$A95) -> 0 | AM95: =AL95-AK95 -> 0 | AN95: =F95+I95+L95+O95+R95+U95+X95+AA95+AD95+AG95+AJ95+AM95 -> 0 | AP95: =AG95+AD95+AA95+X95+U95+R95+O95+L95+I95+F95 -> 0
A96: 4204 | B96: Pendapatan Lainnya | D96: =SUMIFS(JU!$H$5:$H$178,JU!$F$5:$F$178,WS!$A96) -> 0 | E96: =SUMIFS(JU!$K$5:$K$178,JU!$I$5:$I$178,WS!$A96) -> 0 | F96: =E96-D96 -> 0 | G96: =SUMIFS(JU!$H$180:$H$440,JU!$F$180:$F$440,WS!$A96) -> 0 | H96: =SUMIFS(JU!$K$180:$K$440,JU!$I$180:$I$440,WS!$A96) -> 0 | I96: =H96-G96 -> 0 | J96: =SUMIFS(JU!$H$441:$H$695,JU!$F$441:$F$695,WS!$A96) -> 0 | K96: =SUMIFS(JU!$K$441:$K$695,JU!$I$441:$I$695,WS!$A96) -> 253029 | L96: =K96-J96 -> 253029 | M96: =SUMIFS(JU!$H$696:$H$1062,JU!$F$696:$F$1062,$A96) -> 0 | N96: =SUMIFS(JU!$K$696:$K$1062,JU!$I$696:$I$1062,WS!$A96) -> 454254 | O96: =N96-M96 -> 454254 | P96: =SUMIFS(JU!$H$1063:$H$5007,JU!$F$1063:$F$5007,WS!$A96) -> 0 | Q96: =SUMIFS(JU!$K$1063:$K$5007,JU!$I$1063:$I$5007,WS!$A96) -> 0 | R96: =Q96-P96 -> 0 | S96: =SUMIFS(JU!$H$5107:$H$5107,JU!$F$5107:$F$5107,WS!$A96) -> 0 | T96: =SUMIFS(JU!$K$5107:$K$5107,JU!$I$5107:$I$5107,WS!$A96) -> 0 | U96: =T96-S96 -> 0 | V96: =SUMIFS(JU!$H$5107:$H$5107,JU!$F$5107:$F$5107,WS!$A96) -> 0 | W96: =SUMIFS(JU!$K$5107:$K$5107,JU!$I$5107:$I$5107,WS!$A96) -> 0 | X96: =W96-V96 -> 0 | Y96: =SUMIFS(JU!$H$5107:$H$5107,JU!$F$5107:$F$5107,WS!$A96) -> 0 | Z96: =SUMIFS(JU!$K$5107:$K$5107,JU!$I$5107:$I$5107,WS!$A96) -> 0 | AA96: =Z96-Y96 -> 0 | AB96: =SUMIFS(JU!$H$5107:$H$5107,JU!$F$5107:$F$5107,WS!$A96) -> 0 | AC96: =SUMIFS(JU!$K$5107:$K$5107,JU!$I$5107:$I$5107,WS!$A96) -> 0 | AD96: =AC96-AB96 -> 0 | AE96: =SUMIFS(JU!$H$5107:$H$5107,JU!$F$5107:$F$5107,WS!$A96) -> 0 | AF96: =SUMIFS(JU!$K$5107:$K$5107,JU!$I$5107:$I$5107,WS!$A96) -> 0 | AG96: =AF96-AE96 -> 0 | AH96: =SUMIFS(JU!$H$5107:$H$5107,JU!$F$5107:$F$5107,WS!$A96) -> 0 | AI96: =SUMIFS(JU!$K$5107:$K$5107,JU!$I$5107:$I$5107,WS!$A96) -> 0 | AJ96: =AI96-AH96 -> 0 | AK96: =SUMIFS(JU!$H$5107:$H$5107,JU!$F$5107:$F$5107,WS!$A96) -> 0 | AL96: =SUMIFS(JU!$K$5107:$K$5107,JU!$I$5107:$I$5107,WS!$A96) -> 0 | AM96: =AL96-AK96 -> 0 | AN96: =F96+I96+L96+O96+R96+U96+X96+AA96+AD96+AG96+AJ96+AM96 -> 707283 | AP96: =AG96+AD96+AA96+X96+U96+R96+O96+L96+I96+F96 -> 707283
A97: 4205 | B97: Pendapatan Investasi | D97: =SUMIFS(JU!$H$5:$H$178,JU!$F$5:$F$178,WS!$A97) -> 0 | E97: =SUMIFS(JU!$K$5:$K$178,JU!$I$5:$I$178,WS!$A97) -> 0 | F97: =E97-D97 -> 0 | G97: =SUMIFS(JU!$H$180:$H$440,JU!$F$180:$F$440,WS!$A97) -> 0 | H97: =SUMIFS(JU!$K$180:$K$440,JU!$I$180:$I$440,WS!$A97) -> 0 | I97: =H97-G97 -> 0 | J97: =SUMIFS(JU!$H$441:$H$695,JU!$F$441:$F$695,WS!$A97) -> 0 | K97: =SUMIFS(JU!$K$441:$K$695,JU!$I$441:$I$695,WS!$A97) -> 0 | L97: =K97-J97 -> 0 | M97: =SUMIFS(JU!$H$696:$H$1062,JU!$F$696:$F$1062,$A97) -> 0 | N97: =SUMIFS(JU!$K$696:$K$1062,JU!$I$696:$I$1062,WS!$A97) -> 0 | O97: =N97-M97 -> 0 | P97: =SUMIFS(JU!$H$1063:$H$5007,JU!$F$1063:$F$5007,WS!$A97) -> 0 | Q97: =SUMIFS(JU!$K$1063:$K$5007,JU!$I$1063:$I$5007,WS!$A97) -> 0 | R97: =Q97-P97 -> 0 | S97: =SUMIFS(JU!$H$5107:$H$5107,JU!$F$5107:$F$5107,WS!$A97) -> 0 | T97: =SUMIFS(JU!$K$5107:$K$5107,JU!$I$5107:$I$5107,WS!$A97) -> 0 | U97: =T97-S97 -> 0 | V97: =SUMIFS(JU!$H$5107:$H$5107,JU!$F$5107:$F$5107,WS!$A97) -> 0 | W97: =SUMIFS(JU!$K$5107:$K$5107,JU!$I$5107:$I$5107,WS!$A97) -> 0 | X97: =W97-V97 -> 0 | Y97: =SUMIFS(JU!$H$5107:$H$5107,JU!$F$5107:$F$5107,WS!$A97) -> 0 | Z97: =SUMIFS(JU!$K$5107:$K$5107,JU!$I$5107:$I$5107,WS!$A97) -> 0 | AA97: =Z97-Y97 -> 0 | AB97: =SUMIFS(JU!$H$5107:$H$5107,JU!$F$5107:$F$5107,WS!$A97) -> 0 | AC97: =SUMIFS(JU!$K$5107:$K$5107,JU!$I$5107:$I$5107,WS!$A97) -> 0 | AD97: =AC97-AB97 -> 0 | AE97: =SUMIFS(JU!$H$5107:$H$5107,JU!$F$5107:$F$5107,WS!$A97) -> 0 | AF97: =SUMIFS(JU!$K$5107:$K$5107,JU!$I$5107:$I$5107,WS!$A97) -> 0 | AG97: =AF97-AE97 -> 0 | AH97: =SUMIFS(JU!$H$5107:$H$5107,JU!$F$5107:$F$5107,WS!$A97) -> 0 | AI97: =SUMIFS(JU!$K$5107:$K$5107,JU!$I$5107:$I$5107,WS!$A97) -> 0 | AJ97: =AI97-AH97 -> 0 | AK97: =SUMIFS(JU!$H$5107:$H$5107,JU!$F$5107:$F$5107,WS!$A97) -> 0 | AL97: =SUMIFS(JU!$K$5107:$K$5107,JU!$I$5107:$I$5107,WS!$A97) -> 0 | AM97: =AL97-AK97 -> 0 | AN97: =F97+I97+L97+O97+R97+U97+X97+AA97+AD97+AG97+AJ97+AM97 -> 0 | AP97: =AG97+AD97+AA97+X97+U97+R97+O97+L97+I97+F97 -> 0
A98: 4206 | B98: Pendapatan Non-Operasional | D98: =SUMIFS(JU!$H$5:$H$178,JU!$F$5:$F$178,WS!$A98) -> 0 | E98: =SUMIFS(JU!$K$5:$K$178,JU!$I$5:$I$178,WS!$A98) -> 0 | F98: =E98-D98 -> 0 | G98: =SUMIFS(JU!$H$180:$H$440,JU!$F$180:$F$440,WS!$A98) -> 0 | H98: =SUMIFS(JU!$K$180:$K$440,JU!$I$180:$I$440,WS!$A98) -> 0 | I98: =H98-G98 -> 0 | J98: =SUMIFS(JU!$H$441:$H$695,JU!$F$441:$F$695,WS!$A98) -> 0 | K98: =SUMIFS(JU!$K$441:$K$695,JU!$I$441:$I$695,WS!$A98) -> 0 | L98: =K98-J98 -> 0 | M98: =SUMIFS(JU!$H$696:$H$1062,JU!$F$696:$F$1062,$A98) -> 0 | N98: =SUMIFS(JU!$K$696:$K$1062,JU!$I$696:$I$1062,WS!$A98) -> 0 | O98: =N98-M98 -> 0 | P98: =SUMIFS(JU!$H$1063:$H$5007,JU!$F$1063:$F$5007,WS!$A98) -> 0 | Q98: =SUMIFS(JU!$K$1063:$K$5007,JU!$I$1063:$I$5007,WS!$A98) -> 0 | R98: =Q98-P98 -> 0 | S98: =SUMIFS(JU!$H$5107:$H$5107,JU!$F$5107:$F$5107,WS!$A98) -> 0 | T98: =SUMIFS(JU!$K$5107:$K$5107,JU!$I$5107:$I$5107,WS!$A98) -> 0 | U98: =T98-S98 -> 0 | V98: =SUMIFS(JU!$H$5107:$H$5107,JU!$F$5107:$F$5107,WS!$A98) -> 0 | W98: =SUMIFS(JU!$K$5107:$K$5107,JU!$I$5107:$I$5107,WS!$A98) -> 0 | X98: =W98-V98 -> 0 | Y98: =SUMIFS(JU!$H$5107:$H$5107,JU!$F$5107:$F$5107,WS!$A98) -> 0 | Z98: =SUMIFS(JU!$K$5107:$K$5107,JU!$I$5107:$I$5107,WS!$A98) -> 0 | AA98: =Z98-Y98 -> 0 | AB98: =SUMIFS(JU!$H$5107:$H$5107,JU!$F$5107:$F$5107,WS!$A98) -> 0 | AC98: =SUMIFS(JU!$K$5107:$K$5107,JU!$I$5107:$I$5107,WS!$A98) -> 0 | AD98: =AC98-AB98 -> 0 | AE98: =SUMIFS(JU!$H$5107:$H$5107,JU!$F$5107:$F$5107,WS!$A98) -> 0 | AF98: =SUMIFS(JU!$K$5107:$K$5107,JU!$I$5107:$I$5107,WS!$A98) -> 0 | AG98: =AF98-AE98 -> 0 | AH98: =SUMIFS(JU!$H$5107:$H$5107,JU!$F$5107:$F$5107,WS!$A98) -> 0 | AI98: =SUMIFS(JU!$K$5107:$K$5107,JU!$I$5107:$I$5107,WS!$A98) -> 0 | AJ98: =AI98-AH98 -> 0 | AK98: =SUMIFS(JU!$H$5107:$H$5107,JU!$F$5107:$F$5107,WS!$A98) -> 0 | AL98: =SUMIFS(JU!$K$5107:$K$5107,JU!$I$5107:$I$5107,WS!$A98) -> 0 | AM98: =AL98-AK98 -> 0 | AN98: =F98+I98+L98+O98+R98+U98+X98+AA98+AD98+AG98+AJ98+AM98 -> 0 | AP98: =AG98+AD98+AA98+X98+U98+R98+O98+L98+I98+F98 -> 0
A99: Total Pendapatan Lain-Lain | C99: =SUM(C93:C98) -> 0 | D99: =SUMIFS(JU!$H$5:$H$178,JU!$F$5:$F$178,WS!$A99) -> 0 | E99: =SUMIFS(JU!$K$5:$K$178,JU!$I$5:$I$178,WS!$A99) -> 0 | F99: =SUM(F93:F98) -> 0 | G99: =SUMIFS(JU!$H$180:$H$440,JU!$F$180:$F$440,WS!$A99) -> 0 | H99: =SUMIFS(JU!$K$180:$K$440,JU!$I$180:$I$440,WS!$A99) -> 0 | I99: =SUM(I93:I98) -> 293644 | J99: =SUMIFS(JU!$H$441:$H$695,JU!$F$441:$F$695,WS!$A99) -> 0 | K99: =SUMIFS(JU!$K$441:$K$695,JU!$I$441:$I$695,WS!$A99) -> 0 | L99: =SUM(L93:L98) -> 253029 | M99: =SUMIFS(JU!$H$696:$H$1062,JU!$F$696:$F$1062,$A99) -> 0 | N99: =SUMIFS(JU!$K$696:$K$1062,JU!$I$696:$I$1062,WS!$A99) -> 0 | O99: =SUM(O93:O98) -> 454254 | P99: =SUMIFS(JU!$H$1063:$H$5007,JU!$F$1063:$F$5007,WS!$A99) -> 0 | Q99: =SUMIFS(JU!$K$1063:$K$5007,JU!$I$1063:$I$5007,WS!$A99) -> 0 | R99: =SUM(R93:R98) -> 0 | S99: =SUMIFS(JU!$H$5107:$H$5107,JU!$F$5107:$F$5107,WS!$A99) -> 0 | T99: =SUMIFS(JU!$K$5107:$K$5107,JU!$I$5107:$I$5107,WS!$A99) -> 0 | U99: =SUM(U93:U98) -> 0 | V99: =SUMIFS(JU!$H$5107:$H$5107,JU!$F$5107:$F$5107,WS!$A99) -> 0 | W99: =SUMIFS(JU!$K$5107:$K$5107,JU!$I$5107:$I$5107,WS!$A99) -> 0 | X99: =SUM(X93:X98) -> 0 | Y99: =SUMIFS(JU!$H$5107:$H$5107,JU!$F$5107:$F$5107,WS!$A99) -> 0 | Z99: =SUMIFS(JU!$K$5107:$K$5107,JU!$I$5107:$I$5107,WS!$A99) -> 0 | AA99: =SUM(AA93:AA98) -> 0 | AB99: =SUMIFS(JU!$H$5107:$H$5107,JU!$F$5107:$F$5107,WS!$A99) -> 0 | AC99: =SUMIFS(JU!$K$5107:$K$5107,JU!$I$5107:$I$5107,WS!$A99) -> 0 | AD99: =SUM(AD93:AD98) -> 0 | AE99: =SUMIFS(JU!$H$5107:$H$5107,JU!$F$5107:$F$5107,WS!$A99) -> 0 | AF99: =SUMIFS(JU!$K$5107:$K$5107,JU!$I$5107:$I$5107,WS!$A99) -> 0 | AG99: =SUM(AG93:AG98) -> 0 | AH99: =SUMIFS(JU!$H$5107:$H$5107,JU!$F$5107:$F$5107,WS!$A99) -> 0 | AI99: =SUMIFS(JU!$K$5107:$K$5107,JU!$I$5107:$I$5107,WS!$A99) -> 0 | AJ99: =SUM(AJ93:AJ98) -> 0 | AK99: =SUMIFS(JU!$H$5107:$H$5107,JU!$F$5107:$F$5107,WS!$A99) -> 0 | AL99: =SUMIFS(JU!$K$5107:$K$5107,JU!$I$5107:$I$5107,WS!$A99) -> 0 | AM99: =SUM(AM93:AM98) -> 0 | AN99: =F99+I99+L99+O99+R99+U99+X99+AA99+AD99+AG99+AJ99+AM99 -> 1000927 | AP99: =AG99+AD99+AA99+X99+U99+R99+O99+L99+I99+F99 -> 1000927
A100: Total Pendapatan | C100: =C91+C99 -> 0 | D100: =SUMIFS(JU!$H$5:$H$178,JU!$F$5:$F$178,WS!$A100) -> 0 | E100: =SUMIFS(JU!$K$5:$K$178,JU!$I$5:$I$178,WS!$A100) -> 0 | F100: =F91+F99 -> 119000000 | G100: =SUMIFS(JU!$H$180:$H$440,JU!$F$180:$F$440,WS!$A100) -> 0 | H100: =SUMIFS(JU!$K$180:$K$440,JU!$I$180:$I$440,WS!$A100) -> 0 | I100: =I91+I99 -> 793693644 | J100: =SUMIFS(JU!$H$441:$H$695,JU!$F$441:$F$695,WS!$A100) -> 0 | K100: =SUMIFS(JU!$K$441:$K$695,JU!$I$441:$I$695,WS!$A100) -> 0 | L100: =L91+L99 -> 538253029 | M100: =SUMIFS(JU!$H$696:$H$1062,JU!$F$696:$F$1062,$A100) -> 0 | N100: =SUMIFS(JU!$K$696:$K$1062,JU!$I$696:$I$1062,WS!$A100) -> 0 | O100: =O91+O99 -> 2272354254 | P100: =SUMIFS(JU!$H$1063:$H$5007,JU!$F$1063:$F$5007,WS!$A100) -> 0 | Q100: =SUMIFS(JU!$K$1063:$K$5007,JU!$I$1063:$I$5007,WS!$A100) -> 0 | R100: =R91+R99 -> 3157600000 | S100: =SUMIFS(JU!$H$5107:$H$5107,JU!$F$5107:$F$5107,WS!$A100) -> 0 | T100: =SUMIFS(JU!$K$5107:$K$5107,JU!$I$5107:$I$5107,WS!$A100) -> 0 | U100: =U91+U99 -> 0 | V100: =SUMIFS(JU!$H$5107:$H$5107,JU!$F$5107:$F$5107,WS!$A100) -> 0 | W100: =SUMIFS(JU!$K$5107:$K$5107,JU!$I$5107:$I$5107,WS!$A100) -> 0 | X100: =X91+X99 -> 0 | Y100: =SUMIFS(JU!$H$5107:$H$5107,JU!$F$5107:$F$5107,WS!$A100) -> 0 | Z100: =SUMIFS(JU!$K$5107:$K$5107,JU!$I$5107:$I$5107,WS!$A100) -> 0 | AA100: =AA91+AA99 -> 0 | AB100: =SUMIFS(JU!$H$5107:$H$5107,JU!$F$5107:$F$5107,WS!$A100) -> 0 | AC100: =SUMIFS(JU!$K$5107:$K$5107,JU!$I$5107:$I$5107,WS!$A100) -> 0 | AD100: =AD91+AD99 -> 0 | AE100: =SUMIFS(JU!$H$5107:$H$5107,JU!$F$5107:$F$5107,WS!$A100) -> 0 | AF100: =SUMIFS(JU!$K$5107:$K$5107,JU!$I$5107:$I$5107,WS!$A100) -> 0 | AG100: =AG91+AG99 -> 0 | AH100: =SUMIFS(JU!$H$5107:$H$5107,JU!$F$5107:$F$5107,WS!$A100) -> 0 | AI100: =SUMIFS(JU!$K$5107:$K$5107,JU!$I$5107:$I$5107,WS!$A100) -> 0 | AJ100: =AJ91+AJ99 -> 0 | AK100: =SUMIFS(JU!$H$5107:$H$5107,JU!$F$5107:$F$5107,WS!$A100) -> 0 | AL100: =SUMIFS(JU!$K$5107:$K$5107,JU!$I$5107:$I$5107,WS!$A100) -> 0 | AM100: =AM91+AM99 -> 0 | AN100: =F100+I100+L100+O100+R100+U100+X100+AA100+AD100+AG100+AJ100+AM100 -> 6880900927 | AP100: =AG100+AD100+AA100+X100+U100+R100+O100+L100+I100+F100 -> 6880900927
A101: Harga Pokok Penjualan | D101: =SUMIFS(JU!$H$5:$H$178,JU!$F$5:$F$178,WS!$A101) -> 0 | E101: =SUMIFS(JU!$K$5:$K$178,JU!$I$5:$I$178,WS!$A101) -> 0 | G101: =SUMIFS(JU!$H$180:$H$440,JU!$F$180:$F$440,WS!$A101) -> 0 | H101: =SUMIFS(JU!$K$180:$K$440,JU!$I$180:$I$440,WS!$A101) -> 0 | J101: =SUMIFS(JU!$H$441:$H$695,JU!$F$441:$F$695,WS!$A101) -> 0 | K101: =SUMIFS(JU!$K$441:$K$695,JU!$I$441:$I$695,WS!$A101) -> 0 | M101: =SUMIFS(JU!$H$696:$H$1062,JU!$F$696:$F$1062,$A101) -> 0 | N101: =SUMIFS(JU!$K$696:$K$1062,JU!$I$696:$I$1062,WS!$A101) -> 0 | P101: =SUMIFS(JU!$H$1063:$H$5007,JU!$F$1063:$F$5007,WS!$A101) -> 0 | Q101: =SUMIFS(JU!$K$1063:$K$5007,JU!$I$1063:$I$5007,WS!$A101) -> 0 | S101: =SUMIFS(JU!$H$5107:$H$5107,JU!$F$5107:$F$5107,WS!$A101) -> 0 | T101: =SUMIFS(JU!$K$5107:$K$5107,JU!$I$5107:$I$5107,WS!$A101) -> 0 | V101: =SUMIFS(JU!$H$5107:$H$5107,JU!$F$5107:$F$5107,WS!$A101) -> 0 | W101: =SUMIFS(JU!$K$5107:$K$5107,JU!$I$5107:$I$5107,WS!$A101) -> 0 | Y101: =SUMIFS(JU!$H$5107:$H$5107,JU!$F$5107:$F$5107,WS!$A101) -> 0 | Z101: =SUMIFS(JU!$K$5107:$K$5107,JU!$I$5107:$I$5107,WS!$A101) -> 0 | AB101: =SUMIFS(JU!$H$5107:$H$5107,JU!$F$5107:$F$5107,WS!$A101) -> 0 | AC101: =SUMIFS(JU!$K$5107:$K$5107,JU!$I$5107:$I$5107,WS!$A101) -> 0 | AE101: =SUMIFS(JU!$H$5107:$H$5107,JU!$F$5107:$F$5107,WS!$A101) -> 0 | AF101: =SUMIFS(JU!$K$5107:$K$5107,JU!$I$5107:$I$5107,WS!$A101) -> 0 | AH101: =SUMIFS(JU!$H$5107:$H$5107,JU!$F$5107:$F$5107,WS!$A101) -> 0 | AI101: =SUMIFS(JU!$K$5107:$K$5107,JU!$I$5107:$I$5107,WS!$A101) -> 0 | AK101: =SUMIFS(JU!$H$5107:$H$5107,JU!$F$5107:$F$5107,WS!$A101) -> 0 | AL101: =SUMIFS(JU!$K$5107:$K$5107,JU!$I$5107:$I$5107,WS!$A101) -> 0 | AN101: =F101+I101+L101+O101+R101+U101+X101+AA101+AD101+AG101+AJ101+AM101 -> 0 | AP101: =AG101+AD101+AA101+X101+U101+R101+O101+L101+I101+F101 -> 0
...

Sheet JU
D1: 16 Pencairan dan 5 belum ketemu pencairannya (D5, D18, D21, E2, E10). 12 sdh pencairan dan penebusan/adj (4 diluar itu Bank Lain tdk ke tracking penebusan sertif D1-D4), (2 exc belum pencairan
B2: Tanggal | C2: Ref | D2: Keterangan | F2: Debet | I2: Kredit
F3: No Akun | G3: Nama Akun | H3: Jumlah | I3: No Akun | J3: Nama Akun | K3: Jumlah
B5: 46023 | D5: Reklas Terima Pendapatan BIAYA AKAD SAHRUL C34 SN2 | F5: =IF(G5="","",INDEX(COA!$A$4:$A$123,MATCH(JU!$G5,COA!$B$4:$B$123,0))) -> 2204 | G5: Hutang Afiliasi | H5: 15000000 | I5: =IF(J5="","",INDEX(COA!$A$4:$A$123,MATCH(JU!$J5,COA!$B$4:$B$123,0))) -> 4102 | J5: Pendapatan Penjualan Rumah | K5: =IF(H5="","",H5) -> 15000000
B6: 46023 | D6: Reklas By. Biaya BIAYA AKAD SN2 (PINJAM ARYA) | F6: =IF(G6="","",INDEX(COA!$A$4:$A$123,MATCH(JU!$G6,COA!$B$4:$B$123,0))) -> 4102 | G6: Pendapatan Penjualan Rumah | H6: 55000000 | I6: =IF(J6="","",INDEX(COA!$A$4:$A$123,MATCH(JU!$J6,COA!$B$4:$B$123,0))) -> 2204 | J6: Hutang Afiliasi | K6: =IF(H6="","",H6) -> 55000000
B7: 46023 | D7: Reklas By. Biaya SISA DP SN2 (PINJAM ARYA) | F7: =IF(G7="","",INDEX(COA!$A$4:$A$123,MATCH(JU!$G7,COA!$B$4:$B$123,0))) -> 4102 | G7: Pendapatan Penjualan Rumah | H7: 8000000 | I7: =IF(J7="","",INDEX(COA!$A$4:$A$123,MATCH(JU!$J7,COA!$B$4:$B$123,0))) -> 2204 | J7: Hutang Afiliasi | K7: =IF(H7="","",H7) -> 8000000
A9: =IF(G9="BRI 568","Terima Uang Masuk atas ","By. Biaya ") -> Terima Uang Masuk atas | B9: 46023 | D9: Terima Uang Masuk atas | F9: =IF(G9="","",INDEX(COA!$A$4:$A$123,MATCH(JU!$G9,COA!$B$4:$B$123,0))) -> 1103 | G9: BRI 568 | H9: 100000000 | I9: =IF(J9="","",INDEX(COA!$A$4:$A$123,MATCH(JU!$J9,COA!$B$4:$B$123,0))) -> 1202 | J9: Piutang Usaha | K9: =IF(H9="","",H9) -> 100000000
A10: =IF(G10="BRI 568","Terima Uang Masuk atas ","By. Biaya ") -> Terima Uang Masuk atas | B10: 46023 | D10: Terima Uang Masuk atas | F10: =IF(G10="","",INDEX(COA!$A$4:$A$123,MATCH(JU!$G10,COA!$B$4:$B$123,0))) -> 1103 | G10: BRI 568 | H10: 100000000 | I10: =IF(J10="","",INDEX(COA!$A$4:$A$123,MATCH(JU!$J10,COA!$B$4:$B$123,0))) -> 1202 | J10: Piutang Usaha | K10: =IF(H10="","",H10) -> 100000000
A11: =IF(G11="BRI 568","Terima Uang Masuk atas ","By. Biaya ") -> Terima Uang Masuk atas | B11: 46023 | D11: Terima Uang Masuk atas | F11: =IF(G11="","",INDEX(COA!$A$4:$A$123,MATCH(JU!$G11,COA!$B$4:$B$123,0))) -> 1103 | G11: BRI 568 | H11: 50000000 | I11: =IF(J11="","",INDEX(COA!$A$4:$A$123,MATCH(JU!$J11,COA!$B$4:$B$123,0))) -> 1202 | J11: Piutang Usaha | K11: =IF(H11="","",H11) -> 50000000
A12: =IF(G12="BRI 568","Terima Uang Masuk atas ","By. Biaya ") -> By. Biaya | B12: 46023 | C12: GAJI BULAN DESEMBER | D12: By. Biaya GAJI BULAN DESEMBER | F12: =IF(G12="","",INDEX(COA!$A$4:$A$123,MATCH(JU!$G12,COA!$B$4:$B$123,0))) -> 6101 | G12: Gaji & Tunjangan | H12: 18850000 | I12: =IF(J12="","",INDEX(COA!$A$4:$A$123,MATCH(JU!$J12,COA!$B$4:$B$123,0))) -> 1103 | J12: BRI 568 | K12: =IF(H12="","",H12) -> 18850000
A13: =IF(G13="BRI 568","Terima Uang Masuk atas ","By. Biaya ") -> By. Biaya | B13: 46023 | C13: GAJI DESEMBER SHINTA | D13: By. Biaya GAJI DESEMBER SHINTA | F13: =IF(G13="","",INDEX(COA!$A$4:$A$123,MATCH(JU!$G13,COA!$B$4:$B$123,0))) -> 6101 | G13: Gaji & Tunjangan | H13: 1700000 | I13: =IF(J13="","",INDEX(COA!$A$4:$A$123,MATCH(JU!$J13,COA!$B$4:$B$123,0))) -> 1103 | J13: BRI 568 | K13: =IF(H13="","",H13) -> 1700000
A14: =IF(G14="BRI 568","Terima Uang Masuk atas ","By. Biaya ") -> By. Biaya | B14: 46023 | C14: PENJAGA ALAT DAN SECURITY | D14: By. Biaya PENJAGA ALAT DAN SECURITY | F14: =IF(G14="","",INDEX(COA!$A$4:$A$123,MATCH(JU!$G14,COA!$B$4:$B$123,0))) -> 6101 | G14: Gaji & Tunjangan | H14: 7000000 | I14: =IF(J14="","",INDEX(COA!$A$4:$A$123,MATCH(JU!$J14,COA!$B$4:$B$123,0))) -> 1103 | J14: BRI 568 | K14: =IF(H14="","",H14) -> 7000000
A15: =IF(G15="BRI 568","Terima Uang Masuk atas ","By. Biaya ") -> By. Biaya | B15: 46023 | C15: GAJI DESEMBER PAK DIRUT | D15: By. Biaya GAJI DESEMBER PAK DIRUT | F15: =IF(G15="","",INDEX(COA!$A$4:$A$123,MATCH(JU!$G15,COA!$B$4:$B$123,0))) -> 6101 | G15: Gaji & Tunjangan | H15: 5000000 | I15: =IF(J15="","",INDEX(COA!$A$4:$A$123,MATCH(JU!$J15,COA!$B$4:$B$123,0))) -> 1103 | J15: BRI 568 | K15: =IF(H15="","",H15) -> 5000000
A16: =IF(G16="BRI 568","Terima Uang Masuk atas ","By. Biaya ") -> By. Biaya | B16: 46023 | C16: ADMIN BANK | D16: By. Biaya ADMIN BANK | F16: =IF(G16="","",INDEX(COA!$A$4:$A$123,MATCH(JU!$G16,COA!$B$4:$B$123,0))) -> 6303 | G16: Beban Bank & Administrasi Keuangan | H16: 6500 | I16: =IF(J16="","",INDEX(COA!$A$4:$A$123,MATCH(JU!$J16,COA!$B$4:$B$123,0))) -> 1103 | J16: BRI 568 | K16: =IF(H16="","",H16) -> 6500
A17: =IF(G17="BRI 568","Terima Uang Masuk atas ","By. Biaya ") -> By. Biaya | B17: 46023 | C17: KONSTIBUSI WAJIB SATARA | D17: By. Biaya KONSTIBUSI WAJIB SATARA | F17: =IF(G17="","",INDEX(COA!$A$4:$A$123,MATCH(JU!$G17,COA!$B$4:$B$123,0))) -> 6111 | G17: Biaya Pihak Afiliasi | H17: 30000000 | I17: =IF(J17="","",INDEX(COA!$A$4:$A$123,MATCH(JU!$J17,COA!$B$4:$B$123,0))) -> 1103 | J17: BRI 568 | K17: =IF(H17="","",H17) -> 30000000
A18: =IF(G18="BRI 568","Terima Uang Masuk atas ","By. Biaya ") -> By. Biaya | B18: 46023 | C18: ADMIN BANK | D18: By. Biaya ADMIN BANK | F18: =IF(G18="","",INDEX(COA!$A$4:$A$123,MATCH(JU!$G18,COA!$B$4:$B$123,0))) -> 6303 | G18: Beban Bank & Administrasi Keuangan | H18: 6500 | I18: =IF(J18="","",INDEX(COA!$A$4:$A$123,MATCH(JU!$J18,COA!$B$4:$B$123,0))) -> 1103 | J18: BRI 568 | K18: =IF(H18="","",H18) -> 6500
A19: =IF(G19="BRI 568","Terima Uang Masuk atas ","By. Biaya ") -> By. Biaya | B19: 46023 | C19: FEE AKAD C14, C20 TAHAP 2 | D19: By. Biaya FEE AKAD C14, C20 TAHAP 2 | F19: =IF(G19="","",INDEX(COA!$A$4:$A$123,MATCH(JU!$G19,COA!$B$4:$B$123,0))) -> 5109 | G19: Biaya Promosi Penjualan (yang dikapitalisasi) | H19: 2000000 | I19: =IF(J19="","",INDEX(COA!$A$4:$A$123,MATCH(JU!$J19,COA!$B$4:$B$123,0))) -> 1103 | J19: BRI 568 | K19: =IF(H19="","",H19) -> 2000000
